Workbook
Name ______new1: #REF!
Name _____new2: #REF!
Name _____Tax1: [1]Particulars!$A$1:$X$39
Name ____DAT1: [2]rental!#REF!
Name ____DAT10: [2]rental!#REF!
Name ____DAT11: [2]rental!#REF!
Name ____DAT12: #REF!
Name ____DAT13: #REF!
Name ____DAT14: #REF!
Name ____DAT2: [2]rental!#REF!
Name ____DAT3: [2]rental!#REF!
Name ____DAT4: [2]rental!#REF!
Name ____DAT5: [2]rental!#REF!
Name ____DAT6: [2]rental!#REF!
Name ____DAT7: [2]rental!#REF!
Name ____DAT8: [2]rental!#REF!
Name ____DAT9: [2]rental!#REF!
Name ___DAT1: [2]rental!#REF!
Name ___DAT10: [2]rental!#REF!
Name ___DAT11: [2]rental!#REF!
Name ___DAT12: #REF!
Name ___DAT13: #REF!
Name ___DAT14: #REF!
Name ___DAT2: [2]rental!#REF!
Name ___DAT3: [2]rental!#REF!
Name ___DAT4: [2]rental!#REF!
Name ___DAT5: [2]rental!#REF!
Name ___DAT6: [2]rental!#REF!
Name ___DAT7: [2]rental!#REF!
Name ___DAT8: [2]rental!#REF!
Name ___DAT9: [2]rental!#REF!
Name ___mds_view_data___: '[4]SSC Hong Kong'!#REF!
Name ___new1: #REF!
Name ___new2: #REF!
Name ___tax1: #REF!
Name ___tax2: #REF!
Name __DAT1: [2]rental!#REF!
Name __DAT10: [2]rental!#REF!
Name __DAT11: [2]rental!#REF!
Name __DAT12: #REF!
Name __DAT13: #REF!
Name __DAT14: #REF!
Name __DAT15: #REF!
Name __DAT2: [2]rental!#REF!
Name __DAT3: [2]rental!#REF!
Name __DAT4: [2]rental!#REF!
Name __DAT5: [2]rental!#REF!
Name __DAT6: [2]rental!#REF!
Name __DAT7: [2]rental!#REF!
Name __DAT8: [2]rental!#REF!
Name __DAT9: [2]rental!#REF!
Name __new1: #REF!
Name __new2: #REF!
Name __TAX1: '[8]Lei Wang'!$M$11:$O$19
Name __tax2: #REF!
Name __tax3: #REF!
Name _1: #N/A
Name _2355: #REF!
Name _DAT1: [2]rental!#REF!
Name _DAT10: [2]rental!#REF!

Sheet Check Result
F1: 0 | K1: 1
A2: Batch Name | B2: Legal Entity | C2: Payroll Group | D2: WEIN | E2: Check | F2: Diff | G2: Legal Last Name | H2: Legal First Name | I2: Legal full name | J2: Check | K2: Diff | L2: Preferred Name | M2: Hire Status | N2: Last Hired Date | O2: Check | P2: Diff | Q2: Last Employment Date | R2: Check | S2: Diff | T2: Business Department | U2: Check | V2: Diff | W2: Department Code | X2: Position Title | Y2: Check | Z2: Diff | AA2: Employee Cost Center | AB2: Cost Center Code | AC2: Check | AD2: Diff | AE2: Period | AF2: Is Overseas Employee | AG2: Years of Service | AH2: Monthly Base Pay | AI2: Check | AJ2: Diff | AK2: Base Pay 60001000 | AL2: Check | AM2: Diff | AN2: Salary Adj 60001000 | AO2: Check | AP2: Diff | AQ2: Monthly Base Pay(Temp) | AR2: Check | AS2: Diff | AT2: Base Pay(Temp) 60101000 | AU2: Check | AV2: Diff | AW2: Salary Adj (Temp) 60101000 | AX2: Monthly Rental Reimbursement | AY2: Rental Reimbursement 60001000 | AZ2: Rental Reimbursement Adj 60001000 | BA2: Monthly Transport Allowance | BB2: Check | BC2: Diff | BD2: Transport Allowance 60409960 | BE2: Check | BF2: Diff | BG2: Transport Allowance Adj 60409960 | BH2: Check | BI2: Diff | BJ2: Monthly Housing Allowance | BK2: Housing Allowance 60409960 | BL2: Housing Allowance Adj 60409960 | BM2: Total EAO Adj 60409960 | BN2: Check | BO2: Diff | BP2: Maternity Leave Payment 60001000 | BQ2: Check | BR2: Diff | BS2: Paternity Leave payment adjustment | BT2: Paternity Leave Payment 60001000 | BU2: Adjustment of Parental Paid Time Off(PPTO)payment | BV2: Paid Parental Time Off (PPTO) payment | BW2: Check | BX2: Diff | BY2: Sick Leave Payment 60001000 | BZ2: Check | CA2: Diff | CB2: Overtime Payment 99999999 | CC2: Annual Incentive 60201000 | CD2: Check | CE2: Diff | CF2: Sales Incentive (Quantitative) 21201000 | CG2: Check | CH2: Diff | CI2: Sales Incentive (Qualitative) 21201000 | CJ2: Check | CK2: Diff | CL2: Inspire Cash 60702000 | CM2: Check | CN2: Diff | CO2: Inspire Points (Gross Up) 60701000 | CP2: Check | CQ2: Diff | CR2: Goods & Services Differential 60601000 | CS2: Shares Dividend 60204001 | CT2: Check | CU2: Diff | CV2: Red Packet 69001000 | CW2: Check | CX2: Diff | CY2: Year End Bonus 60208000 | CZ2: Check | DA2: Diff | DB2: Gratuity Bonus 60208000 | DC2: Lump Sum Bonus 60409960 | DD2: Check | DE2: Diff | DF2: Referral Bonus 69001000 | DG2: Check | DH2: Diff | DI2: Sign On Bonus 60409960 | DJ2: Check | DK2: Diff | DL2: Retention Bonus 60409960 | DM2: Check | DN2: Diff | DO2: Other Bonus 99999999 | DP2: Check | DQ2: Diff | DR2: Employee Award 60208000 | DS2: AP President Club 60208000 | DT2: Manager of the Year Award 60208000 | DU2: Check | DV2: Diff | DW2: MD Award 60208000 | DX2: Check | DY2: Diff | DZ2: Other Rewards 99999999 | EA2: Check | EB2: Diff | EC2: Other Allowance 60409960 | ED2: Check | EE2: Diff | EF2: Education Benefits 99999999 | EG2: Flexible benefits | EH2: Check | EI2: Diff | EJ2: Pensions 99999999 | EK2: Untaken Annual Leave Payment 60409960 | EL2: Check | EM2: Diff | EN2: PIL ER to EE 60001000 | EO2: Check | EP2: Diff | EQ2: Back Pay 99999999 | ER2: Check | ES2: Diff | ET2: Gratuities 99999999 | EU2: Check | EV2: Diff | EW2: Termination Payment 99999999 | EX2: SP or LSP | EY2: Severance Payment 60404000 | EZ2: Check | FA2: Diff | FB2: Long Service Payment 60409960 | FC2: Check | FD2: Diff | FE2: IA Pay Split | FF2: Check | FG2: Diff | FH2: MPF Relevant Income | FI2: Check | FJ2: Diff | FK2: MPF VC Relevant Income | FL2: Check | FM2: Diff | FN2: ORSO Relevant Income | FO2: Check | FP2: Diff | FQ2: Employees' Compensation 60409960 | FR2: Non-taxable Item 21271000 | FS2: Medical Claim 60409960 | FT2: (Blank) | FU2: Optional Group Upgrade 21351000 | FV2: Check | FW2: Diff | FX2: Hypo Tax 60601000 | FY2: IA Pay Split by Host 60601000 | FZ2: No Pay Leave Deduction 60001000 | GA2: Check | GB2: Diff | GC2: NoPayLeaveCalculationBase_LastMonth | GD2: Overtaken Annual Leave Deduct 60001000 | GE2: PIL EE to ER 60001000 | GF2: Check | GG2: Diff | GH2: MPF EE VC Percentage | GI2: Check | GJ2: Diff | GK2: MPF ER VC Percentage_Input | GL2: MPF ER VC Percentage | GM2: Check | GN2: Diff | GO2: Percent Of ORSO EE | GP2: Check | GQ2: Diff | GR2: Percent Of ORSO ER | GS2: Check | GT2: Diff | GU2: ORSO EE Contribution Rate | GV2: ORSO ER Contribution Rate | GW2: ORSO EE 60801000 | GX2: Check | GY2: Diff | GZ2: ORSO EE Adj | HA2: ORSO ER Adj | HB2: Check | HC2: Diff | HD2: ORSO ER 60801000 | HE2: Check | HF2: Diff | HG2: MPF EE MC 21251000 | HH2: Check | HI2: Diff | HJ2: MPF EE VC 21251000 | HK2: Check | HL2: Diff | HM2: MPF ER MC 60801000 | HN2: Check | HO2: Diff | HP2: MPF ER VC 60801000 | HQ2: Check | HR2: Diff | HS2: Net Pay Adj Positive 21011900 | HT2: Net Pay Adj Negative 21011900 | HU2: Net Pay 21011900 | HV2: (Blank2) | HW2: InspirePoints | HX2: Check | HY2: Diff | HZ2: ECO Income | IA2: Total ECO Income_Pre12Month(Include current month) | IB2: Severance Payment over cap | IC2: Long Service Payment over cap | ID2: Retire Scheme Payment 99999999 | IE2: Salaries Tax Paid by Employer 60601000 | IF2: Share Option 99999999 | IG2: Year End Bonus Accrual 60208000 | IH2: EAO Accrual 60409960 | II2: Days_balance for accrual | IJ2: AL Accrual Base_Rewrite | IK2: Annual Leave Accrual 60409960 | IL2: ORSO Admin Fee 60801000 | IM2: Gratuity Bonus_Rewrite | IN2: ExchangeRate | IO2: AP President Club (US Dollars) | IP2: EAO Gross Income | IQ2: EAO Gross OT | IR2: EAO Days | IS2: PPTO EAO Rate input | IT2: Check | IU2: Diff | IV2: Contract End Date(Temp EE) | IW2: YearEndBonusStore-Dec | IX2: YearEndBonusStore-Unpaid | IY2: YEB Special Start Date | IZ2: YEB Special End Date | JA2: YEB Special Base | JB2: Current Year Hire Begin Date | JC2: Current Year Hire End Date | JD2: CycleCutOffDate_LastMonth | JE2: CycleCutOffDate | JF2: Remark | JG2: Pre-Transition YOS | JH2: Post-Transition YOS | JI2: Pre-Transition SP/LSP | JJ2: Post-Transition SP/LSP | JK2: Long Service Payment_New
A3: MSD Asia202510 | B3: MERCK SHARP & DOHME (ASIA) LIMITED | C3: MSD Asia | D3: 77777777 | E3: 77777777 | F3: TRUE | I3: GGG GG | J3: GGG GGG | K3: FALSE | M3: Active | N3: 2022-04-11 | T3: CAS-HONG KONG | X3: Sr SPEC-Cons,Digital Activation,HHDDA-AP | JG3: 3.05 | JH3: 0.5 | JI3: 0 | JJ3: 0 | JK3: 0

Sheet HC Check
A3: Row Labels | B3: Count of WEIN | C3: Check
A4: Active | B4: 8 | C4: =B11-B12-C13+C15 -> 8
A5: Grand Total | B5: 8
B10: Jul | C10: Aug
A11: Payroll HC | B11: 10 | C11: =GETPIVOTDATA("WEIN",$A$3,"Hire Status","Active") -> 8
A12: Current Month Terminated HC(included) | B12: 0 | C12: 0
A13: Current Month Terminated HC(OC) | B13: 0 | C13: 2
A14: Previous Month Terminated HC(included) | B14: 0 | C14: 3
A15: Current Month New HC | B15: 0 | C15: 0

Sheet Feb for check
M1: Workforce_CurrentMonth | P1: Workforce_CurrentMonth | S1: Workforce_CurrentMonth | V1: Workforce_CurrentMonth | AB1: Workforce_CurrentMonth | AD1: 4EE change salary, rounding issue | AE1: Formula | AH1: Formula | AO1: Allowance_CurrentMonth | AR1: Formula | AY1: Andrew Monthly 40000 | BB1: =SUM(BB3:BB132)-SUM(#REF!) -> #REF! | BD1: =SUM(#REF!)-SUM(BD3:BD132) -> #REF! | BK1: Formula: roundup | BR1: Offline: one time | BT1: Offline: IA | BX1: Formula | CA1: Formula | CD1: Formula | CG1: Offline:upgrade | CP1: Formula | CR1: Formula | CT1: Formula | CW1: Formula | CZ1: Formula | DC1: Formula | DF1: Formula | DI1: Ofline: Inspire | DJ1: =SUM(DI3:DI132)-SUM(#REF!) -> #REF!
A2: Batch Name | B2: Legal Entity | C2: Payroll Group | D2: WEIN | E2: Check LastPR | F2: Legal Last Name | G2: Legal First Name | H2: Legal full name | I2: Check | J2: Diff | K2: Preferred Name | L2: Hire Status | M2: Last Hired Date | N2: Check WR | O2: Diff. | P2: Business Department | Q2: Check WR | R2: Diff | S2: Position Title | T2: Check WR - Business Title | U2: Diff | V2: Cost Center Code | W2: Check WR | X2: Diff | Y2: Period | Z2: Is Overseas Employee | AA2: Years of Service | AB2: Monthly Base Pay | AC2: Check | AD2: Diff | AE2: Base Pay 60001000 | AF2: Check | AG2: Diff | AH2: Salary Adj 60001000 | AI2: Check | AJ2: Diff | AK2: Monthly Base Pay(Temp) | AL2: Check | AM2: Diff | AN2: Base Pay(Temp) 60101000 | AO2: Monthly Transport Allowance | AP2: Check | AQ2: Diff | AR2: Transport Allowance 60409960 | AS2: Check | AT2: Diff | AU2: Transport Allowance Adj 60409960 | AV2: Check | AW2: Monthly Housing Allowance | AX2: Check | AY2: Housing Allowance 60409960 | AZ2: Check | BA2: Total EAO Adj 60409960 | BB2: AL Days_LastM | BC2: Annual Leave calculation base-EAO rate_LastM | BD2: AL Days_CurrentM | BE2: Annual Leave calculation base-EAO rate_CurrentM | BF2: Check | BG2: Diff | BH2: Maternity Leave Payment 60001000 | BI2: Check | BJ2: Diff | BK2: Inspire Points (Gross Up) 60701000 | BL2: Check | BM2: Diff. | BN2: Year End Bonus 60208000 | BO2: Probation Expired | BP2: Check | BQ2: Diff. | BR2: Referral Bonus 69001000 | BS2: Check | BT2: Other Allowance 60409960 | BU2: Check | BV2: IA Pay Split | BW2: Check | BX2: MPF Relevant Income | BY2: Check | BZ2: Diff. | CA2: MPF VC Relevant Income | CB2: Check | CC2: Diff. | CD2: ORSO Relevant Income | CE2: Check | CF2: Diff. | CG2: Optional Group Upgrade 21351000 | CH2: Check | CI2: NoPayLeaveCalculationBase_LastMonth | CJ2: MPF EE VC Percentage | CK2: Check | CL2: MPF ER VC Percentage_Input | CM2: MPF ER VC Percentage | CN2: Percent Of ORSO EE | CO2: Percent Of ORSO ER | CP2: ORSO EE 60801000 | CQ2: Check | CR2: ORSO ER 60801000 | CS2: Check | CT2: MPF EE MC 21251000 | CU2: Check | CV2: Diff. | CW2: MPF EE VC 21251000 | CX2: Check | CY2: Diff. | CZ2: MPF ER MC 60801000 | DA2: Check | DB2: Diff. | DC2: MPF ER VC 60801000 | DD2: Check | DE2: Diff. | DF2: Net Pay 21011900 | DG2: Check | DH2: Diff. | DI2: InspirePoints | DJ2: Check | DK2: Diff. | DL2: ECO Income | DM2: Total ECO Income_Pre12Month(Include current month) | DN2: Year End Bonus Accrual 60208000 | DO2: EAO Accrual 60409960 | DP2: ORSO Admin Fee 60801000 | DQ2: EAO Gross Income | DR2: EAO Days | DS2: YearEndBonusStore-Unpaid | DT2: Current Year Hire Begin Date | DU2: Current Year Hire End Date | DV2: CycleCutOffDate_LastMonth | DW2: CycleCutOffDate
A3: MSD Asia202502 | B3: MERCK SHARP & DOHME (ASIA) LIMITED | C3: MSD Asia | D3: 51509685 | E3: =VLOOKUP(D3,#REF!,1,0) -> #REF! | F3: Kei Fong | G3: Wu | H3: =G3&" "&F3 -> Wu Kei Fong | I3: =VLOOKUP(D3,#REF!,9,0) -> #REF! | J3: =I3=H3 -> #REF! | K3: Wu | L3: Active | M3: 2025-02-06 | N3: =VLOOKUP(D3,#REF!,80,0) -> #REF! | O3: =N3-M3 -> #REF! | P3: HK Macau Team (DS) | Q3: =VLOOKUP(D3,#REF!,50,0) -> #REF! | R3: =Q3=P3 -> #REF! | S3: Customer Rep., Sales GHH | T3: =VLOOKUP(D3,#REF!,21,0) -> #REF! | U3: =T3=S3 -> #REF! | V3: 12630105 | W3: =VLOOKUP(D3,#REF!,51,0) -> #REF! | X3: =W3=V3 -> #REF! | Y3: 202502 | Z3: N | AA3: 0.06 | AB3: 22000 | AC3: =ROUND(VLOOKUP(D3,#REF!,59,0),0) -> #REF! | AD3: =AC3-AB3 -> #REF! | AE3: 18071.43 | AF3: =AB3*23/28 -> 18071.429 | AG3: =AF3-AE3 -> -0.0014285714 | AH3: 0 | AK3: 0 | AN3: 0 | AO3: 2500 | AP3: =IFERROR(VLOOKUP('Feb for check'!D3,#REF!,15,0),0) -> 0 | AQ3: =AP3-AO3 -> -2500 | AR3: 2053.57 | AS3: =AO3*23/28 -> 2053.5714 | AT3: =AS3-AR3 -> 0.0014285714 | AU3: 0 | AW3: 0 | AY3: 0 | BA3: 0 | BB3: =IFERROR(VLOOKUP(D3,#REF!,2,0),0) -> 0 | BC3: =MAX(VLOOKUP(D3,#REF!,13,0)-VLOOKUP(D3,#REF!,14,0),0) -> #REF! | BD3: =IFERROR(VLOOKUP(D3,#REF!,3,0),0) -> 0 | BE3: =MAX(VLOOKUP(D3,#REF!,22,0)-VLOOKUP(D3,#REF!,23,0),0) -> #REF! | BF3: =BB3*BC3+BD3*BE3 -> #REF! | BG3: =BF3-BA3 -> #REF! | BH3: 0 | BK3: 0 | BL3: =ROUNDUP(DI3/(1-0.17)*0.17,0) -> 0 | BM3: =BL3-BK3 -> 0 | BN3: 0 | BR3: 0 | BT3: 0 | BV3: 0 | BX3: 20125 | BY3: =SUM(AE3,AH3,AN3,AR3,AU3,AY3,BA3,BH3,BK3,BN3,BR3,BT3) -> 20125 | BZ3: =BY3-BX3 -> 0 | CA3: 18071.43 | CB3: =SUM(AE3,AH3,BA3,BH3) -> 18071.43 | CC3: =CB3-CA3 -> 0 | CD3: 0 | CG3: 0 | CI3: 0 | CJ3: 0 | CL3: 0 | CM3: 0.075 | CN3: 0 | CO3: 0 | CP3: 0 | CR3: 0 | CT3: 0 | CU3: =MIN(BX3*5%,1500) -> 1006.25 | CV3: 新员工，未满60天不缴纳 | CW3: 0 | CX3: =ROUND(CA3*CJ3,2) -> 0 | CY3: =CX3-CW3 -> 0 | CZ3: 0 | DA3: =MIN(BX3*5%,1500) -> 1006.25 | DB3: 新员工，未满60天不缴纳 | DC3: 0 | DD3: =MAX(ROUND(CA3*CM3-CZ3,2),0) -> 1355.36 | DE3: 新员工，未满60天不缴纳 | DF3: 20125 | DG3: =SUM(AE3,AH3,AN3,AR3,AU3,AY3,BA3,BH3,BK3,BN3,BR3,BT3,BV3,-CG3,-CP3,-CT3,-CW3) -> 20125 | DH3: =DG3-DF3 -> 0 | DI3: 0 | DJ3: =IFERROR(VLOOKUP(D3,#REF!,2,0),0) -> 0 | DK3: =DJ3-DI3 -> 0 | DL3: 18071.43 | DM3: 18071.43 | DN3: 1505.95 | DO3: 0 | DP3: 0 | DQ3: 20125 | DR3: 23 | DS3: 0 | DT3: 2025-02-06 | DU3: 2025-12-31 | DV3: 2025-01-10 | DW3: 2025-02-10
A4: MSD Asia202502 | B4: MERCK SHARP & DOHME (ASIA) LIMITED | C4: MSD Asia | D4: 51416201 | E4: =VLOOKUP(D4,#REF!,1,0) -> #REF! | F4: Tong | G4: Kin Yi | H4: =G4&" "&F4 -> Kin Yi Tong | I4: =VLOOKUP(D4,#REF!,9,0) -> #REF! | J4: =I4=H4 -> #REF! | K4: Gloria | L4: Active | M4: 2023-02-06 | N4: =VLOOKUP(D4,#REF!,80,0) -> #REF! | O4: =N4-M4 -> #REF! | P4: MRL HKG GCTO | Q4: =VLOOKUP(D4,#REF!,50,0) -> #REF! | R4: =Q4=P4 -> #REF! | S4: CRA | T4: =VLOOKUP(D4,#REF!,21,0) -> #REF! | U4: =T4=S4 -> #REF! | V4: 12630167 | W4: =VLOOKUP(D4,#REF!,51,0) -> #REF! | X4: =W4=V4 -> #REF! | Y4: 202502 | Z4: N | AA4: 2.06 | AB4: 38621 | AC4: =ROUND(VLOOKUP(D4,#REF!,59,0),0) -> #REF! | AD4: =AC4-AB4 -> #REF! | AE4: 38621 | AF4: =AB4 -> 38621 | AG4: =AF4-AE4 -> 0 | AH4: 0 | AK4: 0 | AN4: 0 | AO4: 0 | AP4: =IFERROR(VLOOKUP('Feb for check'!D4,#REF!,15,0),0) -> 0 | AQ4: =AP4-AO4 -> 0 | AR4: 0 | AS4: =AO4 -> 0 | AT4: =AS4-AR4 -> 0 | AU4: 0 | AW4: 0 | AY4: 0 | BA4: 1242.76 | BB4: =IFERROR(VLOOKUP(D4,#REF!,2,0),0) -> 0 | BC4: =MAX(VLOOKUP(D4,#REF!,13,0)-VLOOKUP(D4,#REF!,14,0),0) -> #REF! | BD4: =IFERROR(VLOOKUP(D4,#REF!,3,0),0) -> 0 | BE4: =MAX(VLOOKUP(D4,#REF!,22,0)-VLOOKUP(D4,#REF!,23,0),0) -> #REF! | BF4: =BB4*BC4+BD4*BE4 -> #REF! | BG4: =BF4-BA4 -> #REF! | BH4: 0 | BK4: 110 | BL4: =ROUNDUP(DI4/(1-0.17)*0.17,0) -> 110 | BM4: =BL4-BK4 -> 0 | BN4: 0 | BR4: 0 | BT4: 0 | BV4: 0 | BX4: 39973.76 | BY4: =SUM(AE4,AH4,AN4,AR4,AU4,AY4,BA4,BH4,BK4,BN4,BR4,BT4) -> 39973.76 | BZ4: =BY4-BX4 -> 0 | CA4: 39863.76 | CB4: =SUM(AE4,AH4,BA4,BH4) -> 39863.76 | CC4: =CB4-CA4 -> 0 | CD4: 0 | CG4: 0 | CI4: 1269.7315 | CJ4: 0 | CL4: 0 | CM4: 0.075 | CN4: 0 | CO4: 0 | CP4: 0 | CR4: 0 | CT4: 1500 | CU4: =MIN(BX4*5%,1500) -> 1500 | CV4: =CU4-CT4 -> 0 | CW4: 0 | CX4: =ROUND(CA4*CJ4,2) -> 0 | CY4: =CX4-CW4 -> 0 | CZ4: 1500 | DA4: =MIN(BX4*5%,1500) -> 1500 | DB4: =DA4-CZ4 -> 0 | DC4: 1489.78 | DD4: =MAX(ROUND(CA4*CM4-CZ4,2),0) -> 1489.78 | DE4: =DD4-DC4 -> 0 | DF4: 38473.76 | DG4: =SUM(AE4,AH4,AN4,AR4,AU4,AY4,BA4,BH4,BK4,BN4,BR4,BT4,BV4,-CG4,-CP4,-CT4,-CW4) -> 38473.76 | DH4: =DG4-DF4 -> 0 | DI4: 536.21 | DJ4: =IFERROR(VLOOKUP(D4,#REF!,2,0),0) -> 0 | DK4: =DJ4-DI4 -> -536.21 | DL4: 39973.76 | DM4: 617103.87 | DN4: 3218.42 | DO4: 1242.76 | DP4: 0 | DQ4: 39863.76 | DR4: 28 | DS4: 0 | DT4: 2025-01-01 | DU4: 2025-12-31 | DV4: 2025-01-10 | DW4: 2025-02-10
A5: MSD Asia202502 | B5: MERCK SHARP & DOHME (ASIA) LIMITED | C5: MSD Asia | D5: 51425942 | E5: =VLOOKUP(D5,#REF!,1,0) -> #REF! | F5: Ho | G5: Yuk Kam | H5: =G5&" "&F5 -> Yuk Kam Ho | I5: =VLOOKUP(D5,#REF!,9,0) -> #REF! | J5: =I5=H5 -> #REF! | K5: Kana | L5: Active | M5: 2022-04-11 | N5: =VLOOKUP(D5,#REF!,80,0) -> #REF! | O5: =N5-M5 -> #REF! | P5: CAS-HONG KONG | Q5: =VLOOKUP(D5,#REF!,50,0) -> #REF! | R5: =Q5=P5 -> #REF! | S5: Sr Specialist - Consumer, Digital Activation, HHDDA- Asia Pacific | T5: =VLOOKUP(D5,#REF!,21,0) -> #REF! | U5: =T5=S5 -> #REF! | V5: 12630420 | W5: =VLOOKUP(D5,#REF!,51,0) -> #REF! | X5: =W5=V5 -> #REF! | Y5: 202502 | Z5: N | AA5: 2.89 | AB5: 59376.08 | AC5: =ROUND(VLOOKUP(D5,#REF!,59,0),0) -> #REF! | AD5: =AC5-AB5 -> #REF! | AE5: 61105.16 | AF5: =AB5+AB5-VLOOKUP(D5,#REF!,14,0) -> #REF! | AG5: =AF5-AE5 -> #REF! | AH5: 0 | AK5: 0 | AN5: 0 | AO5: 0 | AP5: =IFERROR(VLOOKUP('Feb for check'!D5,#REF!,15,0),0) -> 0 | AQ5: =AP5-AO5 -> 0 | AR5: 0 | AS5: =AO5 -> 0 | AT5: =AS5-AR5 -> 0 | AU5: 0 | AW5: 0 | AY5: 0 | BA5: 0 | BB5: =IFERROR(VLOOKUP(D5,#REF!,2,0),0) -> 0 | BC5: =MAX(VLOOKUP(D5,#REF!,13,0)-VLOOKUP(D5,#REF!,14,0),0) -> #REF! | BD5: =IFERROR(VLOOKUP(D5,#REF!,3,0),0) -> 0 | BE5: =MAX(VLOOKUP(D5,#REF!,22,0)-VLOOKUP(D5,#REF!,23,0),0) -> #REF! | BF5: =BB5*BC5+BD5*BE5 -> #REF! | BG5: =BF5-BA5 -> #REF! | BH5: 0 | BK5: 0 | BL5: =ROUNDUP(DI5/(1-0.17)*0.17,0) -> 0 | BM5: =BL5-BK5 -> 0 | BN5: 0 | BR5: 0 | BT5: 0 | BV5: 0 | BX5: 61105.16 | BY5: =SUM(AE5,AH5,AN5,AR5,AU5,AY5,BA5,BH5,BK5,BN5,BR5,BT5) -> 61105.16 | BZ5: =BY5-BX5 -> 0 | CA5: 61105.16 | CB5: =SUM(AE5,AH5,BA5,BH5) -> 61105.16 | CC5: =CB5-CA5 -> 0 | CD5: 0 | CG5: 0 | CI5: 1895.2438 | CJ5: 0 | CL5: 0 | CM5: 0.075 | CN5: 0 | CO5: 0 | CP5: 0 | CR5: 0 | CT5: 1500 | CU5: =MIN(BX5*5%,1500) -> 1500 | CV5: =CU5-CT5 -> 0 | CW5: 0 | CX5: =ROUND(CA5*CJ5,2) -> 0 | CY5: =CX5-CW5 -> 0 | CZ5: 1500 | DA5: =MIN(BX5*5%,1500) -> 1500 | DB5: =DA5-CZ5 -> 0 | DC5: 3082.89 | DD5: =MAX(ROUND(CA5*CM5-CZ5,2),0) -> 3082.89 | DE5: =DD5-DC5 -> 0 | DF5: 59605.16 | DG5: =SUM(AE5,AH5,AN5,AR5,AU5,AY5,BA5,BH5,BK5,BN5,BR5,BT5,BV5,-CG5,-CP5,-CT5,-CW5) -> 59605.16 | DH5: =DG5-DF5 -> 0 | DI5: 0 | DJ5: =IFERROR(VLOOKUP(D5,#REF!,2,0),0) -> 0 | DK5: =DJ5-DI5 -> 0 | DL5: 61105.16 | DM5: 1027658.7 | DN5: 4948.01 | DO5: 0 | DP5: 0 | DQ5: 61105.16 | DR5: 28 | DS5: 0 | DT5: 2025-01-01 | DU5: 2025-12-31 | DV5: 2025-01-10 | DW5: 2025-02-10
A6: MSD Asia202502 | B6: MERCK SHARP & DOHME (ASIA) LIMITED | C6: MSD Asia | D6: 33900515 | E6: =VLOOKUP(D6,#REF!,1,0) -> #REF! | F6: Mak | G6: Wai Wah | H6: =G6&" "&F6 -> Wai Wah Mak | I6: =VLOOKUP(D6,#REF!,9,0) -> #REF! | J6: =I6=H6 -> #REF! | K6: Norris | L6: Active | M6: 2021-04-19 | N6: =VLOOKUP(D6,#REF!,80,0) -> #REF! | O6: =N6-M6 -> #REF! | P6: HK VACCINE (MA) | Q6: =VLOOKUP(D6,#REF!,50,0) -> #REF! | R6: =Q6=P6 -> #REF! | S6: Business Unit Director, Vaccines | T6: =VLOOKUP(D6,#REF!,21,0) -> #REF! | U6: =T6=S6 -> #REF! | V6: 12630102 | W6: =VLOOKUP(D6,#REF!,51,0) -> #REF! | X6: =W6=V6 -> #REF! | Y6: 202502 | Z6: N | AA6: 20.52 | AB6: 114700 | AC6: =ROUND(VLOOKUP(D6,#REF!,59,0),0) -> #REF! | AD6: =AC6-AB6 -> #REF! | AE6: 114700 | AF6: =AB6 -> 114700 | AG6: =AF6-AE6 -> 0 | AH6: 0 | AK6: 0 | AN6: 0 | AO6: 0 | AP6: =IFERROR(VLOOKUP('Feb for check'!D6,#REF!,15,0),0) -> 0 | AQ6: =AP6-AO6 -> 0 | AR6: 0 | AS6: =AO6 -> 0 | AT6: =AS6-AR6 -> 0 | AU6: 0 | AW6: 0 | AY6: 0 | BA6: 0 | BB6: =IFERROR(VLOOKUP(D6,#REF!,2,0),0) -> 0 | BC6: =MAX(VLOOKUP(D6,#REF!,13,0)-VLOOKUP(D6,#REF!,14,0),0) -> #REF! | BD6: =IFERROR(VLOOKUP(D6,#REF!,3,0),0) -> 0 | BE6: =MAX(VLOOKUP(D6,#REF!,22,0)-VLOOKUP(D6,#REF!,23,0),0) -> #REF! | BF6: =BB6*BC6+BD6*BE6 -> #REF! | BG6: =BF6-BA6 -> #REF! | BH6: 0 | BK6: 1834 | BL6: =ROUNDUP(DI6/(1-0.17)*0.17,0) -> 1834 | BM6: =BL6-BK6 -> 0 | BN6: 0 | BR6: 0 | BT6: 0 | BV6: 0 | BX6: 116534 | BY6: =SUM(AE6,AH6,AN6,AR6,AU6,AY6,BA6,BH6,BK6,BN6,BR6,BT6) -> 116534 | BZ6: =BY6-BX6 -> 0 | CA6: 114700 | CB6: =SUM(AE6,AH6,BA6,BH6) -> 114700 | CC6: =CB6-CA6 -> 0 | CD6: 0 | CG6: 0 | CI6: 3770.9589 | CJ6: 0.05 | CL6: 0 | CM6: 0.1 | CN6: 0 | CO6: 0 | CP6: 0 | CR6: 0 | CT6: 1500 | CU6: =MIN(BX6*5%,1500) -> 1500 | CV6: =CU6-CT6 -> 0 | CW6: 5735 | CX6: =ROUND(CA6*CJ6,2) -> 5735 | CY6: =CX6-CW6 -> 0 | CZ6: 1500 | DA6: =MIN(BX6*5%,1500) -> 1500 | DB6: =DA6-CZ6 -> 0 | DC6: 9970 | DD6: =MAX(ROUND(CA6*CM6-CZ6,2),0) -> 9970 | DE6: =DD6-DC6 -> 0 | DF6: 109299 | DG6: =SUM(AE6,AH6,AN6,AR6,AU6,AY6,BA6,BH6,BK6,BN6,BR6,BT6,BV6,-CG6,-CP6,-CT6,-CW6) -> 109299 | DH6: =DG6-DF6 -> 0 | DI6: 8951.7 | DJ6: =IFERROR(VLOOKUP(D6,#REF!,2,0),0) -> 0 | DK6: =DJ6-DI6 -> -8951.7 | DL6: 116534 | DM6: 2098915.5 | DN6: 9558.33 | DO6: 0 | DP6: 0 | DQ6: 114700 | DR6: 28 | DS6: 0 | DT6: 2025-01-01 | DU6: 2025-12-31 | DV6: 2025-01-10 | DW6: 2025-02-10
A7: MSD Asia202502 | B7: MERCK SHARP & DOHME (ASIA) LIMITED | C7: MSD Asia | D7: 51443582 | E7: =VLOOKUP(D7,#REF!,1,0) -> #REF! | F7: Lam | G7: PO KIN JONATHAN | H7: =G7&" "&F7 -> PO KIN JONATHAN Lam | I7: =VLOOKUP(D7,#REF!,9,0) -> #REF! | J7: =I7=H7 -> #REF! | K7: Jonathan | L7: Active | M7: 2024-09-30 | N7: =VLOOKUP(D7,#REF!,80,0) -> #REF! | O7: =N7-M7 -> #REF! | P7: AH SALES ADMIN | Q7: =VLOOKUP(D7,#REF!,50,0) -> #REF! | R7: =Q7=P7 -> #REF! | S7: Assoc. Spclst., Regulatory Affairs | T7: =VLOOKUP(D7,#REF!,21,0) -> #REF! | U7: =T7=S7 -> #REF! | V7: 12630417 | W7: =VLOOKUP(D7,#REF!,51,0) -> #REF! | X7: =W7=V7 -> #REF! | Y7: 202502 | Z7: N | AA7: 0.42 | AB7: 26520 | AC7: =ROUND(VLOOKUP(D7,#REF!,59,0),0) -> #REF! | AD7: =AC7-AB7 -> #REF! | AE7: 26520 | AF7: =AB7 -> 26520 | AG7: =AF7-AE7 -> 0 | AH7: 0 | AK7: 0 | AN7: 0 | AO7: 0 | AP7: =IFERROR(VLOOKUP('Feb for check'!D7,#REF!,15,0),0) -> 0 | AQ7: =AP7-AO7 -> 0 | AR7: 0 | AS7: =AO7 -> 0 | AT7: =AS7-AR7 -> 0 | AU7: 0 | AW7: 0 | AY7: 0 | BA7: 0 | BB7: =IFERROR(VLOOKUP(D7,#REF!,2,0),0) -> 0 | BC7: =MAX(VLOOKUP(D7,#REF!,13,0)-VLOOKUP(D7,#REF!,14,0),0) -> #REF! | BD7: =IFERROR(VLOOKUP(D7,#REF!,3,0),0) -> 0 | BE7: =MAX(VLOOKUP(D7,#REF!,22,0)-VLOOKUP(D7,#REF!,23,0),0) -> #REF! | BF7: =BB7*BC7+BD7*BE7 -> #REF! | BG7: =BF7-BA7 -> #REF! | BH7: 0 | BK7: 0 | BL7: =ROUNDUP(DI7/(1-0.17)*0.17,0) -> 0 | BM7: =BL7-BK7 -> 0 | BN7: 0 | BR7: 0 | BT7: 0 | BV7: 0 | BX7: 26520 | BY7: =SUM(AE7,AH7,AN7,AR7,AU7,AY7,BA7,BH7,BK7,BN7,BR7,BT7) -> 26520 | BZ7: =BY7-BX7 -> 0 | CA7: 26520 | CB7: =SUM(AE7,AH7,BA7,BH7) -> 26520 | CC7: =CB7-CA7 -> 0 | CD7: 0 | CG7: 0 | CI7: 871.8904 | CJ7: 0 | CL7: 0 | CM7: 0.075 | CN7: 0 | CO7: 0 | CP7: 0 | CR7: 0 | CT7: 1326 | CU7: =MIN(BX7*5%,1500) -> 1326 | CV7: =CU7-CT7 -> 0 | CW7: 0 | CX7: =ROUND(CA7*CJ7,2) -> 0 | CY7: =CX7-CW7 -> 0 | CZ7: 1326 | DA7: =MIN(BX7*5%,1500) -> 1326 | DB7: =DA7-CZ7 -> 0 | DC7: 663 | DD7: =MAX(ROUND(CA7*CM7-CZ7,2),0) -> 663 | DE7: =DD7-DC7 -> 0 | DF7: 25194 | DG7: =SUM(AE7,AH7,AN7,AR7,AU7,AY7,BA7,BH7,BK7,BN7,BR7,BT7,BV7,-CG7,-CP7,-CT7,-CW7) -> 25194 | DH7: =DG7-DF7 -> 0 | DI7: 0 | DJ7: =IFERROR(VLOOKUP(D7,#REF!,2,0),0) -> 0 | DK7: =DJ7-DI7 -> 0 | DL7: 26520 | DM7: 140697.02 | DN7: 2210 | DO7: 0 | DP7: 0 | DQ7: 26520 | DR7: 28 | DS7: 0 | DT7: 2025-01-01 | DU7: 2025-12-31 | DV7: 2025-01-10 | DW7: 2025-02-10
A8: MSD Asia202502 | B8: MERCK SHARP & DOHME (ASIA) LIMITED | C8: MSD Asia | D8: 51317350 | E8: =VLOOKUP(D8,#REF!,1,0) -> #REF! | F8: Chau | G8: Wing Yan Rene | H8: =G8&" "&F8 -> Wing Yan Rene Chau | I8: =VLOOKUP(D8,#REF!,9,0) -> #REF! | J8: =I8=H8 -> #REF! | K8: Rene | L8: Active | M8: 2018-08-01 | N8: =VLOOKUP(D8,#REF!,80,0) -> #REF! | O8: =N8-M8 -> #REF! | P8: MRL HKG GMVC | Q8: =VLOOKUP(D8,#REF!,50,0) -> #REF! | R8: =Q8=P8 -> #REF! | S8: Dir, V&I GMVC, AP HUB, Scientific Ops, Team Lead | T8: =VLOOKUP(D8,#REF!,21,0) -> #REF! | U8: =T8=S8 -> #REF! | V8: 12630364 | W8: =VLOOKUP(D8,#REF!,51,0) -> #REF! | X8: =W8=V8 -> #REF! | Y8: 202502 | Z8: N | AA8: 6.58 | AB8: 130325 | AC8: =ROUND(VLOOKUP(D8,#REF!,59,0),0) -> #REF! | AD8: =AC8-AB8 -> #REF! | AE8: 130325 | AF8: =AB8 -> 130325 | AG8: =AF8-AE8 -> 0 | AH8: 0 | AK8: 0 | AN8: 0 | AO8: 0 | AP8: =IFERROR(VLOOKUP('Feb for check'!D8,#REF!,15,0),0) -> 0 | AQ8: =AP8-AO8 -> 0 | AR8: 0 | AS8: =AO8 -> 0 | AT8: =AS8-AR8 -> 0 | AU8: 0 | AW8: 0 | AY8: 0 | BA8: 0 | BB8: =IFERROR(VLOOKUP(D8,#REF!,2,0),0) -> 0 | BC8: =MAX(VLOOKUP(D8,#REF!,13,0)-VLOOKUP(D8,#REF!,14,0),0) -> #REF! | BD8: =IFERROR(VLOOKUP(D8,#REF!,3,0),0) -> 0 | BE8: =MAX(VLOOKUP(D8,#REF!,22,0)-VLOOKUP(D8,#REF!,23,0),0) -> #REF! | BF8: =BB8*BC8+BD8*BE8 -> #REF! | BG8: =BF8-BA8 -> #REF! | BH8: 0 | BK8: 0 | BL8: =ROUNDUP(DI8/(1-0.17)*0.17,0) -> 0 | BM8: =BL8-BK8 -> 0 | BN8: 0 | BR8: 0 | BT8: 0 | BV8: 0 | BX8: 130325 | BY8: =SUM(AE8,AH8,AN8,AR8,AU8,AY8,BA8,BH8,BK8,BN8,BR8,BT8) -> 130325 | BZ8: =BY8-BX8 -> 0 | CA8: 130325 | CB8: =SUM(AE8,AH8,BA8,BH8) -> 130325 | CC8: =CB8-CA8 -> 0 | CD8: 0 | CG8: 0 | CI8: 4284.6575 | CJ8: 0 | CL8: 0 | CM8: 0.075 | CN8: 0 | CO8: 0 | CP8: 0 | CR8: 0 | CT8: 1500 | CU8: =MIN(BX8*5%,1500) -> 1500 | CV8: =CU8-CT8 -> 0 | CW8: 0 | CX8: =ROUND(CA8*CJ8,2) -> 0 | CY8: =CX8-CW8 -> 0 | CZ8: 1500 | DA8: =MIN(BX8*5%,1500) -> 1500 | DB8: =DA8-CZ8 -> 0 | DC8: 8274.38 | DD8: =MAX(ROUND(CA8*CM8-CZ8,2),0) -> 8274.38 | DE8: =DD8-DC8 -> 0 | DF8: 128825 | DG8: =SUM(AE8,AH8,AN8,AR8,AU8,AY8,BA8,BH8,BK8,BN8,BR8,BT8,BV8,-CG8,-CP8,-CT8,-CW8) -> 128825 | DH8: =DG8-DF8 -> 0 | DI8: 0 | DJ8: =IFERROR(VLOOKUP(D8,#REF!,2,0),0) -> 0 | DK8: =DJ8-DI8 -> 0 | DL8: 130325 | DM8: 2325997 | DN8: 10860.42 | DO8: 0 | DP8: 0 | DQ8: 130325 | DR8: 28 | DS8: 0 | DT8: 2025-01-01 | DU8: 2025-12-31 | DV8: 2025-01-10 | DW8: 2025-02-10
A9: MSD Asia202502 | B9: MERCK SHARP & DOHME (ASIA) LIMITED | C9: MSD Asia | D9: 51026180 | E9: =VLOOKUP(D9,#REF!,1,0) -> #REF! | F9: Leung | G9: Kin Yue Francis | H9: =G9&" "&F9 -> Kin Yue Francis Leung | I9: =VLOOKUP(D9,#REF!,9,0) -> #REF! | J9: =I9=H9 -> #REF! | K9: Francis | L9: Active | M9: 2014-08-25 | N9: =VLOOKUP(D9,#REF!,80,0) -> #REF! | O9: =N9-M9 -> #REF! | P9: MRL HKG GCTO | Q9: =VLOOKUP(D9,#REF!,50,0) -> #REF! | R9: =Q9=P9 -> #REF! | S9: CRD | T9: =VLOOKUP(D9,#REF!,21,0) -> #REF! | U9: =T9=S9 -> #REF! | V9: 12630167 | W9: =VLOOKUP(D9,#REF!,51,0) -> #REF! | X9: =W9=V9 -> #REF! | Y9: 202502 | Z9: N | AA9: 10.52 | AB9: 97000 | AC9: =ROUND(VLOOKUP(D9,#REF!,59,0),0) -> #REF! | AD9: =AC9-AB9 -> #REF! | AE9: 97000 | AF9: =AB9 -> 97000 | AG9: =AF9-AE9 -> 0 | AH9: 0 | AK9: 0 | AN9: 0 | AO9: 0 | AP9: =IFERROR(VLOOKUP('Feb for check'!D9,#REF!,15,0),0) -> 0 | AQ9: =AP9-AO9 -> 0 | AR9: 0 | AS9: =AO9 -> 0 | AT9: =AS9-AR9 -> 0 | AU9: 0 | AW9: 0 | AY9: 0 | BA9: 1562.38 | BB9: =IFERROR(VLOOKUP(D9,#REF!,2,0),0) -> 0 | BC9: =MAX(VLOOKUP(D9,#REF!,13,0)-VLOOKUP(D9,#REF!,14,0),0) -> #REF! | BD9: =IFERROR(VLOOKUP(D9,#REF!,3,0),0) -> 0 | BE9: =MAX(VLOOKUP(D9,#REF!,22,0)-VLOOKUP(D9,#REF!,23,0),0) -> #REF! | BF9: =BB9*BC9+BD9*BE9 -> #REF! | BG9: =BF9-BA9 -> #REF! | BH9: 0 | BK9: 2751 | BL9: =ROUNDUP(DI9/(1-0.17)*0.17,0) -> 2751 | BM9: =BL9-BK9 -> 0 | BN9: 0 | BR9: 0 | BT9: 0 | BV9: 0 | BX9: 101313.38 | BY9: =SUM(AE9,AH9,AN9,AR9,AU9,AY9,BA9,BH9,BK9,BN9,BR9,BT9) -> 101313.38 | BZ9: =BY9-BX9 -> 0 | CA9: 98562.38 | CB9: =SUM(AE9,AH9,BA9,BH9) -> 98562.38 | CC9: =CB9-CA9 -> 0 | CD9: 0 | CG9: 0 | CI9: 3189.041 | CJ9: 0 | CL9: 0 | CM9: 0.075 | CN9: 0 | CO9: 0 | CP9: 0 | CR9: 0 | CT9: 1500 | CU9: =MIN(BX9*5%,1500) -> 1500 | CV9: =CU9-CT9 -> 0 | CW9: 0 | CX9: =ROUND(CA9*CJ9,2) -> 0 | CY9: =CX9-CW9 -> 0 | CZ9: 1500 | DA9: =MIN(BX9*5%,1500) -> 1500 | DB9: =DA9-CZ9 -> 0 | DC9: 5892.18 | DD9: =MAX(ROUND(CA9*CM9-CZ9,2),0) -> 5892.18 | DE9: =DD9-DC9 -> 0 | DF9: 99813.38 | DG9: =SUM(AE9,AH9,AN9,AR9,AU9,AY9,BA9,BH9,BK9,BN9,BR9,BT9,BV9,-CG9,-CP9,-CT9,-CW9) -> 99813.38 | DH9: =DG9-DF9 -> 0 | DI9: 13427.55 | DJ9: =IFERROR(VLOOKUP(D9,#REF!,2,0),0) -> 0 | DK9: =DJ9-DI9 -> -13427.55 | DL9: 101313.38 | DM9: 1571135.6 | DN9: 8083.33 | DO9: 1562.38 | DP9: 0 | DQ9: 98562.38 | DR9: 28 | DS9: 0 | DT9: 2025-01-01 | DU9: 2025-12-31 | DV9: 2025-01-10 | DW9: 2025-02-10
A10: MSD Asia202502 | B10: MERCK SHARP & DOHME (ASIA) LIMITED | C10: MSD Asia | D10: 51447820 | E10: =VLOOKUP(D10,#REF!,1,0) -> #REF! | F10: Fong | G10: Hang Kit | H10: =G10&" "&F10 -> Hang Kit Fong | I10: =VLOOKUP(D10,#REF!,9,0) -> #REF! | J10: =I10=H10 -> #REF! | K10: Hang Kit | L10: Active | M10: 2022-11-14 | N10: =VLOOKUP(D10,#REF!,80,0) -> #REF! | O10: =N10-M10 -> #REF! | P10: MRL HKG GCTO | Q10: =VLOOKUP(D10,#REF!,50,0) -> #REF! | R10: =Q10=P10 -> #REF! | S10: Sr. CRA | T10: =VLOOKUP(D10,#REF!,21,0) -> #REF! | U10: =T10=S10 -> #REF! | V10: 12630167 | W10: =VLOOKUP(D10,#REF!,51,0) -> #REF! | X10: =W10=V10 -> #REF! | Y10: 202502 | Z10: N | AA10: 2.29 | AB10: 47819 | AC10: =ROUND(VLOOKUP(D10,#REF!,59,0),0) -> #REF! | AD10: =AC10-AB10 -> #REF! | AE10: 47819 | AF10: =AB10 -> 47819 | AG10: =AF10-AE10 -> 0 | AH10: 0 | AK10: 0 | AN10: 0 | AO10: 0 | AP10: =IFERROR(VLOOKUP('Feb for check'!D10,#REF!,15,0),0) -> 0 | AQ10: =AP10-AO10 -> 0 | AR10: 0 | AS10: =AO10 -> 0 | AT10: =AS10-AR10 -> 0 | AU10: 0 | AW10: 0 | AY10: 0 | BA10: 244.38 | BB10: =IFERROR(VLOOKUP(D10,#REF!,2,0),0) -> 0 | BC10: =MAX(VLOOKUP(D10,#REF!,13,0)-VLOOKUP(D10,#REF!,14,0),0) -> #REF! | BD10: =IFERROR(VLOOKUP(D10,#REF!,3,0),0) -> 0 | BE10: =MAX(VLOOKUP(D10,#REF!,22,0)-VLOOKUP(D10,#REF!,23,0),0) -> #REF! | BF10: =BB10*BC10+BD10*BE10 -> #REF! | BG10: =BF10-BA10 -> #REF! | BH10: 0 | BK10: 917 | BL10: =ROUNDUP(DI10/(1-0.17)*0.17,0) -> 917 | BM10: =BL10-BK10 -> 0 | BN10: 0 | BR10: 0 | BT10: 0 | BV10: 0 | BX10: 48980.38 | BY10: =SUM(AE10,AH10,AN10,AR10,AU10,AY10,BA10,BH10,BK10,BN10,BR10,BT10) -> 48980.38 | BZ10: =BY10-BX10 -> 0 | CA10: 48063.38 | CB10: =SUM(AE10,AH10,BA10,BH10) -> 48063.38 | CC10: =CB10-CA10 -> 0 | CD10: 0 | CG10: 0 | CI10: 1572.1315 | CJ10: 0 | CL10: 0 | CM10: 0.075 | CN10: 0 | CO10: 0 | CP10: 0 | CR10: 0 | CT10: 1500 | CU10: =MIN(BX10*5%,1500) -> 1500 | CV10: =CU10-CT10 -> 0 | CW10: 0 | CX10: =ROUND(CA10*CJ10,2) -> 0 | CY10: =CX10-CW10 -> 0 | CZ10: 1500 | DA10: =MIN(BX10*5%,1500) -> 1500 | DB10: =DA10-CZ10 -> 0 | DC10: 2104.75 | DD10: =MAX(ROUND(CA10*CM10-CZ10,2),0) -> 2104.75 | DE10: =DD10-DC10 -> 0 | DF10: 47480.38 | DG10: =SUM(AE10,AH10,AN10,AR10,AU10,AY10,BA10,BH10,BK10,BN10,BR10,BT10,BV10,-CG10,-CP10,-CT10,-CW10) -> 47480.38 | DH10: =DG10-DF10 -> 0 | DI10: 4475.85 | DJ10: =IFERROR(VLOOKUP(D10,#REF!,2,0),0) -> 0 | DK10: =DJ10-DI10 -> -4475.85 | DL10: 48980.38 | DM10: 811209.92 | DN10: 3984.92 | DO10: 244.38 | DP10: 0 | DQ10: 48063.38 | DR10: 28 | DS10: 0 | DT10: 2025-01-01 | DU10: 2025-12-31 | DV10: 2025-01-10 | DW10: 2025-02-10
A11: MSD Asia202502 | B11: MERCK SHARP & DOHME (ASIA) LIMITED | C11: MSD Asia | D11: 51302892 | E11: =VLOOKUP(D11,#REF!,1,0) -> #REF! | F11: Li | G11: Wing Ki | H11: =G11&" "&F11 -> Wing Ki Li | I11: =VLOOKUP(D11,#REF!,9,0) -> #REF! | J11: =I11=H11 -> #REF! | K11: Stella | L11: Active | M11: 2018-02-12 | N11: =VLOOKUP(D11,#REF!,80,0) -> #REF! | O11: =N11-M11 -> #REF! | P11: HK Public Sector Access | Q11: =VLOOKUP(D11,#REF!,50,0) -> #REF! | R11: =Q11=P11 -> #REF! | S11: Policy & Corporate Affairs Lead | T11: =VLOOKUP(D11,#REF!,21,0) -> #REF! | U11: =T11=S11 -> #REF! | V11: 12630108 | W11: =VLOOKUP(D11,#REF!,51,0) -> #REF! | X11: =W11=V11 -> #REF! | Y11: 202502 | Z11: N | AA11: 7.05 | AB11: 70390 | AC11: =ROUND(VLOOKUP(D11,#REF!,59,0),0) -> #REF! | AD11: =AC11-AB11 -> #REF! | AE11: 70390 | AF11: =AB11 -> 70390 | AG11: =AF11-AE11 -> 0 | AH11: 0 | AK11: 0 | AN11: 0 | AO11: 0 | AP11: =IFERROR(VLOOKUP('Feb for check'!D11,#REF!,15,0),0) -> 0 | AQ11: =AP11-AO11 -> 0 | AR11: 0 | AS11: =AO11 -> 0 | AT11: =AS11-AR11 -> 0 | AU11: 0 | AW11: 0 | AY11: 0 | BA11: 1837.22 | BB11: =IFERROR(VLOOKUP(D11,#REF!,2,0),0) -> 0 | BC11: =MAX(VLOOKUP(D11,#REF!,13,0)-VLOOKUP(D11,#REF!,14,0),0) -> #REF! | BD11: =IFERROR(VLOOKUP(D11,#REF!,3,0),0) -> 0 | BE11: =MAX(VLOOKUP(D11,#REF!,22,0)-VLOOKUP(D11,#REF!,23,0),0) -> #REF! | BF11: =BB11*BC11+BD11*BE11 -> #REF! | BG11: =BF11-BA11 -> #REF! | BH11: 0 | BK11: 917 | BL11: =ROUNDUP(DI11/(1-0.17)*0.17,0) -> 917 | BM11: =BL11-BK11 -> 0 | BN11: 0 | BR11: 0 | BT11: 0 | BV11: 0 | BX11: 73144.22 | BY11: =SUM(AE11,AH11,AN11,AR11,AU11,AY11,BA11,BH11,BK11,BN11,BR11,BT11) -> 73144.22 | BZ11: =BY11-BX11 -> 0 | CA11: 72227.22 | CB11: =SUM(AE11,AH11,BA11,BH11) -> 72227.22 | CC11: =CB11-CA11 -> 0 | CD11: 0 | CG11: 0 | CI11: 2314.1917 | CJ11: 0 | CL11: 0 | CM11: 0.075 | CN11: 0 | CO11: 0 | CP11: 0 | CR11: 0 | CT11: 1500 | CU11: =MIN(BX11*5%,1500) -> 1500 | CV11: =CU11-CT11 -> 0 | CW11: 0 | CX11: =ROUND(CA11*CJ11,2) -> 0 | CY11: =CX11-CW11 -> 0 | CZ11: 1500 | DA11: =MIN(BX11*5%,1500) -> 1500 | DB11: =DA11-CZ11 -> 0 | DC11: 3917.04 | DD11: =MAX(ROUND(CA11*CM11-CZ11,2),0) -> 3917.04 | DE11: =DD11-DC11 -> 0 | DF11: 71644.22 | DG11: =SUM(AE11,AH11,AN11,AR11,AU11,AY11,BA11,BH11,BK11,BN11,BR11,BT11,BV11,-CG11,-CP11,-CT11,-CW11) -> 71644.22 | DH11: =DG11-DF11 -> 0 | DI11: 4475.84 | DJ11: =IFERROR(VLOOKUP(D11,#REF!,2,0),0) -> 0 | DK11: =DJ11-DI11 -> -4475.84 | DL11: 73144.22 | DM11: 1195263.7 | DN11: 5865.83 | DO11: 1837.22 | DP11: 0 | DQ11: 72227.22 | DR11: 28 | DS11: 0 | DT11: 2025-01-01 | DU11: 2025-12-31 | DV11: 2025-01-10 | DW11: 2025-02-10
A12: MSD Asia202502 | B12: MERCK SHARP & DOHME (ASIA) LIMITED | C12: MSD Asia | D12: 51505904 | E12: =VLOOKUP(D12,#REF!,1,0) -> #REF! | F12: Tam | G12: Yin Kei | H12: =G12&" "&F12 -> Yin Kei Tam | I12: =VLOOKUP(D12,#REF!,9,0) -> #REF! | J12: =I12=H12 -> #REF! | K12: Yin Kei | L12: Active | M12: 2025-01-02 | N12: =VLOOKUP(D12,#REF!,80,0) -> #REF! | O12: =N12-M12 -> #REF! | P12: MRL HKG GRA INTL | Q12: =VLOOKUP(D12,#REF!,50,0) -> #REF! | R12: =Q12=P12 -> #REF! | S12: Regulatory Affairs Associate (Pharmacy Intern) | T12: =VLOOKUP(D12,#REF!,21,0) -> #REF! | U12: =T12=S12 -> #REF! | V12: 12630168 | W12: =VLOOKUP(D12,#REF!,51,0) -> #REF! | X12: =W12=V12 -> #REF! | Y12: 202502 | Z12: N | AA12: 0.16 | AB12: 0 | AE12: 0 | AH12: 0 | AK12: 13500 | AL12: =VLOOKUP(D12,#REF!,59,0) -> #REF! | AM12: =AL12-AK12 -> #REF! | AN12: 13500 | AO12: 0 | AP12: =IFERROR(VLOOKUP('Feb for check'!D12,#REF!,15,0),0) -> 0 | AQ12: =AP12-AO12 -> 0 | AR12: 0 | AS12: =AO12 -> 0 | AT12: =AS12-AR12 -> 0 | AU12: 0 | AW12: 0 | AY12: 0 | BA12: 0 | BB12: =IFERROR(VLOOKUP(D12,#REF!,2,0),0) -> 0 | BC12: =MAX(VLOOKUP(D12,#REF!,13,0)-VLOOKUP(D12,#REF!,14,0),0) -> #REF! | BD12: =IFERROR(VLOOKUP(D12,#REF!,3,0),0) -> 0 | BE12: =MAX(VLOOKUP(D12,#REF!,22,0)-VLOOKUP(D12,#REF!,23,0),0) -> #REF! | BF12: =BB12*BC12+BD12*BE12 -> #REF! | BG12: =BF12-BA12 -> #REF! | BH12: 0 | BK12: 0 | BL12: =ROUNDUP(DI12/(1-0.17)*0.17,0) -> 0 | BM12: =BL12-BK12 -> 0 | BN12: 0 | BR12: 0 | BT12: 0 | BV12: 0 | BX12: 13500 | BY12: =SUM(AE12,AH12,AN12,AR12,AU12,AY12,BA12,BH12,BK12,BN12,BR12,BT12) -> 13500 | BZ12: =BY12-BX12 -> 0 | CA12: 0 | CB12: =SUM(AE12,AH12,BA12,BH12) -> 0 | CC12: =CB12-CA12 -> 0 | CD12: 0 | CG12: 0 | CI12: 443.8356 | CJ12: 0 | CL12: 0 | CM12: 0 | CN12: 0 | CO12: 0 | CP12: 0 | CR12: 0 | CT12: 0 | CU12: =MIN(BX12*5%,1500) -> 675 | CV12: 新员工，未满60天不缴纳 | CW12: 0 | CX12: =ROUND(CA12*CJ12,2) -> 0 | CY12: =CX12-CW12 -> 0 | CZ12: 0 | DA12: =MIN(BX12*5%,1500) -> 675 | DB12: 新员工，未满60天不缴纳 | DC12: 0 | DD12: =MAX(ROUND(CA12*CM12-CZ12,2),0) -> 0 | DE12: =DD12-DC12 -> 0 | DF12: 13500 | DG12: =SUM(AE12,AH12,AN12,AR12,AU12,AY12,BA12,BH12,BK12,BN12,BR12,BT12,BV12,-CG12,-CP12,-CT12,-CW12) -> 13500 | DH12: =DG12-DF12 -> 0 | DI12: 0 | DJ12: =IFERROR(VLOOKUP(D12,#REF!,2,0),0) -> 0 | DK12: =DJ12-DI12 -> 0 | DL12: 13500 | DM12: 26564.52 | DN12: 1125 | DO12: 0 | DP12: 0 | DQ12: 13500 | DR12: 28 | DS12: 0 | DT12: 2025-01-02 | DU12: 2025-12-31 | DV12: 2025-01-10 | DW12: 2025-02-10
A13: MSD Asia202502 | B13: MERCK SHARP & DOHME (ASIA) LIMITED | C13: MSD Asia | D13: 10233093 | E13: =VLOOKUP(D13,#REF!,1,0) -> #REF! | F13: Wong | G13: Hoi Yan Pamela | H13: =G13&" "&F13 -> Hoi Yan Pamela Wong | I13: =VLOOKUP(D13,#REF!,9,0) -> #REF! | J13: =I13=H13 -> #REF! | K13: Pamela | L13: Active | M13: 2008-09-08 | N13: =VLOOKUP(D13,#REF!,80,0) -> #REF! | O13: =N13-M13 -> #REF! | P13: IT Global Infrastructure Operations - HK | Q13: =VLOOKUP(D13,#REF!,50,0) -> #REF! | R13: =Q13=P13 -> #REF! | S13: Director, Strategist, Foundational Platforms | T13: =VLOOKUP(D13,#REF!,21,0) -> #REF! | U13: =T13=S13 -> #REF! | V13: 12630026 | W13: =VLOOKUP(D13,#REF!,51,0) -> #REF! | X13: =W13=V13 -> #REF! | Y13: 202502 | Z13: N | AA13: 16.48 | AB13: 112137 | AC13: =ROUND(VLOOKUP(D13,#REF!,59,0),0) -> #REF! | AD13: =AC13-AB13 -> #REF! | AE13: 112137 | AF13: =AB13 -> 112137 | AG13: =AF13-AE13 -> 0 | AH13: 0 | AK13: 0 | AN13: 0 | AO13: 0 | AP13: =IFERROR(VLOOKUP('Feb for check'!D13,#REF!,15,0),0) -> 0 | AQ13: =AP13-AO13 -> 0 | AR13: 0 | AS13: =AO13 -> 0 | AT13: =AS13-AR13 -> 0 | AU13: 0 | AW13: 0 | AY13: 0 | BA13: 0 | BB13: =IFERROR(VLOOKUP(D13,#REF!,2,0),0) -> 0 | BC13: =MAX(VLOOKUP(D13,#REF!,13,0)-VLOOKUP(D13,#REF!,14,0),0) -> #REF! | BD13: =IFERROR(VLOOKUP(D13,#REF!,3,0),0) -> 0 | BE13: =MAX(VLOOKUP(D13,#REF!,22,0)-VLOOKUP(D13,#REF!,23,0),0) -> #REF! | BF13: =BB13*BC13+BD13*BE13 -> #REF! | BG13: =BF13-BA13 -> #REF! | BH13: 0 | BK13: 1540 | BL13: =ROUNDUP(DI13/(1-0.17)*0.17,0) -> 1540 | BM13: =BL13-BK13 -> 0 | BN13: 0 | BR13: 0 | BT13: 0 | BV13: 0 | BX13: 113677 | BY13: =SUM(AE13,AH13,AN13,AR13,AU13,AY13,BA13,BH13,BK13,BN13,BR13,BT13) -> 113677 | BZ13: =BY13-BX13 -> 0 | CA13: 112137 | CB13: =SUM(AE13,AH13,BA13,BH13) -> 112137 | CC13: =CB13-CA13 -> 0 | CD13: 0 | CG13: 0 | CI13: 3686.6958 | CJ13: 0.05 | CL13: 0 | CM13: 0.1 | CN13: 0 | CO13: 0 | CP13: 0 | CR13: 0 | CT13: 1500 | CU13: =MIN(BX13*5%,1500) -> 1500 | CV13: =CU13-CT13 -> 0 | CW13: 5606.85 | CX13: =ROUND(CA13*CJ13,2) -> 5606.85 | CY13: =CX13-CW13 -> 0 | CZ13: 1500 | DA13: =MIN(BX13*5%,1500) -> 1500 | DB13: =DA13-CZ13 -> 0 | DC13: 9713.7 | DD13: =MAX(ROUND(CA13*CM13-CZ13,2),0) -> 9713.7 | DE13: =DD13-DC13 -> 0 | DF13: 106570.15 | DG13: =SUM(AE13,AH13,AN13,AR13,AU13,AY13,BA13,BH13,BK13,BN13,BR13,BT13,BV13,-CG13,-CP13,-CT13,-CW13) -> 106570.15 | DH13: =DG13-DF13 -> 0 | DI13: 7518.08 | DJ13: =IFERROR(VLOOKUP(D13,#REF!,2,0),0) -> 0 | DK13: =DJ13-DI13 -> -7518.08 | DL13: 113677 | DM13: 2213744 | DN13: 9344.75 | DO13: 0 | DP13: 0 | DQ13: 112137 | DR13: 28 | DS13: 0 | DT13: 2025-01-01 | DU13: 2025-12-31 | DV13: 2025-01-10 | DW13: 2025-02-10
A14: MSD Asia202502 | B14: MERCK SHARP & DOHME (ASIA) LIMITED | C14: MSD Asia | D14: 51167064 | E14: =VLOOKUP(D14,#REF!,1,0) -> #REF! | F14: Lam | G14: Siu Yan | H14: =G14&" "&F14 -> Siu Yan Lam | I14: =VLOOKUP(D14,#REF!,9,0) -> #REF! | J14: =I14=H14 -> #REF! | K14: Sharon | L14: Active | M14: 2013-03-18 | N14: =VLOOKUP(D14,#REF!,80,0) -> #REF! | O14: =N14-M14 -> #REF! | P14: HK Direct Selling - Oncology | Q14: =VLOOKUP(D14,#REF!,50,0) -> #REF! | R14: =Q14=P14 -> #REF! | S14: Associate Sales Manager, Oncology | T14: =VLOOKUP(D14,#REF!,21,0) -> #REF! | U14: =T14=S14 -> #REF! | V14: 12630118 | W14: =VLOOKUP(D14,#REF!,51,0) -> #REF! | X14: =W14=V14 -> #REF! | Y14: 202502 | Z14: N | AA14: 11.95 | AB14: 45371 | AC14: =ROUND(VLOOKUP(D14,#REF!,59,0),0) -> #REF! | AD14: =AC14-AB14 -> #REF! | AE14: 45371 | AF14: =AB14 -> 45371 | AG14: =AF14-AE14 -> 0 | AH14: 0 | AK14: 0 | AN14: 0 | AO14: 2500 | AP14: =IFERROR(VLOOKUP('Feb for check'!D14,#REF!,15,0),0) -> 0 | AQ14: =AP14-AO14 -> -2500 | AR14: 2500 | AS14: =AO14 -> 2500 | AT14: =AS14-AR14 -> 0 | AU14: 0 | AW14: 0 | AY14: 0 | BA14: 2414.85 | BB14: =IFERROR(VLOOKUP(D14,#REF!,2,0),0) -> 0 | BC14: =MAX(VLOOKUP(D14,#REF!,13,0)-VLOOKUP(D14,#REF!,14,0),0) -> #REF! | BD14: =IFERROR(VLOOKUP(D14,#REF!,3,0),0) -> 0 | BE14: =MAX(VLOOKUP(D14,#REF!,22,0)-VLOOKUP(D14,#REF!,23,0),0) -> #REF! | BF14: =BB14*BC14+BD14*BE14 -> #REF! | BG14: =BF14-BA14 -> #REF! | BH14: 0 | BK14: 0 | BL14: =ROUNDUP(DI14/(1-0.17)*0.17,0) -> 0 | BM14: =BL14-BK14 -> 0 | BN14: 0 | BR14: 0 | BT14: 0 | BV14: 0 | BX14: 50285.85 | BY14: =SUM(AE14,AH14,AN14,AR14,AU14,AY14,BA14,BH14,BK14,BN14,BR14,BT14) -> 50285.85 | BZ14: =BY14-BX14 -> 0 | CA14: 47785.85 | CB14: =SUM(AE14,AH14,BA14,BH14) -> 47785.85 | CC14: =CB14-CA14 -> 0 | CD14: 0 | CG14: 0 | CI14: 1573.841 | CJ14: 0.05 | CL14: 0 | CM14: 0.1 | CN14: 0 | CO14: 0 | CP14: 0 | CR14: 0 | CT14: 1500 | CU14: =MIN(BX14*5%,1500) -> 1500 | CV14: =CU14-CT14 -> 0 | CW14: 2389.29 | CX14: =ROUND(CA14*CJ14,2) -> 2389.29 | CY14: =CX14-CW14 -> 0 | CZ14: 1500 | DA14: =MIN(BX14*5%,1500) -> 1500 | DB14: =DA14-CZ14 -> 0 | DC14: 3278.59 | DD14: =MAX(ROUND(CA14*CM14-CZ14,2),0) -> 3278.59 | DE14: =DD14-DC14 -> 0 | DF14: 46396.56 | DG14: =SUM(AE14,AH14,AN14,AR14,AU14,AY14,BA14,BH14,BK14,BN14,BR14,BT14,BV14,-CG14,-CP14,-CT14,-CW14) -> 46396.56 | DH14: =DG14-DF14 -> 0 | DI14: 0 | DJ14: =IFERROR(VLOOKUP(D14,#REF!,2,0),0) -> 0 | DK14: =DJ14-DI14 -> 0 | DL14: 47785.85 | DM14: 779433.25 | DN14: 3780.92 | DO14: 2414.85 | DP14: 0 | DQ14: 50285.85 | DR14: 28 | DS14: 0 | DT14: 2025-01-01 | DU14: 2025-12-31 | DV14: 2025-01-10 | DW14: 2025-02-10
A15: MSD Asia202502 | B15: MERCK SHARP & DOHME (ASIA) LIMITED | C15: MSD Asia | D15: 51445144 | E15: =VLOOKUP(D15,#REF!,1,0) -> #REF! | F15: Lin | G15: Nga Man | H15: =G15&" "&F15 -> Nga Man Lin | I15: =VLOOKUP(D15,#REF!,9,0) -> #REF! | J15: =I15=H15 -> #REF! | K15: Carman | L15: Active | M15: 2022-12-06 | N15: =VLOOKUP(D15,#REF!,80,0) -> #REF! | O15: =N15-M15 -> #REF! | P15: MRL HKG GCTO | Q15: =VLOOKUP(D15,#REF!,50,0) -> #REF! | R15: =Q15=P15 -> #REF! | S15: COM | T15: =VLOOKUP(D15,#REF!,21,0) -> #REF! | U15: =T15=S15 -> #REF! | V15: 12630167 | W15: =VLOOKUP(D15,#REF!,51,0) -> #REF! | X15: =W15=V15 -> #REF! | Y15: 202502 | Z15: N | AA15: 2.23 | AB15: 47493 | AC15: =ROUND(VLOOKUP(D15,#REF!,59,0),0) -> #REF! | AD15: =AC15-AB15 -> #REF! | AE15: 47493 | AF15: =AB15 -> 47493 | AG15: =AF15-AE15 -> 0 | AH15: 0 | AK15: 0 | AN15: 0 | AO15: 0 | AP15: =IFERROR(VLOOKUP('Feb for check'!D15,#REF!,15,0),0) -> 0 | AQ15: =AP15-AO15 -> 0 | AR15: 0 | AS15: =AO15 -> 0 | AT15: =AS15-AR15 -> 0 | AU15: 0 | AW15: 0 | AY15: 0 | BA15: 0 | BB15: =IFERROR(VLOOKUP(D15,#REF!,2,0),0) -> 0 | BC15: =MAX(VLOOKUP(D15,#REF!,13,0)-VLOOKUP(D15,#REF!,14,0),0) -> #REF! | BD15: =IFERROR(VLOOKUP(D15,#REF!,3,0),0) -> 0 | BE15: =MAX(VLOOKUP(D15,#REF!,22,0)-VLOOKUP(D15,#REF!,23,0),0) -> #REF! | BF15: =BB15*BC15+BD15*BE15 -> #REF! | BG15: =BF15-BA15 -> #REF! | BH15: 0 | BK15: 0 | BL15: =ROUNDUP(DI15/(1-0.17)*0.17,0) -> 0 | BM15: =BL15-BK15 -> 0 | BN15: 0 | BR15: 0 | BT15: 0 | BV15: 0 | BX15: 47493 | BY15: =SUM(AE15,AH15,AN15,AR15,AU15,AY15,BA15,BH15,BK15,BN15,BR15,BT15) -> 47493 | BZ15: =BY15-BX15 -> 0 | CA15: 47493 | CB15: =SUM(AE15,AH15,BA15,BH15) -> 47493 | CC15: =CB15-CA15 -> 0 | CD15: 0 | CG15: 0 | CI15: 1561.4136 | CJ15: 0 | CL15: 0 | CM15: 0.075 | CN15: 0 | CO15: 0 | CP15: 0 | CR15: 0 | CT15: 1500 | CU15: =MIN(BX15*5%,1500) -> 1500 | CV15: =CU15-CT15 -> 0 | CW15: 0 | CX15: =ROUND(CA15*CJ15,2) -> 0 | CY15: =CX15-CW15 -> 0 | CZ15: 1500 | DA15: =MIN(BX15*5%,1500) -> 1500 | DB15: =DA15-CZ15 -> 0 | DC15: 2061.98 | DD15: =MAX(ROUND(CA15*CM15-CZ15,2),0) -> 2061.98 | DE15: =DD15-DC15 -> 0 | DF15: 45993 | DG15: =SUM(AE15,AH15,AN15,AR15,AU15,AY15,BA15,BH15,BK15,BN15,BR15,BT15,BV15,-CG15,-CP15,-CT15,-CW15) -> 45993 | DH15: =DG15-DF15 -> 0 | DI15: 0 | DJ15: =IFERROR(VLOOKUP(D15,#REF!,2,0),0) -> 0 | DK15: =DJ15-DI15 -> 0 | DL15: 47493 | DM15: 796842.14 | DN15: 3957.75 | DO15: 0 | DP15: 0 | DQ15: 47493 | DR15: 28 | DS15: 0 | DT15: 2025-01-01 | DU15: 2025-12-31 | DV15: 2025-01-10 | DW15: 2025-02-10
A16: MSD Asia202502 | B16: MERCK SHARP & DOHME (ASIA) LIMITED | C16: MSD Asia | D16: 51490540 | E16: =VLOOKUP(D16,#REF!,1,0) -> #REF! | F16: Wan | G16: Woon See Claudia | H16: =G16&" "&F16 -> Woon See Claudia Wan | I16: =VLOOKUP(D16,#REF!,9,0) -> #REF! | J16: =I16=H16 -> #REF! | L16: Active | M16: 2024-05-13 | N16: =VLOOKUP(D16,#REF!,80,0) -> #REF! | O16: =N16-M16 -> #REF! | P16: MRL HKG GCTO | Q16: =VLOOKUP(D16,#REF!,50,0) -> #REF! | R16: =Q16=P16 -> #REF! | S16: CTC | T16: =VLOOKUP(D16,#REF!,21,0) -> #REF! | U16: =T16=S16 -> #REF! | V16: 12630167 | W16: =VLOOKUP(D16,#REF!,51,0) -> #REF! | X16: =W16=V16 -> #REF! | Y16: 202502 | Z16: N | AA16: 0.8 | AB16: 29000 | AC16: =ROUND(VLOOKUP(D16,#REF!,59,0),0) -> #REF! | AD16: =AC16-AB16 -> #REF! | AE16: 29000 | AF16: =AB16 -> 29000 | AG16: =AF16-AE16 -> 0 | AH16: 0 | AK16: 0 | AN16: 0 | AO16: 0 | AP16: =IFERROR(VLOOKUP('Feb for check'!D16,#REF!,15,0),0) -> 0 | AQ16: =AP16-AO16 -> 0 | AR16: 0 | AS16: =AO16 -> 0 | AT16: =AS16-AR16 -> 0 | AU16: 0 | AW16: 0 | AY16: 0 | BA16: 0 | BB16: =IFERROR(VLOOKUP(D16,#REF!,2,0),0) -> 0 | BC16: =MAX(VLOOKUP(D16,#REF!,13,0)-VLOOKUP(D16,#REF!,14,0),0) -> #REF! | BD16: =IFERROR(VLOOKUP(D16,#REF!,3,0),0) -> 0 | BE16: =MAX(VLOOKUP(D16,#REF!,22,0)-VLOOKUP(D16,#REF!,23,0),0) -> #REF! | BF16: =BB16*BC16+BD16*BE16 -> #REF! | BG16: =BF16-BA16 -> #REF! | BH16: 0 | BK16: 0 | BL16: =ROUNDUP(DI16/(1-0.17)*0.17,0) -> 0 | BM16: =BL16-BK16 -> 0 | BN16: 0 | BR16: 0 | BT16: 0 | BV16: 0 | BX16: 29000 | BY16: =SUM(AE16,AH16,AN16,AR16,AU16,AY16,BA16,BH16,BK16,BN16,BR16,BT16) -> 29000 | BZ16: =BY16-BX16 -> 0 | CA16: 29000 | CB16: =SUM(AE16,AH16,BA16,BH16) -> 29000 | CC16: =CB16-CA16 -> 0 | CD16: 0 | CG16: 0 | CI16: 953.4246 | CJ16: 0 | CL16: 0 | CM16: 0.075 | CN16: 0 | CO16: 0 | CP16: 0 | CR16: 0 | CT16: 1450 | CU16: =MIN(BX16*5%,1500) -> 1450 | CV16: =CU16-CT16 -> 0 | CW16: 0 | CX16: =ROUND(CA16*CJ16,2) -> 0 | CY16: =CX16-CW16 -> 0 | CZ16: 1450 | DA16: =MIN(BX16*5%,1500) -> 1450 | DB16: =DA16-CZ16 -> 0 | DC16: 725 | DD16: =MAX(ROUND(CA16*CM16-CZ16,2),0) -> 725 | DE16: =DD16-DC16 -> 0 | DF16: 27550 | DG16: =SUM(AE16,AH16,AN16,AR16,AU16,AY16,BA16,BH16,BK16,BN16,BR16,BT16,BV16,-CG16,-CP16,-CT16,-CW16) -> 27550 | DH16: =DG16-DF16 -> 0 | DI16: 0 | DJ16: =IFERROR(VLOOKUP(D16,#REF!,2,0),0) -> 0 | DK16: =DJ16-DI16 -> 0 | DL16: 29000 | DM16: 297797.81 | DN16: 2416.67 | DO16: 0 | DP16: 0 | DQ16: 29000 | DR16: 28 | DS16: 0 | DT16: 2025-01-01 | DU16: 2025-12-31 | DV16: 2025-01-10 | DW16: 2025-02-10
A17: MSD Asia202502 | B17: MERCK SHARP & DOHME (ASIA) LIMITED | C17: MSD Asia | D17: 51090149 | E17: =VLOOKUP(D17,#REF!,1,0) -> #REF! | F17: Iu | G17: Hoi Yan | H17: =G17&" "&F17 -> Hoi Yan Iu | I17: =VLOOKUP(D17,#REF!,9,0) -> #REF! | J17: =I17=H17 -> #REF! | K17: Orlean | L17: Active | M17: 2011-12-12 | N17: =VLOOKUP(D17,#REF!,80,0) -> #REF! | O17: =N17-M17 -> #REF! | P17: MRL HKG GRA INTL | Q17: =VLOOKUP(D17,#REF!,50,0) -> #REF! | R17: =Q17=P17 -> #REF! | S17: Regulatory Affairs Manager | T17: =VLOOKUP(D17,#REF!,21,0) -> #REF! | U17: =T17=S17 -> #REF! | V17: 12630168 | W17: =VLOOKUP(D17,#REF!,51,0) -> #REF! | X17: =W17=V17 -> #REF! | Y17: 202502 | Z17: N | AA17: 13.22 | AB17: 55161 | AC17: =ROUND(VLOOKUP(D17,#REF!,59,0),0) -> #REF! | AD17: =AC17-AB17 -> #REF! | AE17: 55161 | AF17: =AB17 -> 55161 | AG17: =AF17-AE17 -> 0 | AH17: 0 | AK17: 0 | AN17: 0 | AO17: 0 | AP17: =IFERROR(VLOOKUP('Feb for check'!D17,#REF!,15,0),0) -> 0 | AQ17: =AP17-AO17 -> 0 | AR17: 0 | AS17: =AO17 -> 0 | AT17: =AS17-AR17 -> 0 | AU17: 0 | AW17: 0 | AY17: 0 | BA17: 299.6 | BB17: =IFERROR(VLOOKUP(D17,#REF!,2,0),0) -> 0 | BC17: =MAX(VLOOKUP(D17,#REF!,13,0)-VLOOKUP(D17,#REF!,14,0),0) -> #REF! | BD17: =IFERROR(VLOOKUP(D17,#REF!,3,0),0) -> 0 | BE17: =MAX(VLOOKUP(D17,#REF!,22,0)-VLOOKUP(D17,#REF!,23,0),0) -> #REF! | BF17: =BB17*BC17+BD17*BE17 -> #REF! | BG17: =BF17-BA17 -> #REF! | BH17: 0 | BK17: 0 | BL17: =ROUNDUP(DI17/(1-0.17)*0.17,0) -> 0 | BM17: =BL17-BK17 -> 0 | BN17: 0 | BR17: 0 | BT17: 0 | BV17: 0 | BX17: 55460.6 | BY17: =SUM(AE17,AH17,AN17,AR17,AU17,AY17,BA17,BH17,BK17,BN17,BR17,BT17) -> 55460.6 | BZ17: =BY17-BX17 -> 0 | CA17: 55460.6 | CB17: =SUM(AE17,AH17,BA17,BH17) -> 55460.6 | CC17: =CB17-CA17 -> 0 | CD17: 0 | CG17: 0 | CI17: 1813.5123 | CJ17: 0 | CL17: 0 | CM17: 0.075 | CN17: 0 | CO17: 0 | CP17: 0 | CR17: 0 | CT17: 1500 | CU17: =MIN(BX17*5%,1500) -> 1500 | CV17: =CU17-CT17 -> 0 | CW17: 0 | CX17: =ROUND(CA17*CJ17,2) -> 0 | CY17: =CX17-CW17 -> 0 | CZ17: 1500 | DA17: =MIN(BX17*5%,1500) -> 1500 | DB17: =DA17-CZ17 -> 0 | DC17: 2659.55 | DD17: =MAX(ROUND(CA17*CM17-CZ17,2),0) -> 2659.55 | DE17: =DD17-DC17 -> 0 | DF17: 53960.6 | DG17: =SUM(AE17,AH17,AN17,AR17,AU17,AY17,BA17,BH17,BK17,BN17,BR17,BT17,BV17,-CG17,-CP17,-CT17,-CW17) -> 53960.6 | DH17: =DG17-DF17 -> 0 | DI17: 0 | DJ17: =IFERROR(VLOOKUP(D17,#REF!,2,0),0) -> 0 | DK17: =DJ17-DI17 -> 0 | DL17: 55460.6 | DM17: 947197.43 | DN17: 4596.75 | DO17: 299.6 | DP17: 0 | DQ17: 55460.6 | DR17: 28 | DS17: 0 | DT17: 2025-01-01 | DU17: 2025-12-31 | DV17: 2025-01-10 | DW17: 2025-02-10
A18: MSD Asia202502 | B18: MERCK SHARP & DOHME (ASIA) LIMITED | C18: MSD Asia | D18: 51477071 | E18: =VLOOKUP(D18,#REF!,1,0) -> #REF! | F18: Choi | G18: Ching Ha Pamela | H18: =G18&" "&F18 -> Ching Ha Pamela Choi | I18: =VLOOKUP(D18,#REF!,9,0) -> #REF! | J18: =I18=H18 -> #REF! | K18: Pamela | L18: Active | M18: 2024-01-02 | N18: =VLOOKUP(D18,#REF!,80,0) -> #REF! | O18: =N18-M18 -> #REF! | P18: MRL HKG GRA INTL | Q18: =VLOOKUP(D18,#REF!,50,0) -> #REF! | R18: =Q18=P18 -> #REF! | S18: Senior Regulatory Affairs Associate | T18: =VLOOKUP(D18,#REF!,21,0) -> #REF! | U18: =T18=S18 -> #REF! | V18: 12630168 | W18: =VLOOKUP(D18,#REF!,51,0) -> #REF! | X18: =W18=V18 -> #REF! | Y18: 202502 | Z18: N | AA18: 1.16 | AB18: 34000 | AC18: =ROUND(VLOOKUP(D18,#REF!,59,0),0) -> #REF! | AD18: =AC18-AB18 -> #REF! | AE18: 34000 | AF18: =AB18 -> 34000 | AG18: =AF18-AE18 -> 0 | AH18: 0 | AK18: 0 | AN18: 0 | AO18: 0 | AP18: =IFERROR(VLOOKUP('Feb for check'!D18,#REF!,15,0),0) -> 0 | AQ18: =AP18-AO18 -> 0 | AR18: 0 | AS18: =AO18 -> 0 | AT18: =AS18-AR18 -> 0 | AU18: 0 | AW18: 0 | AY18: 0 | BA18: 9.46 | BB18: =IFERROR(VLOOKUP(D18,#REF!,2,0),0) -> 0 | BC18: =MAX(VLOOKUP(D18,#REF!,13,0)-VLOOKUP(D18,#REF!,14,0),0) -> #REF! | BD18: =IFERROR(VLOOKUP(D18,#REF!,3,0),0) -> 0 | BE18: =MAX(VLOOKUP(D18,#REF!,22,0)-VLOOKUP(D18,#REF!,23,0),0) -> #REF! | BF18: =BB18*BC18+BD18*BE18 -> #REF! | BG18: =BF18-BA18 -> #REF! | BH18: 0 | BK18: 221 | BL18: =ROUNDUP(DI18/(1-0.17)*0.17,0) -> 221 | BM18: =BL18-BK18 -> 0 | BN18: 0 | BR18: 0 | BT18: 0 | BV18: 0 | BX18: 34230.46 | BY18: =SUM(AE18,AH18,AN18,AR18,AU18,AY18,BA18,BH18,BK18,BN18,BR18,BT18) -> 34230.46 | BZ18: =BY18-BX18 -> 0 | CA18: 34009.46 | CB18: =SUM(AE18,AH18,BA18,BH18) -> 34009.46 | CC18: =CB18-CA18 -> 0 | CD18: 0 | CG18: 0 | CI18: 1117.8082 | CJ18: 0 | CL18: 0 | CM18: 0.075 | CN18: 0 | CO18: 0 | CP18: 0 | CR18: 0 | CT18: 1500 | CU18: =MIN(BX18*5%,1500) -> 1500 | CV18: =CU18-CT18 -> 0 | CW18: 0 | CX18: =ROUND(CA18*CJ18,2) -> 0 | CY18: =CX18-CW18 -> 0 | CZ18: 1500 | DA18: =MIN(BX18*5%,1500) -> 1500 | DB18: =DA18-CZ18 -> 0 | DC18: 1050.71 | DD18: =MAX(ROUND(CA18*CM18-CZ18,2),0) -> 1050.71 | DE18: =DD18-DC18 -> 0 | DF18: 32730.46 | DG18: =SUM(AE18,AH18,AN18,AR18,AU18,AY18,BA18,BH18,BK18,BN18,BR18,BT18,BV18,-CG18,-CP18,-CT18,-CW18) -> 32730.46 | DH18: =DG18-DF18 -> 0 | DI18: 1076.14 | DJ18: =IFERROR(VLOOKUP(D18,#REF!,2,0),0) -> 0 | DK18: =DJ18-DI18 -> -1076.14 | DL18: 34230.46 | DM18: 443189.37 | DN18: 2833.33 | DO18: 9.46 | DP18: 0 | DQ18: 34009.46 | DR18: 28 | DS18: 0 | DT18: 2025-01-01 | DU18: 2025-12-31 | DV18: 2025-01-10 | DW18: 2025-02-10
A19: MSD Asia202502 | B19: MERCK SHARP & DOHME (ASIA) LIMITED | C19: MSD Asia | D19: 33900076 | E19: =VLOOKUP(D19,#REF!,1,0) -> #REF! | F19: Chu | G19: Wai Kwan Agnes | H19: =G19&" "&F19 -> Wai Kwan Agnes Chu | I19: =VLOOKUP(D19,#REF!,9,0) -> #REF! | J19: =I19=H19 -> #REF! | K19: Agnes | L19: Active | M19: 1992-01-06 | N19: =VLOOKUP(D19,#REF!,80,0) -> #REF! | O19: Follow Payroll system date | P19: Distribution & Logistics - HK | Q19: =VLOOKUP(D19,#REF!,50,0) -> #REF! | R19: =Q19=P19 -> #REF! | S19: SCM Lead, Hong Kong | T19: =VLOOKUP(D19,#REF!,21,0) -> #REF! | U19: =T19=S19 -> #REF! | V19: 12630165 | W19: =VLOOKUP(D19,#REF!,51,0) -> #REF! | X19: =W19=V19 -> #REF! | Y19: 202502 | Z19: N | AA19: 33.15 | AB19: 61865 | AC19: =ROUND(VLOOKUP(D19,#REF!,59,0),0) -> #REF! | AD19: =AC19-AB19 -> #REF! | AE19: 61865 | AF19: =AB19 -> 61865 | AG19: =AF19-AE19 -> 0 | AH19: 0 | AK19: 0 | AN19: 0 | AO19: 0 | AP19: =IFERROR(VLOOKUP('Feb for check'!D19,#REF!,15,0),0) -> 0 | AQ19: =AP19-AO19 -> 0 | AR19: 0 | AS19: =AO19 -> 0 | AT19: =AS19-AR19 -> 0 | AU19: 0 | AW19: 0 | AY19: 0 | BA19: 4322.34 | BB19: =IFERROR(VLOOKUP(D19,#REF!,2,0),0) -> 0 | BC19: =MAX(VLOOKUP(D19,#REF!,13,0)-VLOOKUP(D19,#REF!,14,0),0) -> #REF! | BD19: =IFERROR(VLOOKUP(D19,#REF!,3,0),0) -> 0 | BE19: =MAX(VLOOKUP(D19,#REF!,22,0)-VLOOKUP(D19,#REF!,23,0),0) -> #REF! | BF19: =BB19*BC19+BD19*BE19 -> #REF! | BG19: =BF19-BA19 -> #REF! | BH19: 0 | BK19: 0 | BL19: =ROUNDUP(DI19/(1-0.17)*0.17,0) -> 0 | BM19: =BL19-BK19 -> 0 | BN19: 0 | BR19: 0 | BT19: 0 | BV19: 0 | BX19: 0 | CA19: 0 | CD19: 61865 | CE19: =AE19 -> 61865 | CF19: =CE19-CD19 -> 0 | CG19: 0 | CI19: 2033.9178 | CJ19: 0 | CL19: 0 | CM19: 0 | CN19: 0.05 | CO19: 0.061 | CP19: 3093.25 | CQ19: =ROUND(CN19*CD19,2) -> 3093.25 | CR19: 3773.77 | CS19: =ROUND(CD19*CO19,2) -> 3773.77 | CT19: 0 | CW19: 0 | CX19: =ROUND(CA19*CJ19,2) -> 0 | CY19: =CX19-CW19 -> 0 | CZ19: 0 | DA19: =MIN(BX19*5%,1500) -> 0 | DB19: =DA19-CZ19 -> 0 | DC19: 0 | DD19: =MAX(ROUND(CA19*CM19-CZ19,2),0) -> 0 | DE19: =DD19-DC19 -> 0 | DF19: 63094.09 | DG19: =SUM(AE19,AH19,AN19,AR19,AU19,AY19,BA19,BH19,BK19,BN19,BR19,BT19,BV19,-CG19,-CP19,-CT19,-CW19) -> 63094.09 | DH19: =DG19-DF19 -> 0 | DI19: 0 | DJ19: =IFERROR(VLOOKUP(D19,#REF!,2,0),0) -> 0 | DK19: =DJ19-DI19 -> 0 | DL19: 66187.34 | DM19: 1046341.6 | DN19: 5155.42 | DO19: 4322.34 | DP19: 54.94 | DQ19: 66187.34 | DR19: 28 | DS19: 0 | DT19: 2025-01-01 | DU19: 2025-12-31 | DV19: 2025-01-10 | DW19: 2025-02-10
A20: MSD Asia202502 | B20: MERCK SHARP & DOHME (ASIA) LIMITED | C20: MSD Asia | D20: 51443693 | E20: =VLOOKUP(D20,#REF!,1,0) -> #REF! | F20: Tse | G20: Wai ling | H20: =G20&" "&F20 -> Wai ling Tse | I20: =VLOOKUP(D20,#REF!,9,0) -> #REF! | J20: =I20=H20 -> #REF! | K20: Elva | L20: Active | M20: 2022-09-26 | N20: =VLOOKUP(D20,#REF!,80,0) -> #REF! | O20: =N20-M20 -> #REF! | P20: CAS-HONG KONG | Q20: =VLOOKUP(D20,#REF!,50,0) -> #REF! | R20: =Q20=P20 -> #REF! | S20: Specialist - Solutions, Decision Science, HHDDA- Asia Pacific | T20: =VLOOKUP(D20,#REF!,21,0) -> #REF! | U20: =T20=S20 -> #REF! | V20: 12630420 | W20: =VLOOKUP(D20,#REF!,51,0) -> #REF! | X20: =W20=V20 -> #REF! | Y20: 202502 | Z20: N | AA20: 2.43 | AB20: 45292.85 | AC20: =ROUND(VLOOKUP(D20,#REF!,59,0),0) -> #REF! | AD20: =AC20-AB20 -> #REF! | AE20: 46611.7 | AF20: =AB20+AB20-VLOOKUP(D20,#REF!,14,0) -> #REF! | AG20: =AF20-AE20 -> #REF! | AH20: 0 | AK20: 0 | AN20: 0 | AO20: 0 | AP20: =IFERROR(VLOOKUP('Feb for check'!D20,#REF!,15,0),0) -> 0 | AQ20: =AP20-AO20 -> 0 | AR20: 0 | AS20: =AO20 -> 0 | AT20: =AS20-AR20 -> 0 | AU20: 0 | AW20: 0 | AY20: 0 | BA20: 2160.21 | BB20: =IFERROR(VLOOKUP(D20,#REF!,2,0),0) -> 0 | BC20: =MAX(VLOOKUP(D20,#REF!,13,0)-VLOOKUP(D20,#REF!,14,0),0) -> #REF! | BD20: =IFERROR(VLOOKUP(D20,#REF!,3,0),0) -> 0 | BE20: =MAX(VLOOKUP(D20,#REF!,22,0)-VLOOKUP(D20,#REF!,23,0),0) -> #REF! | BF20: =BB20*BC20+BD20*BE20 -> #REF! | BG20: =BF20-BA20 -> #REF! | BH20: 0 | BK20: 0 | BL20: =ROUNDUP(DI20/(1-0.17)*0.17,0) -> 0 | BM20: =BL20-BK20 -> 0 | BN20: 0 | BR20: 0 | BT20: 0 | BV20: 0 | BX20: 48771.91 | BY20: =SUM(AE20,AH20,AN20,AR20,AU20,AY20,BA20,BH20,BK20,BN20,BR20,BT20) -> 48771.91 | BZ20: =BY20-BX20 -> 0 | CA20: 48771.91 | CB20: =SUM(AE20,AH20,BA20,BH20) -> 48771.91 | CC20: =CB20-CA20 -> 0 | CD20: 0 | CG20: 0 | CI20: 1445.7205 | CJ20: 0 | CL20: 0 | CM20: 0.075 | CN20: 0 | CO20: 0 | CP20: 0 | CR20: 0 | CT20: 1500 | CU20: =MIN(BX20*5%,1500) -> 1500 | CV20: =CU20-CT20 -> 0 | CW20: 0 | CX20: =ROUND(CA20*CJ20,2) -> 0 | CY20: =CX20-CW20 -> 0 | CZ20: 1500 | DA20: =MIN(BX20*5%,1500) -> 1500 | DB20: =DA20-CZ20 -> 0 | DC20: 2157.89 | DD20: =MAX(ROUND(CA20*CM20-CZ20,2),0) -> 2157.89 | DE20: =DD20-DC20 -> 0 | DF20: 47271.91 | DG20: =SUM(AE20,AH20,AN20,AR20,AU20,AY20,BA20,BH20,BK20,BN20,BR20,BT20,BV20,-CG20,-CP20,-CT20,-CW20) -> 47271.91 | DH20: =DG20-DF20 -> 0 | DI20: 0 | DJ20: =IFERROR(VLOOKUP(D20,#REF!,2,0),0) -> 0 | DK20: =DJ20-DI20 -> 0 | DL20: 48771.91 | DM20: 696251.17 | DN20: 3774.4 | DO20: 2160.21 | DP20: 0 | DQ20: 48771.91 | DR20: 28 | DS20: 0 | DT20: 2025-01-01 | DU20: 2025-12-31 | DV20: 2025-01-10 | DW20: 2025-02-10
A21: MSD Asia202502 | B21: MERCK SHARP & DOHME (ASIA) LIMITED | C21: MSD Asia | D21: 51430650 | E21: =VLOOKUP(D21,#REF!,1,0) -> #REF! | F21: Leung | G21: Sze Ching | H21: =G21&" "&F21 -> Sze Ching Leung | I21: =VLOOKUP(D21,#REF!,9,0) -> #REF! | J21: =I21=H21 -> #REF! | K21: Natalie | L21: Active | M21: 2022-06-13 | N21: =VLOOKUP(D21,#REF!,80,0) -> #REF! | O21: =N21-M21 -> #REF! | P21: HK Direct Selling - Oncology | Q21: =VLOOKUP(D21,#REF!,50,0) -> #REF! | R21: =Q21=P21 -> #REF! | S21: Customer Rep., Sales ONC | T21: =VLOOKUP(D21,#REF!,21,0) -> #REF! | U21: =T21=S21 -> #REF! | V21: 12630118 | W21: =VLOOKUP(D21,#REF!,51,0) -> #REF! | X21: =W21=V21 -> #REF! | Y21: 202502 | Z21: N | AA21: 2.72 | AB21: 27500 | AC21: =ROUND(VLOOKUP(D21,#REF!,59,0),0) -> #REF! | AD21: =AC21-AB21 -> #REF! | AE21: 27500 | AF21: =AB21 -> 27500 | AG21: =AF21-AE21 -> 0 | AH21: 0 | AK21: 0 | AN21: 0 | AO21: 2500 | AP21: =IFERROR(VLOOKUP('Feb for check'!D21,#REF!,15,0),0) -> 0 | AQ21: =AP21-AO21 -> -2500 | AR21: 2500 | AS21: =AO21 -> 2500 | AT21: =AS21-AR21 -> 0 | AU21: 0 | AW21: 0 | AY21: 0 | BA21: 0 | BB21: =IFERROR(VLOOKUP(D21,#REF!,2,0),0) -> 0 | BC21: =MAX(VLOOKUP(D21,#REF!,13,0)-VLOOKUP(D21,#REF!,14,0),0) -> #REF! | BD21: =IFERROR(VLOOKUP(D21,#REF!,3,0),0) -> 0 | BE21: =MAX(VLOOKUP(D21,#REF!,22,0)-VLOOKUP(D21,#REF!,23,0),0) -> #REF! | BF21: =BB21*BC21+BD21*BE21 -> #REF! | BG21: =BF21-BA21 -> #REF! | BH21: 0 | BK21: 276 | BL21: =ROUNDUP(DI21/(1-0.17)*0.17,0) -> 276 | BM21: =BL21-BK21 -> 0 | BN21: 0 | BR21: 0 | BT21: 0 | BV21: 0 | BX21: 30276 | BY21: =SUM(AE21,AH21,AN21,AR21,AU21,AY21,BA21,BH21,BK21,BN21,BR21,BT21) -> 30276 | BZ21: =BY21-BX21 -> 0 | CA21: 27500 | CB21: =SUM(AE21,AH21,BA21,BH21) -> 27500 | CC21: =CB21-CA21 -> 0 | CD21: 0 | CG21: 0 | CI21: 986.3013 | CJ21: 0 | CL21: 0 | CM21: 0.075 | CN21: 0 | CO21: 0 | CP21: 0 | CR21: 0 | CT21: 1500 | CU21: =MIN(BX21*5%,1500) -> 1500 | CV21: =CU21-CT21 -> 0 | CW21: 0 | CX21: =ROUND(CA21*CJ21,2) -> 0 | CY21: =CX21-CW21 -> 0 | CZ21: 1500 | DA21: =MIN(BX21*5%,1500) -> 1500 | DB21: =DA21-CZ21 -> 0 | DC21: 562.5 | DD21: =MAX(ROUND(CA21*CM21-CZ21,2),0) -> 562.5 | DE21: =DD21-DC21 -> 0 | DF21: 28776 | DG21: =SUM(AE21,AH21,AN21,AR21,AU21,AY21,BA21,BH21,BK21,BN21,BR21,BT21,BV21,-CG21,-CP21,-CT21,-CW21) -> 28776 | DH21: =DG21-DF21 -> 0 | DI21: 1344.24 | DJ21: =IFERROR(VLOOKUP(D21,#REF!,2,0),0) -> 0 | DK21: =DJ21-DI21 -> -1344.24 | DL21: 27776 | DM21: 474904.41 | DN21: 2291.67 | DO21: 0 | DP21: 0 | DQ21: 30000 | DR21: 28 | DS21: 0 | DT21: 2025-01-01 | DU21: 2025-12-31 | DV21: 2025-01-10 | DW21: 2025-02-10
A22: MSD Asia202502 | B22: MERCK SHARP & DOHME (ASIA) LIMITED | C22: MSD Asia | D22: 51301103 | E22: =VLOOKUP(D22,#REF!,1,0) -> #REF! | F22: Khan | G22: Tsz Kin Aaron | H22: =G22&" "&F22 -> Tsz Kin Aaron Khan | I22: =VLOOKUP(D22,#REF!,9,0) -> #REF! | J22: =I22=H22 -> #REF! | K22: Aaron | L22: Active | M22: 2018-01-29 | N22: =VLOOKUP(D22,#REF!,80,0) -> #REF! | O22: =N22-M22 -> #REF! | P22: MRL HKG MEDICAL AFFAIRS | Q22: =VLOOKUP(D22,#REF!,50,0) -> #REF! | R22: =Q22=P22 -> #REF! | S22: Therapeutic Area Lead | T22: =VLOOKUP(D22,#REF!,21,0) -> #REF! | U22: =T22=S22 -> #REF! | V22: 12630106 | W22: =VLOOKUP(D22,#REF!,51,0) -> #REF! | X22: =W22=V22 -> #REF! | Y22: 202502 | Z22: N | AA22: 7.08 | AB22: 74314 | AC22: =ROUND(VLOOKUP(D22,#REF!,59,0),0) -> #REF! | AD22: =AC22-AB22 -> #REF! | AE22: 74314 | AF22: =AB22 -> 74314 | AG22: =AF22-AE22 -> 0 | AH22: 0 | AK22: 0 | AN22: 0 | AO22: 0 | AP22: =IFERROR(VLOOKUP('Feb for check'!D22,#REF!,15,0),0) -> 0 | AQ22: =AP22-AO22 -> 0 | AR22: 0 | AS22: =AO22 -> 0 | AT22: =AS22-AR22 -> 0 | AU22: 0 | AW22: 0 | AY22: 0 | BA22: 5385.93 | BB22: =IFERROR(VLOOKUP(D22,#REF!,2,0),0) -> 0 | BC22: =MAX(VLOOKUP(D22,#REF!,13,0)-VLOOKUP(D22,#REF!,14,0),0) -> #REF! | BD22: =IFERROR(VLOOKUP(D22,#REF!,3,0),0) -> 0 | BE22: =MAX(VLOOKUP(D22,#REF!,22,0)-VLOOKUP(D22,#REF!,23,0),0) -> #REF! | BF22: =BB22*BC22+BD22*BE22 -> #REF! | BG22: =BF22-BA22 -> #REF! | BH22: 0 | BK22: 221 | BL22: =ROUNDUP(DI22/(1-0.17)*0.17,0) -> 221 | BM22: =BL22-BK22 -> 0 | BN22: 0 | BR22: 0 | BT22: 0 | BV22: 0 | BX22: 79920.93 | BY22: =SUM(AE22,AH22,AN22,AR22,AU22,AY22,BA22,BH22,BK22,BN22,BR22,BT22) -> 79920.93 | BZ22: =BY22-BX22 -> 0 | CA22: 79699.93 | CB22: =SUM(AE22,AH22,BA22,BH22) -> 79699.93 | CC22: =CB22-CA22 -> 0 | CD22: 0 | CG22: 0 | CI22: 2443.2 | CJ22: 0.05 | CL22: 0 | CM22: 0.1 | CN22: 0 | CO22: 0 | CP22: 0 | CR22: 0 | CT22: 1500 | CU22: =MIN(BX22*5%,1500) -> 1500 | CV22: =CU22-CT22 -> 0 | CW22: 3985 | CX22: =ROUND(CA22*CJ22,2) -> 3985 | CY22: =CX22-CW22 -> 0 | CZ22: 1500 | DA22: =MIN(BX22*5%,1500) -> 1500 | DB22: =DA22-CZ22 -> 0 | DC22: 6469.99 | DD22: =MAX(ROUND(CA22*CM22-CZ22,2),0) -> 6469.99 | DE22: =DD22-DC22 -> 0 | DF22: 74435.93 | DG22: =SUM(AE22,AH22,AN22,AR22,AU22,AY22,BA22,BH22,BK22,BN22,BR22,BT22,BV22,-CG22,-CP22,-CT22,-CW22) -> 74435.93 | DH22: =DG22-DF22 -> 0 | DI22: 1076.14 | DJ22: =IFERROR(VLOOKUP(D22,#REF!,2,0),0) -> 0 | DK22: =DJ22-DI22 -> -1076.14 | DL22: 79920.93 | DM22: 1346229.1 | DN22: 6192.83 | DO22: 5385.93 | DP22: 0 | DQ22: 79699.93 | DR22: 28 | DS22: 0 | DT22: 2025-01-01 | DU22: 2025-12-31 | DV22: 2025-01-10 | DW22: 2025-02-10
A23: MSD Asia202502 | B23: MERCK SHARP & DOHME (ASIA) LIMITED | C23: MSD Asia | D23: 51470677 | E23: =VLOOKUP(D23,#REF!,1,0) -> #REF! | F23: Pau | G23: King Man | H23: =G23&" "&F23 -> King Man Pau | I23: =VLOOKUP(D23,#REF!,9,0) -> #REF! | J23: =I23=H23 -> #REF! | K23: Brian | L23: Active | M23: 2023-09-18 | N23: =VLOOKUP(D23,#REF!,80,0) -> #REF! | O23: =N23-M23 -> #REF! | P23: MRL HKG GCTO | Q23: =VLOOKUP(D23,#REF!,50,0) -> #REF! | R23: =Q23=P23 -> #REF! | S23: CRA Manager | T23: =VLOOKUP(D23,#REF!,21,0) -> #REF! | U23: =T23=S23 -> #REF! | V23: 12630167 | W23: =VLOOKUP(D23,#REF!,51,0) -> #REF! | X23: =W23=V23 -> #REF! | Y23: 202502 | Z23: N | AA23: 1.45 | AB23: 96914 | AC23: =ROUND(VLOOKUP(D23,#REF!,59,0),0) -> #REF! | AD23: =AC23-AB23 -> #REF! | AE23: 96914 | AF23: =AB23 -> 96914 | AG23: =AF23-AE23 -> 0 | AH23: 0 | AK23: 0 | AN23: 0 | AO23: 0 | AP23: =IFERROR(VLOOKUP('Feb for check'!D23,#REF!,15,0),0) -> 0 | AQ23: =AP23-AO23 -> 0 | AR23: 0 | AS23: =AO23 -> 0 | AT23: =AS23-AR23 -> 0 | AU23: 0 | AW23: 0 | AY23: 0 | BA23: 0 | BB23: =IFERROR(VLOOKUP(D23,#REF!,2,0),0) -> 0 | BC23: =MAX(VLOOKUP(D23,#REF!,13,0)-VLOOKUP(D23,#REF!,14,0),0) -> #REF! | BD23: =IFERROR(VLOOKUP(D23,#REF!,3,0),0) -> 0 | BE23: =MAX(VLOOKUP(D23,#REF!,22,0)-VLOOKUP(D23,#REF!,23,0),0) -> #REF! | BF23: =BB23*BC23+BD23*BE23 -> #REF! | BG23: =BF23-BA23 -> #REF! | BH23: 0 | BK23: 55 | BL23: =ROUNDUP(DI23/(1-0.17)*0.17,0) -> 55 | BM23: =BL23-BK23 -> 0 | BN23: 0 | BR23: 0 | BT23: 0 | BV23: 0 | BX23: 96969 | BY23: =SUM(AE23,AH23,AN23,AR23,AU23,AY23,BA23,BH23,BK23,BN23,BR23,BT23) -> 96969 | BZ23: =BY23-BX23 -> 0 | CA23: 96914 | CB23: =SUM(AE23,AH23,BA23,BH23) -> 96914 | CC23: =CB23-CA23 -> 0 | CD23: 0 | CG23: 0 | CI23: 3186.2136 | CJ23: 0 | CL23: 0 | CM23: 0.075 | CN23: 0 | CO23: 0 | CP23: 0 | CR23: 0 | CT23: 1500 | CU23: =MIN(BX23*5%,1500) -> 1500 | CV23: =CU23-CT23 -> 0 | CW23: 0 | CX23: =ROUND(CA23*CJ23,2) -> 0 | CY23: =CX23-CW23 -> 0 | CZ23: 1500 | DA23: =MIN(BX23*5%,1500) -> 1500 | DB23: =DA23-CZ23 -> 0 | DC23: 5768.55 | DD23: =MAX(ROUND(CA23*CM23-CZ23,2),0) -> 5768.55 | DE23: =DD23-DC23 -> 0 | DF23: 95469 | DG23: =SUM(AE23,AH23,AN23,AR23,AU23,AY23,BA23,BH23,BK23,BN23,BR23,BT23,BV23,-CG23,-CP23,-CT23,-CW23) -> 95469 | DH23: =DG23-DF23 -> 0 | DI23: 268.1 | DJ23: =IFERROR(VLOOKUP(D23,#REF!,2,0),0) -> 0 | DK23: =DJ23-DI23 -> -268.1 | DL23: 96969 | DM23: 1380753 | DN23: 8076.17 | DO23: 0 | DP23: 0 | DQ23: 96914 | DR23: 28 | DS23: 0 | DT23: 2025-01-01 | DU23: 2025-12-31 | DV23: 2025-01-10 | DW23: 2025-02-10
A24: MSD Asia202502 | B24: MERCK SHARP & DOHME (ASIA) LIMITED | C24: MSD Asia | D24: 10240817 | E24: =VLOOKUP(D24,#REF!,1,0) -> #REF! | F24: Fong | G24: Siu Yuet | H24: =G24&" "&F24 -> Siu Yuet Fong | I24: =VLOOKUP(D24,#REF!,9,0) -> #REF! | J24: =I24=H24 -> #REF! | K24: Simmy | L24: Active | M24: 2009-05-14 | N24: =VLOOKUP(D24,#REF!,80,0) -> #REF! | O24: =N24-M24 -> #REF! | P24: HK Specialty Care (DS) | Q24: =VLOOKUP(D24,#REF!,50,0) -> #REF! | R24: =Q24=P24 -> #REF! | S24: Assistant Manager | T24: =VLOOKUP(D24,#REF!,21,0) -> #REF! | U24: =T24=S24 -> #REF! | V24: 12630116 | W24: =VLOOKUP(D24,#REF!,51,0) -> #REF! | X24: =W24=V24 -> #REF! | Y24: 202502 | Z24: N | AA24: 15.8 | AB24: 42275 | AC24: =ROUND(VLOOKUP(D24,#REF!,59,0),0) -> #REF! | AD24: =AC24-AB24 -> #REF! | AE24: 42275 | AF24: =AB24 -> 42275 | AG24: =AF24-AE24 -> 0 | AH24: 0 | AK24: 0 | AN24: 0 | AO24: 2500 | AP24: =IFERROR(VLOOKUP('Feb for check'!D24,#REF!,15,0),0) -> 0 | AQ24: =AP24-AO24 -> -2500 | AR24: 2500 | AS24: =AO24 -> 2500 | AT24: =AS24-AR24 -> 0 | AU24: 0 | AW24: 0 | AY24: 0 | BA24: 586.3 | BB24: =IFERROR(VLOOKUP(D24,#REF!,2,0),0) -> 0 | BC24: =MAX(VLOOKUP(D24,#REF!,13,0)-VLOOKUP(D24,#REF!,14,0),0) -> #REF! | BD24: =IFERROR(VLOOKUP(D24,#REF!,3,0),0) -> 0 | BE24: =MAX(VLOOKUP(D24,#REF!,22,0)-VLOOKUP(D24,#REF!,23,0),0) -> #REF! | BF24: =BB24*BC24+BD24*BE24 -> #REF! | BG24: =BF24-BA24 -> #REF! | BH24: 0 | BK24: 0 | BL24: =ROUNDUP(DI24/(1-0.17)*0.17,0) -> 0 | BM24: =BL24-BK24 -> 0 | BN24: 0 | BR24: 0 | BT24: 0 | BV24: 0 | BX24: 45361.3 | BY24: =SUM(AE24,AH24,AN24,AR24,AU24,AY24,BA24,BH24,BK24,BN24,BR24,BT24) -> 45361.3 | BZ24: =BY24-BX24 -> 0 | CA24: 42861.3 | CB24: =SUM(AE24,AH24,BA24,BH24) -> 42861.3 | CC24: =CB24-CA24 -> 0 | CD24: 0 | CG24: 0 | CI24: 1472.0547 | CJ24: 0.05 | CL24: 0 | CM24: 0.1 | CN24: 0 | CO24: 0 | CP24: 0 | CR24: 0 | CT24: 1500 | CU24: =MIN(BX24*5%,1500) -> 1500 | CV24: =CU24-CT24 -> 0 | CW24: 2143.07 | CX24: =ROUND(CA24*CJ24,2) -> 2143.07 | CY24: =CX24-CW24 -> 0 | CZ24: 1500 | DA24: =MIN(BX24*5%,1500) -> 1500 | DB24: =DA24-CZ24 -> 0 | DC24: 2786.13 | DD24: =MAX(ROUND(CA24*CM24-CZ24,2),0) -> 2786.13 | DE24: =DD24-DC24 -> 0 | DF24: 41718.23 | DG24: =SUM(AE24,AH24,AN24,AR24,AU24,AY24,BA24,BH24,BK24,BN24,BR24,BT24,BV24,-CG24,-CP24,-CT24,-CW24) -> 41718.23 | DH24: =DG24-DF24 -> 0 | DI24: 0 | DJ24: =IFERROR(VLOOKUP(D24,#REF!,2,0),0) -> 0 | DK24: =DJ24-DI24 -> 0 | DL24: 42861.3 | DM24: 743455.46 | DN24: 3522.92 | DO24: 586.3 | DP24: 0 | DQ24: 45361.3 | DR24: 28 | DS24: 0 | DT24: 2025-01-01 | DU24: 2025-12-31 | DV24: 2025-01-10 | DW24: 2025-02-10
A25: MSD Asia202502 | B25: MERCK SHARP & DOHME (ASIA) LIMITED | C25: MSD Asia | D25: 10190450 | E25: =VLOOKUP(D25,#REF!,1,0) -> #REF! | F25: Lee | G25: Chin Yng Emily | H25: =G25&" "&F25 -> Chin Yng Emily Lee | I25: =VLOOKUP(D25,#REF!,9,0) -> #REF! | J25: =I25=H25 -> #REF! | K25: Emily | L25: Active | M25: 2006-11-27 | N25: =VLOOKUP(D25,#REF!,80,0) -> #REF! | O25: =N25-M25 -> #REF! | P25: MRL HKG GRA INTL | Q25: =VLOOKUP(D25,#REF!,50,0) -> #REF! | R25: =Q25=P25 -> #REF! | S25: Regulatory Affairs Director | T25: =VLOOKUP(D25,#REF!,21,0) -> #REF! | U25: =T25=S25 -> #REF! | V25: 12630168 | W25: =VLOOKUP(D25,#REF!,51,0) -> #REF! | X25: =W25=V25 -> #REF! | Y25: 202502 | Z25: N | AA25: 18.26 | AB25: 109287 | AC25: =ROUND(VLOOKUP(D25,#REF!,59,0),0) -> #REF! | AD25: =AC25-AB25 -> #REF! | AE25: 109287 | AF25: =AB25 -> 109287 | AG25: =AF25-AE25 -> 0 | AH25: 0 | AK25: 0 | AN25: 0 | AO25: 0 | AP25: =IFERROR(VLOOKUP('Feb for check'!D25,#REF!,15,0),0) -> 0 | AQ25: =AP25-AO25 -> 0 | AR25: 0 | AS25: =AO25 -> 0 | AT25: =AS25-AR25 -> 0 | AU25: 0 | AW25: 0 | AY25: 0 | BA25: 4362.63 | BB25: =IFERROR(VLOOKUP(D25,#REF!,2,0),0) -> 0 | BC25: =MAX(VLOOKUP(D25,#REF!,13,0)-VLOOKUP(D25,#REF!,14,0),0) -> #REF! | BD25: =IFERROR(VLOOKUP(D25,#REF!,3,0),0) -> 0 | BE25: =MAX(VLOOKUP(D25,#REF!,22,0)-VLOOKUP(D25,#REF!,23,0),0) -> #REF! | BF25: =BB25*BC25+BD25*BE25 -> #REF! | BG25: =BF25-BA25 -> #REF! | BH25: 0 | BK25: 1834 | BL25: =ROUNDUP(DI25/(1-0.17)*0.17,0) -> 1834 | BM25: =BL25-BK25 -> 0 | BN25: 0 | BR25: 0 | BT25: 0 | BV25: 0 | BX25: 115483.63 | BY25: =SUM(AE25,AH25,AN25,AR25,AU25,AY25,BA25,BH25,BK25,BN25,BR25,BT25) -> 115483.63 | BZ25: =BY25-BX25 -> 0 | CA25: 113649.63 | CB25: =SUM(AE25,AH25,BA25,BH25) -> 113649.63 | CC25: =CB25-CA25 -> 0 | CD25: 0 | CG25: 0 | CI25: 3592.9972 | CJ25: 0.05 | CL25: 0 | CM25: 0.1 | CN25: 0 | CO25: 0 | CP25: 0 | CR25: 0 | CT25: 1500 | CU25: =MIN(BX25*5%,1500) -> 1500 | CV25: =CU25-CT25 -> 0 | CW25: 5682.48 | CX25: =ROUND(CA25*CJ25,2) -> 5682.48 | CY25: =CX25-CW25 -> 0 | CZ25: 1500 | DA25: =MIN(BX25*5%,1500) -> 1500 | DB25: =DA25-CZ25 -> 0 | DC25: 9864.96 | DD25: =MAX(ROUND(CA25*CM25-CZ25,2),0) -> 9864.96 | DE25: =DD25-DC25 -> 0 | DF25: 108301.15 | DG25: =SUM(AE25,AH25,AN25,AR25,AU25,AY25,BA25,BH25,BK25,BN25,BR25,BT25,BV25,-CG25,-CP25,-CT25,-CW25) -> 108301.15 | DH25: =DG25-DF25 -> 0 | DI25: 8951.7 | DJ25: =IFERROR(VLOOKUP(D25,#REF!,2,0),0) -> 0 | DK25: =DJ25-DI25 -> -8951.7 | DL25: 115483.63 | DM25: 1958741.2 | DN25: 9107.25 | DO25: 4362.63 | DP25: 0 | DQ25: 113649.63 | DR25: 28 | DS25: 0 | DT25: 2025-01-01 | DU25: 2025-12-31 | DV25: 2025-01-10 | DW25: 2025-02-10
A26: MSD Asia202502 | B26: MERCK SHARP & DOHME (ASIA) LIMITED | C26: MSD Asia | D26: 51501109 | E26: =VLOOKUP(D26,#REF!,1,0) -> #REF! | F26: Tang | G26: Wai Fan | H26: =G26&" "&F26 -> Wai Fan Tang | I26: =VLOOKUP(D26,#REF!,9,0) -> #REF! | J26: =I26=H26 -> #REF! | K26: Fanny | L26: Active | M26: 2024-09-23 | N26: =VLOOKUP(D26,#REF!,80,0) -> #REF! | O26: =N26-M26 -> #REF! | P26: Human Resources - HK | Q26: =VLOOKUP(D26,#REF!,50,0) -> #REF! | R26: =Q26=P26 -> #REF! | S26: Spclst, HR Business Partner | T26: =VLOOKUP(D26,#REF!,21,0) -> #REF! | U26: =T26=S26 -> #REF! | V26: 12630008 | W26: =VLOOKUP(D26,#REF!,51,0) -> #REF! | X26: =W26=V26 -> #REF! | Y26: 202502 | Z26: N | AA26: 0.44 | AB26: 42500 | AC26: =ROUND(VLOOKUP(D26,#REF!,59,0),0) -> #REF! | AD26: =AC26-AB26 -> #REF! | AE26: 42500 | AF26: =AB26 -> 42500 | AG26: =AF26-AE26 -> 0 | AH26: 0 | AK26: 0 | AN26: 0 | AO26: 0 | AP26: =IFERROR(VLOOKUP('Feb for check'!D26,#REF!,15,0),0) -> 0 | AQ26: =AP26-AO26 -> 0 | AR26: 0 | AS26: =AO26 -> 0 | AT26: =AS26-AR26 -> 0 | AU26: 0 | AW26: 0 | AY26: 0 | BA26: 0 | BB26: =IFERROR(VLOOKUP(D26,#REF!,2,0),0) -> 0 | BC26: =MAX(VLOOKUP(D26,#REF!,13,0)-VLOOKUP(D26,#REF!,14,0),0) -> #REF! | BD26: =IFERROR(VLOOKUP(D26,#REF!,3,0),0) -> 0 | BE26: =MAX(VLOOKUP(D26,#REF!,22,0)-VLOOKUP(D26,#REF!,23,0),0) -> #REF! | BF26: =BB26*BC26+BD26*BE26 -> #REF! | BG26: =BF26-BA26 -> #REF! | BH26: 0 | BK26: 0 | BL26: =ROUNDUP(DI26/(1-0.17)*0.17,0) -> 0 | BM26: =BL26-BK26 -> 0 | BN26: 0 | BR26: 0 | BT26: 0 | BV26: 0 | BX26: 42500 | BY26: =SUM(AE26,AH26,AN26,AR26,AU26,AY26,BA26,BH26,BK26,BN26,BR26,BT26) -> 42500 | BZ26: =BY26-BX26 -> 0 | CA26: 42500 | CB26: =SUM(AE26,AH26,BA26,BH26) -> 42500 | CC26: =CB26-CA26 -> 0 | CD26: 0 | CG26: 0 | CI26: 1397.2602 | CJ26: 0 | CL26: 0 | CM26: 0.075 | CN26: 0 | CO26: 0 | CP26: 0 | CR26: 0 | CT26: 1500 | CU26: =MIN(BX26*5%,1500) -> 1500 | CV26: =CU26-CT26 -> 0 | CW26: 0 | CX26: =ROUND(CA26*CJ26,2) -> 0 | CY26: =CX26-CW26 -> 0 | CZ26: 1500 | DA26: =MIN(BX26*5%,1500) -> 1500 | DB26: =DA26-CZ26 -> 0 | DC26: 1687.5 | DD26: =MAX(ROUND(CA26*CM26-CZ26,2),0) -> 1687.5 | DE26: =DD26-DC26 -> 0 | DF26: 41000 | DG26: =SUM(AE26,AH26,AN26,AR26,AU26,AY26,BA26,BH26,BK26,BN26,BR26,BT26,BV26,-CG26,-CP26,-CT26,-CW26) -> 41000 | DH26: =DG26-DF26 -> 0 | DI26: 0 | DJ26: =IFERROR(VLOOKUP(D26,#REF!,2,0),0) -> 0 | DK26: =DJ26-DI26 -> 0 | DL26: 42500 | DM26: 255036.13 | DN26: 3541.67 | DO26: 0 | DP26: 0 | DQ26: 42500 | DR26: 28 | DS26: 0 | DT26: 2025-01-01 | DU26: 2025-12-31 | DV26: 2025-01-10 | DW26: 2025-02-10
A27: MSD Asia202502 | B27: MERCK SHARP & DOHME (ASIA) LIMITED | C27: MSD Asia | D27: 51417920 | E27: =VLOOKUP(D27,#REF!,1,0) -> #REF! | F27: Chung | G27: Cho Sze | H27: =G27&" "&F27 -> Cho Sze Chung | I27: =VLOOKUP(D27,#REF!,9,0) -> #REF! | J27: =I27=H27 -> #REF! | K27: Jo | L27: Active | M27: 2022-01-17 | N27: =VLOOKUP(D27,#REF!,80,0) -> #REF! | O27: =N27-M27 -> #REF! | P27: Human Resources - HK | Q27: =VLOOKUP(D27,#REF!,50,0) -> #REF! | R27: =Q27=P27 -> #REF! | S27: Human Resources Lead | T27: =VLOOKUP(D27,#REF!,21,0) -> #REF! | U27: =T27=S27 -> #REF! | V27: 12630008 | W27: =VLOOKUP(D27,#REF!,51,0) -> #REF! | X27: =W27=V27 -> #REF! | Y27: 202502 | Z27: N | AA27: 3.12 | AB27: 94279 | AC27: =ROUND(VLOOKUP(D27,#REF!,59,0),0) -> #REF! | AD27: =AC27-AB27 -> #REF! | AE27: 94279 | AF27: =AB27 -> 94279 | AG27: =AF27-AE27 -> 0 | AH27: 0 | AK27: 0 | AN27: 0 | AO27: 0 | AP27: =IFERROR(VLOOKUP('Feb for check'!D27,#REF!,15,0),0) -> 0 | AQ27: =AP27-AO27 -> 0 | AR27: 0 | AS27: =AO27 -> 0 | AT27: =AS27-AR27 -> 0 | AU27: 0 | AW27: 0 | AY27: 0 | BA27: 983.22 | BB27: =IFERROR(VLOOKUP(D27,#REF!,2,0),0) -> 0 | BC27: =MAX(VLOOKUP(D27,#REF!,13,0)-VLOOKUP(D27,#REF!,14,0),0) -> #REF! | BD27: =IFERROR(VLOOKUP(D27,#REF!,3,0),0) -> 0 | BE27: =MAX(VLOOKUP(D27,#REF!,22,0)-VLOOKUP(D27,#REF!,23,0),0) -> #REF! | BF27: =BB27*BC27+BD27*BE27 -> #REF! | BG27: =BF27-BA27 -> #REF! | BH27: 0 | BK27: 2347 | BL27: =ROUNDUP(DI27/(1-0.17)*0.17,0) -> 2347 | BM27: =BL27-BK27 -> 0 | BN27: 0 | BR27: 0 | BT27: 0 | BV27: 0 | BX27: 97609.22 | BY27: =SUM(AE27,AH27,AN27,AR27,AU27,AY27,BA27,BH27,BK27,BN27,BR27,BT27) -> 97609.22 | BZ27: =BY27-BX27 -> 0 | CA27: 95262.22 | CB27: =SUM(AE27,AH27,BA27,BH27) -> 95262.22 | CC27: =CB27-CA27 -> 0 | CD27: 0 | CG27: 0 | CI27: 3099.5835 | CJ27: 0 | CL27: 0 | CM27: 0.075 | CN27: 0 | CO27: 0 | CP27: 0 | CR27: 0 | CT27: 1500 | CU27: =MIN(BX27*5%,1500) -> 1500 | CV27: =CU27-CT27 -> 0 | CW27: 0 | CX27: =ROUND(CA27*CJ27,2) -> 0 | CY27: =CX27-CW27 -> 0 | CZ27: 1500 | DA27: =MIN(BX27*5%,1500) -> 1500 | DB27: =DA27-CZ27 -> 0 | DC27: 5644.67 | DD27: =MAX(ROUND(CA27*CM27-CZ27,2),0) -> 5644.67 | DE27: =DD27-DC27 -> 0 | DF27: 96109.22 | DG27: =SUM(AE27,AH27,AN27,AR27,AU27,AY27,BA27,BH27,BK27,BN27,BR27,BT27,BV27,-CG27,-CP27,-CT27,-CW27) -> 96109.22 | DH27: =DG27-DF27 -> 0 | DI27: 11457.72 | DJ27: =IFERROR(VLOOKUP(D27,#REF!,2,0),0) -> 0 | DK27: =DJ27-DI27 -> -11457.72 | DL27: 97609.22 | DM27: 1584218.8 | DN27: 7856.58 | DO27: 983.22 | DP27: 0 | DQ27: 95262.22 | DR27: 28 | DS27: 0 | DT27: 2025-01-01 | DU27: 2025-12-31 | DV27: 2025-01-10 | DW27: 2025-02-10
A28: MSD Asia202502 | B28: MERCK SHARP & DOHME (ASIA) LIMITED | C28: MSD Asia | D28: 51294969 | E28: =VLOOKUP(D28,#REF!,1,0) -> #REF! | F28: Choi | G28: Tsz Yan | H28: =G28&" "&F28 -> Tsz Yan Choi | I28: =VLOOKUP(D28,#REF!,9,0) -> #REF! | J28: =I28=H28 -> #REF! | K28: Gian | L28: Active | M28: 2017-11-13 | N28: =VLOOKUP(D28,#REF!,80,0) -> #REF! | O28: =N28-M28 -> #REF! | P28: HK Vaccine (DS) | Q28: =VLOOKUP(D28,#REF!,50,0) -> #REF! | R28: =Q28=P28 -> #REF! | S28: Key Account Manager | T28: =VLOOKUP(D28,#REF!,21,0) -> #REF! | U28: =T28=S28 -> #REF! | V28: 12630115 | W28: =VLOOKUP(D28,#REF!,51,0) -> #REF! | X28: =W28=V28 -> #REF! | Y28: 202502 | Z28: N | AA28: 7.3 | AB28: 34993 | AC28: =ROUND(VLOOKUP(D28,#REF!,59,0),0) -> #REF! | AD28: =AC28-AB28 -> #REF! | AE28: 34993 | AF28: =AB28 -> 34993 | AG28: =AF28-AE28 -> 0 | AH28: 0 | AK28: 0 | AN28: 0 | AO28: 2500 | AP28: =IFERROR(VLOOKUP('Feb for check'!D28,#REF!,15,0),0) -> 0 | AQ28: =AP28-AO28 -> -2500 | AR28: 2500 | AS28: =AO28 -> 2500 | AT28: =AS28-AR28 -> 0 | AU28: 0 | AW28: 0 | AY28: 0 | BA28: 257.26 | BB28: =IFERROR(VLOOKUP(D28,#REF!,2,0),0) -> 0 | BC28: =MAX(VLOOKUP(D28,#REF!,13,0)-VLOOKUP(D28,#REF!,14,0),0) -> #REF! | BD28: =IFERROR(VLOOKUP(D28,#REF!,3,0),0) -> 0 | BE28: =MAX(VLOOKUP(D28,#REF!,22,0)-VLOOKUP(D28,#REF!,23,0),0) -> #REF! | BF28: =BB28*BC28+BD28*BE28 -> #REF! | BG28: =BF28-BA28 -> #REF! | BH28: 0 | BK28: 0 | BL28: =ROUNDUP(DI28/(1-0.17)*0.17,0) -> 0 | BM28: =BL28-BK28 -> 0 | BN28: 0 | BR28: 0 | BT28: 0 | BV28: 0 | BX28: 37750.26 | BY28: =SUM(AE28,AH28,AN28,AR28,AU28,AY28,BA28,BH28,BK28,BN28,BR28,BT28) -> 37750.26 | BZ28: =BY28-BX28 -> 0 | CA28: 35250.26 | CB28: =SUM(AE28,AH28,BA28,BH28) -> 35250.26 | CC28: =CB28-CA28 -> 0 | CD28: 0 | CG28: 0 | CI28: 1232.6465 | CJ28: 0.04 | CL28: 0 | CM28: 0.095 | CN28: 0 | CO28: 0 | CP28: 0 | CR28: 0 | CT28: 1500 | CU28: =MIN(BX28*5%,1500) -> 1500 | CV28: =CU28-CT28 -> 0 | CW28: 1410.01 | CX28: =ROUND(CA28*CJ28,2) -> 1410.01 | CY28: =CX28-CW28 -> 0 | CZ28: 1500 | DA28: =MIN(BX28*5%,1500) -> 1500 | DB28: =DA28-CZ28 -> 0 | DC28: 1848.77 | DD28: =MAX(ROUND(CA28*CM28-CZ28,2),0) -> 1848.77 | DE28: =DD28-DC28 -> 0 | DF28: 34840.25 | DG28: =SUM(AE28,AH28,AN28,AR28,AU28,AY28,BA28,BH28,BK28,BN28,BR28,BT28,BV28,-CG28,-CP28,-CT28,-CW28) -> 34840.25 | DH28: =DG28-DF28 -> 0 | DI28: 0 | DJ28: =IFERROR(VLOOKUP(D28,#REF!,2,0),0) -> 0 | DK28: =DJ28-DI28 -> 0 | DL28: 35250.26 | DM28: 656028.2 | DN28: 2916.08 | DO28: 257.26 | DP28: 0 | DQ28: 37750.26 | DR28: 28 | DS28: 0 | DT28: 2025-01-01 | DU28: 2025-12-31 | DV28: 2025-01-10 | DW28: 2025-02-10
A29: MSD Asia202502 | B29: MERCK SHARP & DOHME (ASIA) LIMITED | C29: MSD Asia | D29: 51507640 | E29: =VLOOKUP(D29,#REF!,1,0) -> #REF! | F29: Chan | G29: Yu Ki | H29: =G29&" "&F29 -> Yu Ki Chan | I29: =VLOOKUP(D29,#REF!,9,0) -> #REF! | J29: =I29=H29 -> #REF! | K29: Jacky | L29: Active | M29: 2025-01-03 | N29: =VLOOKUP(D29,#REF!,80,0) -> #REF! | O29: =N29-M29 -> #REF! | P29: HK Direct Selling - Oncology | Q29: =VLOOKUP(D29,#REF!,50,0) -> #REF! | R29: =Q29=P29 -> #REF! | S29: Sr. Customer Rep., Sales ONC | T29: =VLOOKUP(D29,#REF!,21,0) -> #REF! | U29: =T29=S29 -> #REF! | V29: 12630118 | W29: =VLOOKUP(D29,#REF!,51,0) -> #REF! | X29: =W29=V29 -> #REF! | Y29: 202502 | Z29: N | AA29: 0.16 | AB29: 49200 | AC29: =ROUND(VLOOKUP(D29,#REF!,59,0),0) -> #REF! | AD29: =AC29-AB29 -> #REF! | AE29: 49200 | AF29: =AB29 -> 49200 | AG29: =AF29-AE29 -> 0 | AH29: 0 | AK29: 0 | AN29: 0 | AO29: 2500 | AP29: =IFERROR(VLOOKUP('Feb for check'!D29,#REF!,15,0),0) -> 0 | AQ29: =AP29-AO29 -> -2500 | AR29: 2500 | AS29: =AO29 -> 2500 | AT29: =AS29-AR29 -> 0 | AU29: 0 | AW29: 0 | AY29: 0 | BA29: 0 | BB29: =IFERROR(VLOOKUP(D29,#REF!,2,0),0) -> 0 | BC29: =MAX(VLOOKUP(D29,#REF!,13,0)-VLOOKUP(D29,#REF!,14,0),0) -> #REF! | BD29: =IFERROR(VLOOKUP(D29,#REF!,3,0),0) -> 0 | BE29: =MAX(VLOOKUP(D29,#REF!,22,0)-VLOOKUP(D29,#REF!,23,0),0) -> #REF! | BF29: =BB29*BC29+BD29*BE29 -> #REF! | BG29: =BF29-BA29 -> #REF! | BH29: 0 | BK29: 0 | BL29: =ROUNDUP(DI29/(1-0.17)*0.17,0) -> 0 | BM29: =BL29-BK29 -> 0 | BN29: 0 | BR29: 0 | BT29: 5815.62 | BU29: =VLOOKUP(D29,#REF!,28,0) -> #REF! | BV29: 0 | BX29: 57515.62 | BY29: =SUM(AE29,AH29,AN29,AR29,AU29,AY29,BA29,BH29,BK29,BN29,BR29,BT29) -> 57515.62 | BZ29: =BY29-BX29 -> 0 | CA29: 49200 | CB29: =SUM(AE29,AH29,BA29,BH29) -> 49200 | CC29: =CB29-CA29 -> 0 | CD29: 0 | CG29: 0 | CI29: 1699.726 | CJ29: 0 | CL29: 0 | CM29: 0.075 | CN29: 0 | CO29: 0 | CP29: 0 | CR29: 0 | CT29: 0 | CU29: =MIN(BX29*5%,1500) -> 1500 | CV29: 新员工，未满60天不缴纳 | CW29: 0 | CX29: =ROUND(CA29*CJ29,2) -> 0 | CY29: =CX29-CW29 -> 0 | CZ29: 0 | DA29: =MIN(BX29*5%,1500) -> 1500 | DB29: 新员工，未满60天不缴纳 | DC29: 0 | DD29: =MAX(ROUND(CA29*CM29-CZ29,2),0) -> 3690 | DE29: 新员工，未满60天不缴纳 | DF29: 57515.62 | DG29: =SUM(AE29,AH29,AN29,AR29,AU29,AY29,BA29,BH29,BK29,BN29,BR29,BT29,BV29,-CG29,-CP29,-CT29,-CW29) -> 57515.62 | DH29: =DG29-DF29 -> 0 | DI29: 0 | DJ29: =IFERROR(VLOOKUP(D29,#REF!,2,0),0) -> 0 | DK29: =DJ29-DI29 -> 0 | DL29: 55015.62 | DM29: 101429.43 | DN29: 4100 | DO29: 0 | DP29: 0 | DQ29: 51700 | DR29: 28 | DS29: 0 | DT29: 2025-01-03 | DU29: 2025-12-31 | DV29: 2025-01-10 | DW29: 2025-02-10
A30: MSD Asia202502 | B30: MERCK SHARP & DOHME (ASIA) LIMITED | C30: MSD Asia | D30: 51444085 | E30: =VLOOKUP(D30,#REF!,1,0) -> #REF! | F30: So | G30: Kam Wing | H30: =G30&" "&F30 -> Kam Wing So | I30: =VLOOKUP(D30,#REF!,9,0) -> #REF! | J30: =I30=H30 -> #REF! | K30: Billy | L30: Active | M30: 2022-10-03 | N30: =VLOOKUP(D30,#REF!,80,0) -> #REF! | O30: =N30-M30 -> #REF! | P30: HK Vaccine (DS) | Q30: =VLOOKUP(D30,#REF!,50,0) -> #REF! | R30: =Q30=P30 -> #REF! | S30: Associate Sales Manager | T30: =VLOOKUP(D30,#REF!,21,0) -> #REF! | U30: =T30=S30 -> #REF! | V30: 12630115 | W30: =VLOOKUP(D30,#REF!,51,0) -> #REF! | X30: =W30=V30 -> #REF! | Y30: 202502 | Z30: N | AA30: 2.41 | AB30: 47978 | AC30: =ROUND(VLOOKUP(D30,#REF!,59,0),0) -> #REF! | AD30: =AC30-AB30 -> #REF! | AE30: 47978 | AF30: =AB30 -> 47978 | AG30: =AF30-AE30 -> 0 | AH30: 0 | AK30: 0 | AN30: 0 | AO30: 2500 | AP30: =IFERROR(VLOOKUP('Feb for check'!D30,#REF!,15,0),0) -> 0 | AQ30: =AP30-AO30 -> -2500 | AR30: 2500 | AS30: =AO30 -> 2500 | AT30: =AS30-AR30 -> 0 | AU30: 0 | AW30: 0 | AY30: 0 | BA30: 714.12 | BB30: =IFERROR(VLOOKUP(D30,#REF!,2,0),0) -> 0 | BC30: =MAX(VLOOKUP(D30,#REF!,13,0)-VLOOKUP(D30,#REF!,14,0),0) -> #REF! | BD30: =IFERROR(VLOOKUP(D30,#REF!,3,0),0) -> 0 | BE30: =MAX(VLOOKUP(D30,#REF!,22,0)-VLOOKUP(D30,#REF!,23,0),0) -> #REF! | BF30: =BB30*BC30+BD30*BE30 -> #REF! | BG30: =BF30-BA30 -> #REF! | BH30: 0 | BK30: 0 | BL30: =ROUNDUP(DI30/(1-0.17)*0.17,0) -> 0 | BM30: =BL30-BK30 -> 0 | BN30: 0 | BR30: 0 | BT30: 0 | BV30: 0 | BX30: 51192.12 | BY30: =SUM(AE30,AH30,AN30,AR30,AU30,AY30,BA30,BH30,BK30,BN30,BR30,BT30) -> 51192.12 | BZ30: =BY30-BX30 -> 0 | CA30: 48692.12 | CB30: =SUM(AE30,AH30,BA30,BH30) -> 48692.12 | CC30: =CB30-CA30 -> 0 | CD30: 0 | CG30: 0 | CI30: 1659.5506 | CJ30: 0 | CL30: 0 | CM30: 0.075 | CN30: 0 | CO30: 0 | CP30: 0 | CR30: 0 | CT30: 1500 | CU30: =MIN(BX30*5%,1500) -> 1500 | CV30: =CU30-CT30 -> 0 | CW30: 0 | CX30: =ROUND(CA30*CJ30,2) -> 0 | CY30: =CX30-CW30 -> 0 | CZ30: 1500 | DA30: =MIN(BX30*5%,1500) -> 1500 | DB30: =DA30-CZ30 -> 0 | DC30: 2151.91 | DD30: =MAX(ROUND(CA30*CM30-CZ30,2),0) -> 2151.91 | DE30: =DD30-DC30 -> 0 | DF30: 49692.12 | DG30: =SUM(AE30,AH30,AN30,AR30,AU30,AY30,BA30,BH30,BK30,BN30,BR30,BT30,BV30,-CG30,-CP30,-CT30,-CW30) -> 49692.12 | DH30: =DG30-DF30 -> 0 | DI30: 0 | DJ30: =IFERROR(VLOOKUP(D30,#REF!,2,0),0) -> 0 | DK30: =DJ30-DI30 -> 0 | DL30: 48692.12 | DM30: 844291.21 | DN30: 3998.17 | DO30: 714.12 | DP30: 0 | DQ30: 51192.12 | DR30: 28 | DS30: 0 | DT30: 2025-01-01 | DU30: 2025-12-31 | DV30: 2025-01-10 | DW30: 2025-02-10
A31: MSD Asia202502 | B31: MERCK SHARP & DOHME (ASIA) LIMITED | C31: MSD Asia | D31: 51428359 | E31: =VLOOKUP(D31,#REF!,1,0) -> #REF! | F31: Tang | G31: Siu Kwan | H31: =G31&" "&F31 -> Siu Kwan Tang | I31: =VLOOKUP(D31,#REF!,9,0) -> #REF! | J31: =I31=H31 -> #REF! | K31: Delius | L31: Active | M31: 2022-05-30 | N31: =VLOOKUP(D31,#REF!,80,0) -> #REF! | O31: =N31-M31 -> #REF! | P31: GLOBAL FRANCHISES-ONCOLOGY | Q31: =VLOOKUP(D31,#REF!,50,0) -> #REF! | R31: =Q31=P31 -> #REF! | S31: Assoc. Dir, Regional Marketing ONC | T31: =VLOOKUP(D31,#REF!,21,0) -> #REF! | U31: =T31=S31 -> #REF! | V31: 12630044 | W31: =VLOOKUP(D31,#REF!,51,0) -> #REF! | X31: =W31=V31 -> #REF! | Y31: 202502 | Z31: N | AA31: 2.75 | AB31: 66156 | AC31: =ROUND(VLOOKUP(D31,#REF!,59,0),0) -> #REF! | AD31: =AC31-AB31 -> #REF! | AE31: 66156 | AF31: =AB31 -> 66156 | AG31: =AF31-AE31 -> 0 | AH31: 0 | AK31: 0 | AN31: 0 | AO31: 0 | AP31: =IFERROR(VLOOKUP('Feb for check'!D31,#REF!,15,0),0) -> 0 | AQ31: =AP31-AO31 -> 0 | AR31: 0 | AS31: =AO31 -> 0 | AT31: =AS31-AR31 -> 0 | AU31: 0 | AW31: 0 | AY31: 0 | BA31: 0 | BB31: =IFERROR(VLOOKUP(D31,#REF!,2,0),0) -> 0 | BC31: =MAX(VLOOKUP(D31,#REF!,13,0)-VLOOKUP(D31,#REF!,14,0),0) -> #REF! | BD31: =IFERROR(VLOOKUP(D31,#REF!,3,0),0) -> 0 | BE31: =MAX(VLOOKUP(D31,#REF!,22,0)-VLOOKUP(D31,#REF!,23,0),0) -> #REF! | BF31: =BB31*BC31+BD31*BE31 -> #REF! | BG31: =BF31-BA31 -> #REF! | BH31: 0 | BK31: 0 | BL31: =ROUNDUP(DI31/(1-0.17)*0.17,0) -> 0 | BM31: =BL31-BK31 -> 0 | BN31: 0 | BR31: 0 | BT31: 0 | BV31: 0 | BX31: 66156 | BY31: =SUM(AE31,AH31,AN31,AR31,AU31,AY31,BA31,BH31,BK31,BN31,BR31,BT31) -> 66156 | BZ31: =BY31-BX31 -> 0 | CA31: 66156 | CB31: =SUM(AE31,AH31,BA31,BH31) -> 66156 | CC31: =CB31-CA31 -> 0 | CD31: 0 | CG31: 0 | CI31: 2174.9917 | CJ31: 0 | CL31: 0 | CM31: 0.075 | CN31: 0 | CO31: 0 | CP31: 0 | CR31: 0 | CT31: 1500 | CU31: =MIN(BX31*5%,1500) -> 1500 | CV31: =CU31-CT31 -> 0 | CW31: 0 | CX31: =ROUND(CA31*CJ31,2) -> 0 | CY31: =CX31-CW31 -> 0 | CZ31: 1500 | DA31: =MIN(BX31*5%,1500) -> 1500 | DB31: =DA31-CZ31 -> 0 | DC31: 3461.7 | DD31: =MAX(ROUND(CA31*CM31-CZ31,2),0) -> 3461.7 | DE31: =DD31-DC31 -> 0 | DF31: 64656 | DG31: =SUM(AE31,AH31,AN31,AR31,AU31,AY31,BA31,BH31,BK31,BN31,BR31,BT31,BV31,-CG31,-CP31,-CT31,-CW31) -> 64656 | DH31: =DG31-DF31 -> 0 | DI31: 0 | DJ31: =IFERROR(VLOOKUP(D31,#REF!,2,0),0) -> 0 | DK31: =DJ31-DI31 -> 0 | DL31: 66156 | DM31: 1060978.9 | DN31: 5513 | DO31: 0 | DP31: 0 | DQ31: 66156 | DR31: 28 | DS31: 0 | DT31: 2025-01-01 | DU31: 2025-12-31 | DV31: 2025-01-10 | DW31: 2025-02-10
A32: MSD Asia202502 | B32: MERCK SHARP & DOHME (ASIA) LIMITED | C32: MSD Asia | D32: 51455003 | E32: =VLOOKUP(D32,#REF!,1,0) -> #REF! | F32: Chu | G32: Man Kee | H32: =G32&" "&F32 -> Man Kee Chu | I32: =VLOOKUP(D32,#REF!,9,0) -> #REF! | J32: =I32=H32 -> #REF! | K32: Maggie | L32: Active | M32: 2023-03-01 | N32: =VLOOKUP(D32,#REF!,80,0) -> #REF! | O32: =N32-M32 -> #REF! | P32: CAS-HONG KONG | Q32: =VLOOKUP(D32,#REF!,50,0) -> #REF! | R32: =Q32=P32 -> #REF! | S32: Lead, Business Insights & Activation, HHDDA Hong Kong & India | T32: =VLOOKUP(D32,#REF!,21,0) -> #REF! | U32: =T32=S32 -> #REF! | V32: 12630420 | W32: =VLOOKUP(D32,#REF!,51,0) -> #REF! | X32: =W32=V32 -> #REF! | Y32: 202502 | Z32: N | AA32: 2 | AB32: 99621.62 | AC32: =ROUND(VLOOKUP(D32,#REF!,59,0),0) -> #REF! | AD32: =AC32-AB32 -> #REF! | AE32: 102523.24 | AF32: =AB32+AB32-VLOOKUP(D32,#REF!,14,0) -> #REF! | AG32: =AF32-AE32 -> #REF! | AH32: 0 | AK32: 0 | AN32: 0 | AO32: 0 | AP32: =IFERROR(VLOOKUP('Feb for check'!D32,#REF!,15,0),0) -> 0 | AQ32: =AP32-AO32 -> 0 | AR32: 0 | AS32: =AO32 -> 0 | AT32: =AS32-AR32 -> 0 | AU32: 0 | AW32: 0 | AY32: 0 | BA32: 0 | BB32: =IFERROR(VLOOKUP(D32,#REF!,2,0),0) -> 0 | BC32: =MAX(VLOOKUP(D32,#REF!,13,0)-VLOOKUP(D32,#REF!,14,0),0) -> #REF! | BD32: =IFERROR(VLOOKUP(D32,#REF!,3,0),0) -> 0 | BE32: =MAX(VLOOKUP(D32,#REF!,22,0)-VLOOKUP(D32,#REF!,23,0),0) -> #REF! | BF32: =BB32*BC32+BD32*BE32 -> #REF! | BG32: =BF32-BA32 -> #REF! | BH32: 0 | BK32: 917 | BL32: =ROUNDUP(DI32/(1-0.17)*0.17,0) -> 917 | BM32: =BL32-BK32 -> 0 | BN32: 0 | BR32: 0 | BT32: 0 | BV32: 0 | BX32: 103440.24 | BY32: =SUM(AE32,AH32,AN32,AR32,AU32,AY32,BA32,BH32,BK32,BN32,BR32,BT32) -> 103440.24 | BZ32: =BY32-BX32 -> 0 | CA32: 102523.24 | CB32: =SUM(AE32,AH32,BA32,BH32) -> 102523.24 | CC32: =CB32-CA32 -> 0 | CD32: 0 | CG32: 0 | CI32: 3179.8356 | CJ32: 0.05 | CL32: 0 | CM32: 0.1 | CN32: 0 | CO32: 0 | CP32: 0 | CR32: 0 | CT32: 1500 | CU32: =MIN(BX32*5%,1500) -> 1500 | CV32: =CU32-CT32 -> 0 | CW32: 5126.16 | CX32: =ROUND(CA32*CJ32,2) -> 5126.16 | CY32: =CX32-CW32 -> 0 | CZ32: 1500 | DA32: =MIN(BX32*5%,1500) -> 1500 | DB32: =DA32-CZ32 -> 0 | DC32: 8752.32 | DD32: =MAX(ROUND(CA32*CM32-CZ32,2),0) -> 8752.32 | DE32: =DD32-DC32 -> 0 | DF32: 96814.08 | DG32: =SUM(AE32,AH32,AN32,AR32,AU32,AY32,BA32,BH32,BK32,BN32,BR32,BT32,BV32,-CG32,-CP32,-CT32,-CW32) -> 96814.08 | DH32: =DG32-DF32 -> 0 | DI32: 4475.85 | DJ32: =IFERROR(VLOOKUP(D32,#REF!,2,0),0) -> 0 | DK32: =DJ32-DI32 -> -4475.85 | DL32: 103440.24 | DM32: 1571895.4 | DN32: 8301.8 | DO32: 0 | DP32: 0 | DQ32: 102523.24 | DR32: 28 | DS32: 0 | DT32: 2025-01-01 | DU32: 2025-12-31 | DV32: 2025-01-10 | DW32: 2025-02-10
A33: MSD Asia202502 | B33: MERCK SHARP & DOHME (ASIA) LIMITED | C33: MSD Asia | D33: 51246689 | E33: =VLOOKUP(D33,#REF!,1,0) -> #REF! | F33: Loo | G33: Lok Hang | H33: =G33&" "&F33 -> Lok Hang Loo | I33: =VLOOKUP(D33,#REF!,9,0) -> #REF! | J33: =I33=H33 -> #REF! | K33: Jacky | L33: Active | M33: 2016-03-07 | N33: =VLOOKUP(D33,#REF!,80,0) -> #REF! | O33: =N33-M33 -> #REF! | P33: HK Public Sector Access | Q33: =VLOOKUP(D33,#REF!,50,0) -> #REF! | R33: =Q33=P33 -> #REF! | S33: Market Access Manager | T33: =VLOOKUP(D33,#REF!,21,0) -> #REF! | U33: =T33=S33 -> #REF! | V33: 12630108 | W33: =VLOOKUP(D33,#REF!,51,0) -> #REF! | X33: =W33=V33 -> #REF! | Y33: 202502 | Z33: N | AA33: 8.98 | AB33: 57403 | AC33: =ROUND(VLOOKUP(D33,#REF!,59,0),0) -> #REF! | AD33: =AC33-AB33 -> #REF! | AE33: 57403 | AF33: =AB33 -> 57403 | AG33: =AF33-AE33 -> 0 | AH33: 0 | AK33: 0 | AN33: 0 | AO33: 0 | AP33: =IFERROR(VLOOKUP('Feb for check'!D33,#REF!,15,0),0) -> 0 | AQ33: =AP33-AO33 -> 0 | AR33: 0 | AS33: =AO33 -> 0 | AT33: =AS33-AR33 -> 0 | AU33: 0 | AW33: 0 | AY33: 0 | BA33: 0 | BB33: =IFERROR(VLOOKUP(D33,#REF!,2,0),0) -> 0 | BC33: =MAX(VLOOKUP(D33,#REF!,13,0)-VLOOKUP(D33,#REF!,14,0),0) -> #REF! | BD33: =IFERROR(VLOOKUP(D33,#REF!,3,0),0) -> 0 | BE33: =MAX(VLOOKUP(D33,#REF!,22,0)-VLOOKUP(D33,#REF!,23,0),0) -> #REF! | BF33: =BB33*BC33+BD33*BE33 -> #REF! | BG33: =BF33-BA33 -> #REF! | BH33: 0 | BK33: 55 | BL33: =ROUNDUP(DI33/(1-0.17)*0.17,0) -> 55 | BM33: =BL33-BK33 -> 0 | BN33: 0 | BR33: 0 | BT33: 0 | BV33: 0 | BX33: 57458 | BY33: =SUM(AE33,AH33,AN33,AR33,AU33,AY33,BA33,BH33,BK33,BN33,BR33,BT33) -> 57458 | BZ33: =BY33-BX33 -> 0 | CA33: 57403 | CB33: =SUM(AE33,AH33,BA33,BH33) -> 57403 | CC33: =CB33-CA33 -> 0 | CD33: 0 | CG33: 0 | CI33: 1887.2219 | CJ33: 0 | CL33: 0 | CM33: 0.075 | CN33: 0 | CO33: 0 | CP33: 0 | CR33: 0 | CT33: 1500 | CU33: =MIN(BX33*5%,1500) -> 1500 | CV33: =CU33-CT33 -> 0 | CW33: 0 | CX33: =ROUND(CA33*CJ33,2) -> 0 | CY33: =CX33-CW33 -> 0 | CZ33: 1500 | DA33: =MIN(BX33*5%,1500) -> 1500 | DB33: =DA33-CZ33 -> 0 | DC33: 2805.23 | DD33: =MAX(ROUND(CA33*CM33-CZ33,2),0) -> 2805.23 | DE33: =DD33-DC33 -> 0 | DF33: 55958 | DG33: =SUM(AE33,AH33,AN33,AR33,AU33,AY33,BA33,BH33,BK33,BN33,BR33,BT33,BV33,-CG33,-CP33,-CT33,-CW33) -> 55958 | DH33: =DG33-DF33 -> 0 | DI33: 268.1 | DJ33: =IFERROR(VLOOKUP(D33,#REF!,2,0),0) -> 0 | DK33: =DJ33-DI33 -> -268.1 | DL33: 57458 | DM33: 957613.17 | DN33: 4783.58 | DO33: 0 | DP33: 0 | DQ33: 57403 | DR33: 28 | DS33: 0 | DT33: 2025-01-01 | DU33: 2025-12-31 | DV33: 2025-01-10 | DW33: 2025-02-10
A34: MSD Asia202502 | B34: MERCK SHARP & DOHME (ASIA) LIMITED | C34: MSD Asia | D34: 51358175 | E34: =VLOOKUP(D34,#REF!,1,0) -> #REF! | F34: Lai | G34: Kit Sum | H34: =G34&" "&F34 -> Kit Sum Lai | I34: =VLOOKUP(D34,#REF!,9,0) -> #REF! | J34: =I34=H34 -> #REF! | K34: Sammi | L34: Active | M34: 2023-09-25 | N34: =VLOOKUP(D34,#REF!,80,0) -> #REF! | O34: =N34-M34 -> #REF! | P34: HK Comm Oper (SA) | Q34: =VLOOKUP(D34,#REF!,50,0) -> #REF! | R34: =Q34=P34 -> #REF! | S34: Administrative Associate | T34: =VLOOKUP(D34,#REF!,21,0) -> #REF! | U34: =T34=S34 -> #REF! | V34: 12630222 | W34: =VLOOKUP(D34,#REF!,51,0) -> #REF! | X34: =W34=V34 -> #REF! | Y34: 202502 | Z34: N | AA34: 1.43 | AB34: 27693 | AC34: =ROUND(VLOOKUP(D34,#REF!,59,0),0) -> #REF! | AD34: =AC34-AB34 -> #REF! | AE34: 27693 | AF34: =AB34 -> 27693 | AG34: =AF34-AE34 -> 0 | AH34: 0 | AK34: 0 | AN34: 0 | AO34: 0 | AP34: =IFERROR(VLOOKUP('Feb for check'!D34,#REF!,15,0),0) -> 0 | AQ34: =AP34-AO34 -> 0 | AR34: 0 | AS34: =AO34 -> 0 | AT34: =AS34-AR34 -> 0 | AU34: 0 | AW34: 0 | AY34: 0 | BA34: 35.99 | BB34: =IFERROR(VLOOKUP(D34,#REF!,2,0),0) -> 0 | BC34: =MAX(VLOOKUP(D34,#REF!,13,0)-VLOOKUP(D34,#REF!,14,0),0) -> #REF! | BD34: =IFERROR(VLOOKUP(D34,#REF!,3,0),0) -> 0 | BE34: =MAX(VLOOKUP(D34,#REF!,22,0)-VLOOKUP(D34,#REF!,23,0),0) -> #REF! | BF34: =BB34*BC34+BD34*BE34 -> #REF! | BG34: =BF34-BA34 -> #REF! | BH34: 0 | BK34: 0 | BL34: =ROUNDUP(DI34/(1-0.17)*0.17,0) -> 0 | BM34: =BL34-BK34 -> 0 | BN34: 0 | BR34: 0 | BT34: 0 | BV34: 0 | BX34: 27728.99 | BY34: =SUM(AE34,AH34,AN34,AR34,AU34,AY34,BA34,BH34,BK34,BN34,BR34,BT34) -> 27728.99 | BZ34: =BY34-BX34 -> 0 | CA34: 27728.99 | CB34: =SUM(AE34,AH34,BA34,BH34) -> 27728.99 | CC34: =CB34-CA34 -> 0 | CD34: 0 | CG34: 0 | CI34: 910.4547 | CJ34: 0 | CL34: 0 | CM34: 0.075 | CN34: 0 | CO34: 0 | CP34: 0 | CR34: 0 | CT34: 1386.45 | CU34: =MIN(BX34*5%,1500) -> 1386.4495 | CV34: =CU34-CT34 -> -0.0005 | CW34: 0 | CX34: =ROUND(CA34*CJ34,2) -> 0 | CY34: =CX34-CW34 -> 0 | CZ34: 1386.45 | DA34: =MIN(BX34*5%,1500) -> 1386.4495 | DB34: =DA34-CZ34 -> -0.0005 | DC34: 693.22 | DD34: =MAX(ROUND(CA34*CM34-CZ34,2),0) -> 693.22 | DE34: =DD34-DC34 -> 0 | DF34: 26342.54 | DG34: =SUM(AE34,AH34,AN34,AR34,AU34,AY34,BA34,BH34,BK34,BN34,BR34,BT34,BV34,-CG34,-CP34,-CT34,-CW34) -> 26342.54 | DH34: =DG34-DF34 -> 0 | DI34: 0 | DJ34: =IFERROR(VLOOKUP(D34,#REF!,2,0),0) -> 0 | DK34: =DJ34-DI34 -> 0 | DL34: 27728.99 | DM34: 370750.2 | DN34: 2307.75 | DO34: 35.99 | DP34: 0 | DQ34: 27728.99 | DR34: 28 | DS34: 0 | DT34: 2025-01-01 | DU34: 2025-12-31 | DV34: 2025-01-10 | DW34: 2025-02-10
A35: MSD Asia202502 | B35: MERCK SHARP & DOHME (ASIA) LIMITED | C35: MSD Asia | D35: 51251255 | E35: =VLOOKUP(D35,#REF!,1,0) -> #REF! | F35: Wong | G35: Lok Yee | H35: =G35&" "&F35 -> Lok Yee Wong | I35: =VLOOKUP(D35,#REF!,9,0) -> #REF! | J35: =I35=H35 -> #REF! | K35: Anna | L35: Active | M35: 2016-07-04 | N35: =VLOOKUP(D35,#REF!,80,0) -> #REF! | O35: Follow Payroll system date | P35: MRL HKG REG AFFAIRS OPS | Q35: =VLOOKUP(D35,#REF!,50,0) -> #REF! | R35: =Q35=P35 -> #REF! | S35: Regional Labeling Liaison | T35: =VLOOKUP(D35,#REF!,21,0) -> #REF! | U35: =T35=S35 -> #REF! | V35: 12630408 | W35: =VLOOKUP(D35,#REF!,51,0) -> #REF! | X35: =W35=V35 -> #REF! | Y35: 202502 | Z35: N | AA35: 8.66 | AB35: 40534 | AC35: =ROUND(VLOOKUP(D35,#REF!,59,0),0) -> #REF! | AD35: =AC35-AB35 -> #REF! | AE35: 40534 | AF35: =AB35 -> 40534 | AG35: =AF35-AE35 -> 0 | AH35: 0 | AK35: 0 | AN35: 0 | AO35: 0 | AP35: =IFERROR(VLOOKUP('Feb for check'!D35,#REF!,15,0),0) -> 0 | AQ35: =AP35-AO35 -> 0 | AR35: 0 | AS35: =AO35 -> 0 | AT35: =AS35-AR35 -> 0 | AU35: 0 | AW35: 0 | AY35: 0 | BA35: 1008.33 | BB35: =IFERROR(VLOOKUP(D35,#REF!,2,0),0) -> 0 | BC35: =MAX(VLOOKUP(D35,#REF!,13,0)-VLOOKUP(D35,#REF!,14,0),0) -> #REF! | BD35: =IFERROR(VLOOKUP(D35,#REF!,3,0),0) -> 0 | BE35: =MAX(VLOOKUP(D35,#REF!,22,0)-VLOOKUP(D35,#REF!,23,0),0) -> #REF! | BF35: =BB35*BC35+BD35*BE35 -> #REF! | BG35: =BF35-BA35 -> #REF! | BH35: 0 | BK35: 1596 | BL35: =ROUNDUP(DI35/(1-0.17)*0.17,0) -> 1596 | BM35: =BL35-BK35 -> 0 | BN35: 0 | BR35: 0 | BT35: 0 | BV35: 0 | BX35: 43138.33 | BY35: =SUM(AE35,AH35,AN35,AR35,AU35,AY35,BA35,BH35,BK35,BN35,BR35,BT35) -> 43138.33 | BZ35: =BY35-BX35 -> 0 | CA35: 41542.33 | CB35: =SUM(AE35,AH35,BA35,BH35) -> 41542.33 | CC35: =CB35-CA35 -> 0 | CD35: 0 | CG35: 0 | CI35: 1332.6246 | CJ35: 0 | CL35: 0 | CM35: 0.075 | CN35: 0 | CO35: 0 | CP35: 0 | CR35: 0 | CT35: 1500 | CU35: =MIN(BX35*5%,1500) -> 1500 | CV35: =CU35-CT35 -> 0 | CW35: 0 | CX35: =ROUND(CA35*CJ35,2) -> 0 | CY35: =CX35-CW35 -> 0 | CZ35: 1500 | DA35: =MIN(BX35*5%,1500) -> 1500 | DB35: =DA35-CZ35 -> 0 | DC35: 1615.67 | DD35: =MAX(ROUND(CA35*CM35-CZ35,2),0) -> 1615.67 | DE35: =DD35-DC35 -> 0 | DF35: 41638.33 | DG35: =SUM(AE35,AH35,AN35,AR35,AU35,AY35,BA35,BH35,BK35,BN35,BR35,BT35,BV35,-CG35,-CP35,-CT35,-CW35) -> 41638.33 | DH35: =DG35-DF35 -> 0 | DI35: 7789.91 | DJ35: =IFERROR(VLOOKUP(D35,#REF!,2,0),0) -> 0 | DK35: =DJ35-DI35 -> -7789.91 | DL35: 43138.33 | DM35: 656434.3 | DN35: 3377.83 | DO35: 1008.33 | DP35: 0 | DQ35: 41542.33 | DR35: 28 | DS35: 0 | DT35: 2025-01-01 | DU35: 2025-12-31 | DV35: 2025-01-10 | DW35: 2025-02-10
A36: MSD Asia202502 | B36: MERCK SHARP & DOHME (ASIA) LIMITED | C36: MSD Asia | D36: 51190702 | E36: =VLOOKUP(D36,#REF!,1,0) -> #REF! | F36: Huang | G36: Lan | H36: =G36&" "&F36 -> Lan Huang | I36: =VLOOKUP(D36,#REF!,9,0) -> #REF! | J36: =I36=H36 -> #REF! | K36: Lan | L36: Active | M36: 2022-10-17 | N36: =VLOOKUP(D36,#REF!,80,0) -> #REF! | O36: Follow Payroll system date | P36: Finance - HK | Q36: =VLOOKUP(D36,#REF!,50,0) -> #REF! | R36: =Q36=P36 -> #REF! | S36: Dir, Finance | T36: =VLOOKUP(D36,#REF!,21,0) -> #REF! | U36: =T36=S36 -> #REF! | V36: 12630016 | W36: =VLOOKUP(D36,#REF!,51,0) -> #REF! | X36: =W36=V36 -> #REF! | Y36: 202502 | Z36: N | AA36: 10.91 | AB36: 96106 | AC36: =ROUND(VLOOKUP(D36,#REF!,59,0),0) -> #REF! | AD36: =AC36-AB36 -> #REF! | AE36: 96106 | AF36: =AB36 -> 96106 | AG36: =AF36-AE36 -> 0 | AH36: 0 | AK36: 0 | AN36: 0 | AO36: 0 | AP36: =IFERROR(VLOOKUP('Feb for check'!D36,#REF!,15,0),0) -> 0 | AQ36: =AP36-AO36 -> 0 | AR36: 0 | AS36: =AO36 -> 0 | AT36: =AS36-AR36 -> 0 | AU36: 0 | AW36: 0 | AY36: 0 | BA36: 4181.31 | BB36: =IFERROR(VLOOKUP(D36,#REF!,2,0),0) -> 0 | BC36: =MAX(VLOOKUP(D36,#REF!,13,0)-VLOOKUP(D36,#REF!,14,0),0) -> #REF! | BD36: =IFERROR(VLOOKUP(D36,#REF!,3,0),0) -> 0 | BE36: =MAX(VLOOKUP(D36,#REF!,22,0)-VLOOKUP(D36,#REF!,23,0),0) -> #REF! | BF36: =BB36*BC36+BD36*BE36 -> #REF! | BG36: =BF36-BA36 -> #REF! | BH36: 0 | BK36: 459 | BL36: =ROUNDUP(DI36/(1-0.17)*0.17,0) -> 459 | BM36: =BL36-BK36 -> 0 | BN36: 0 | BR36: 0 | BT36: 0 | BV36: 0 | BX36: 100746.31 | BY36: =SUM(AE36,AH36,AN36,AR36,AU36,AY36,BA36,BH36,BK36,BN36,BR36,BT36) -> 100746.31 | BZ36: =BY36-BX36 -> 0 | CA36: 100287.31 | CB36: =SUM(AE36,AH36,BA36,BH36) -> 100287.31 | CC36: =CB36-CA36 -> 0 | CD36: 0 | CG36: 0 | CI36: 3159.6493 | CJ36: 0.05 | CL36: 0 | CM36: 0.1 | CN36: 0 | CO36: 0 | CP36: 0 | CR36: 0 | CT36: 1500 | CU36: =MIN(BX36*5%,1500) -> 1500 | CV36: =CU36-CT36 -> 0 | CW36: 5014.37 | CX36: =ROUND(CA36*CJ36,2) -> 5014.37 | CY36: =CX36-CW36 -> 0 | CZ36: 1500 | DA36: =MIN(BX36*5%,1500) -> 1500 | DB36: =DA36-CZ36 -> 0 | DC36: 8528.73 | DD36: =MAX(ROUND(CA36*CM36-CZ36,2),0) -> 8528.73 | DE36: =DD36-DC36 -> 0 | DF36: 94231.94 | DG36: =SUM(AE36,AH36,AN36,AR36,AU36,AY36,BA36,BH36,BK36,BN36,BR36,BT36,BV36,-CG36,-CP36,-CT36,-CW36) -> 94231.94 | DH36: =DG36-DF36 -> 0 | DI36: 2237.92 | DJ36: =IFERROR(VLOOKUP(D36,#REF!,2,0),0) -> 0 | DK36: =DJ36-DI36 -> -2237.92 | DL36: 100746.31 | DM36: 1705262.2 | DN36: 8008.83 | DO36: 4181.31 | DP36: 0 | DQ36: 100287.31 | DR36: 28 | DS36: 0 | DT36: 2025-01-01 | DU36: 2025-12-31 | DV36: 2025-01-10 | DW36: 2025-02-10
A37: MSD Asia202502 | B37: MERCK SHARP & DOHME (ASIA) LIMITED | C37: MSD Asia | D37: 51391533 | E37: =VLOOKUP(D37,#REF!,1,0) -> #REF! | F37: Shing | G37: Chun Yin | H37: =G37&" "&F37 -> Chun Yin Shing | I37: =VLOOKUP(D37,#REF!,9,0) -> #REF! | J37: =I37=H37 -> #REF! | K37: Chris | L37: Active | M37: 2021-04-07 | N37: =VLOOKUP(D37,#REF!,80,0) -> #REF! | O37: =N37-M37 -> #REF! | P37: HK SPECIALTY CARE (MA) | Q37: =VLOOKUP(D37,#REF!,50,0) -> #REF! | R37: =Q37=P37 -> #REF! | S37: Business Unit Director, Pharmaceuticals & Macau | T37: =VLOOKUP(D37,#REF!,21,0) -> #REF! | U37: =T37=S37 -> #REF! | V37: 12630103 | W37: =VLOOKUP(D37,#REF!,51,0) -> #REF! | X37: =W37=V37 -> #REF! | Y37: 202502 | Z37: N | AA37: 3.9 | AB37: 90000 | AC37: =ROUND(VLOOKUP(D37,#REF!,59,0),0) -> #REF! | AD37: =AC37-AB37 -> #REF! | AE37: 90000 | AF37: =AB37 -> 90000 | AG37: =AF37-AE37 -> 0 | AH37: 0 | AK37: 0 | AN37: 0 | AO37: 0 | AP37: =IFERROR(VLOOKUP('Feb for check'!D37,#REF!,15,0),0) -> 0 | AQ37: =AP37-AO37 -> 0 | AR37: 0 | AS37: =AO37 -> 0 | AT37: =AS37-AR37 -> 0 | AU37: 0 | AW37: 0 | AY37: 0 | BA37: 0 | BB37: =IFERROR(VLOOKUP(D37,#REF!,2,0),0) -> 0 | BC37: =MAX(VLOOKUP(D37,#REF!,13,0)-VLOOKUP(D37,#REF!,14,0),0) -> #REF! | BD37: =IFERROR(VLOOKUP(D37,#REF!,3,0),0) -> 0 | BE37: =MAX(VLOOKUP(D37,#REF!,22,0)-VLOOKUP(D37,#REF!,23,0),0) -> #REF! | BF37: =BB37*BC37+BD37*BE37 -> #REF! | BG37: =BF37-BA37 -> #REF! | BH37: 0 | BK37: 2292 | BL37: =ROUNDUP(DI37/(1-0.17)*0.17,0) -> 2292 | BM37: =BL37-BK37 -> 0 | BN37: 0 | BR37: 0 | BT37: 0 | BV37: 0 | BX37: 92292 | BY37: =SUM(AE37,AH37,AN37,AR37,AU37,AY37,BA37,BH37,BK37,BN37,BR37,BT37) -> 92292 | BZ37: =BY37-BX37 -> 0 | CA37: 90000 | CB37: =SUM(AE37,AH37,BA37,BH37) -> 90000 | CC37: =CB37-CA37 -> 0 | CD37: 0 | CG37: 0 | CI37: 2958.9041 | CJ37: 0.05 | CL37: 0 | CM37: 0.1 | CN37: 0 | CO37: 0 | CP37: 0 | CR37: 0 | CT37: 1500 | CU37: =MIN(BX37*5%,1500) -> 1500 | CV37: =CU37-CT37 -> 0 | CW37: 4500 | CX37: =ROUND(CA37*CJ37,2) -> 4500 | CY37: =CX37-CW37 -> 0 | CZ37: 1500 | DA37: =MIN(BX37*5%,1500) -> 1500 | DB37: =DA37-CZ37 -> 0 | DC37: 7500 | DD37: =MAX(ROUND(CA37*CM37-CZ37,2),0) -> 7500 | DE37: =DD37-DC37 -> 0 | DF37: 86292 | DG37: =SUM(AE37,AH37,AN37,AR37,AU37,AY37,BA37,BH37,BK37,BN37,BR37,BT37,BV37,-CG37,-CP37,-CT37,-CW37) -> 86292 | DH37: =DG37-DF37 -> 0 | DI37: 11189.62 | DJ37: =IFERROR(VLOOKUP(D37,#REF!,2,0),0) -> 0 | DK37: =DJ37-DI37 -> -11189.62 | DL37: 92292 | DM37: 1512962.5 | DN37: 7500 | DO37: 0 | DP37: 0 | DQ37: 90000 | DR37: 28 | DS37: 0 | DT37: 2025-01-01 | DU37: 2025-12-31 | DV37: 2025-01-10 | DW37: 2025-02-10
A38: MSD Asia202502 | B38: MERCK SHARP & DOHME (ASIA) LIMITED | C38: MSD Asia | D38: 51474203 | E38: =VLOOKUP(D38,#REF!,1,0) -> #REF! | F38: Cheung | G38: Man Lok | H38: =G38&" "&F38 -> Man Lok Cheung | I38: =VLOOKUP(D38,#REF!,9,0) -> #REF! | J38: =I38=H38 -> #REF! | K38: Nelly | L38: Active | M38: 2023-10-12 | N38: =VLOOKUP(D38,#REF!,80,0) -> #REF! | O38: =N38-M38 -> #REF! | P38: HK Public Sector Access | Q38: =VLOOKUP(D38,#REF!,50,0) -> #REF! | R38: =Q38=P38 -> #REF! | S38: Communication Manager | T38: =VLOOKUP(D38,#REF!,21,0) -> #REF! | U38: =T38=S38 -> #REF! | V38: 12630108 | W38: =VLOOKUP(D38,#REF!,51,0) -> #REF! | X38: =W38=V38 -> #REF! | Y38: 202502 | Z38: N | AA38: 1.38 | AB38: 48504 | AC38: =ROUND(VLOOKUP(D38,#REF!,59,0),0) -> #REF! | AD38: =AC38-AB38 -> #REF! | AE38: 48504 | AF38: =AB38 -> 48504 | AG38: =AF38-AE38 -> 0 | AH38: 0 | AK38: 0 | AN38: 0 | AO38: 0 | AP38: =IFERROR(VLOOKUP('Feb for check'!D38,#REF!,15,0),0) -> 0 | AQ38: =AP38-AO38 -> 0 | AR38: 0 | AS38: =AO38 -> 0 | AT38: =AS38-AR38 -> 0 | AU38: 0 | AW38: 0 | AY38: 0 | BA38: 49.4 | BB38: =IFERROR(VLOOKUP(D38,#REF!,2,0),0) -> 0 | BC38: =MAX(VLOOKUP(D38,#REF!,13,0)-VLOOKUP(D38,#REF!,14,0),0) -> #REF! | BD38: =IFERROR(VLOOKUP(D38,#REF!,3,0),0) -> 0 | BE38: =MAX(VLOOKUP(D38,#REF!,22,0)-VLOOKUP(D38,#REF!,23,0),0) -> #REF! | BF38: =BB38*BC38+BD38*BE38 -> #REF! | BG38: =BF38-BA38 -> #REF! | BH38: 0 | BK38: 0 | BL38: =ROUNDUP(DI38/(1-0.17)*0.17,0) -> 0 | BM38: =BL38-BK38 -> 0 | BN38: 0 | BR38: 0 | BT38: 0 | BV38: 0 | BX38: 48553.4 | BY38: =SUM(AE38,AH38,AN38,AR38,AU38,AY38,BA38,BH38,BK38,BN38,BR38,BT38) -> 48553.4 | BZ38: =BY38-BX38 -> 0 | CA38: 48553.4 | CB38: =SUM(AE38,AH38,BA38,BH38) -> 48553.4 | CC38: =CB38-CA38 -> 0 | CD38: 0 | CG38: 0 | CI38: 1594.652 | CJ38: 0 | CL38: 0 | CM38: 0.075 | CN38: 0 | CO38: 0 | CP38: 0 | CR38: 0 | CT38: 1500 | CU38: =MIN(BX38*5%,1500) -> 1500 | CV38: =CU38-CT38 -> 0 | CW38: 0 | CX38: =ROUND(CA38*CJ38,2) -> 0 | CY38: =CX38-CW38 -> 0 | CZ38: 1500 | DA38: =MIN(BX38*5%,1500) -> 1500 | DB38: =DA38-CZ38 -> 0 | DC38: 2141.51 | DD38: =MAX(ROUND(CA38*CM38-CZ38,2),0) -> 2141.51 | DE38: =DD38-DC38 -> 0 | DF38: 47053.4 | DG38: =SUM(AE38,AH38,AN38,AR38,AU38,AY38,BA38,BH38,BK38,BN38,BR38,BT38,BV38,-CG38,-CP38,-CT38,-CW38) -> 47053.4 | DH38: =DG38-DF38 -> 0 | DI38: 0 | DJ38: =IFERROR(VLOOKUP(D38,#REF!,2,0),0) -> 0 | DK38: =DJ38-DI38 -> 0 | DL38: 48553.4 | DM38: 632085.02 | DN38: 4042 | DO38: 49.4 | DP38: 0 | DQ38: 48553.4 | DR38: 28 | DS38: 0 | DT38: 2025-01-01 | DU38: 2025-12-31 | DV38: 2025-01-10 | DW38: 2025-02-10
A39: MSD Asia202502 | B39: MERCK SHARP & DOHME (ASIA) LIMITED | C39: MSD Asia | D39: 51356635 | E39: =VLOOKUP(D39,#REF!,1,0) -> #REF! | F39: Lau | G39: On SiK | H39: =G39&" "&F39 -> On SiK Lau | I39: =VLOOKUP(D39,#REF!,9,0) -> #REF! | J39: =I39=H39 -> #REF! | K39: Anthony | L39: Active | M39: 2019-12-02 | N39: =VLOOKUP(D39,#REF!,80,0) -> #REF! | O39: =N39-M39 -> #REF! | P39: HK Direct Selling - Oncology | Q39: =VLOOKUP(D39,#REF!,50,0) -> #REF! | R39: =Q39=P39 -> #REF! | S39: Senior Sales Manager | T39: =VLOOKUP(D39,#REF!,21,0) -> #REF! | U39: =T39=S39 -> #REF! | V39: 12630118 | W39: =VLOOKUP(D39,#REF!,51,0) -> #REF! | X39: =W39=V39 -> #REF! | Y39: 202502 | Z39: N | AA39: 5.24 | AB39: 78200 | AC39: =ROUND(VLOOKUP(D39,#REF!,59,0),0) -> #REF! | AD39: =AC39-AB39 -> #REF! | AE39: 78200 | AF39: =AB39 -> 78200 | AG39: =AF39-AE39 -> 0 | AH39: 0 | AK39: 0 | AN39: 0 | AO39: 2500 | AP39: =IFERROR(VLOOKUP('Feb for check'!D39,#REF!,15,0),0) -> 0 | AQ39: =AP39-AO39 -> -2500 | AR39: 2500 | AS39: =AO39 -> 2500 | AT39: =AS39-AR39 -> 0 | AU39: 0 | AW39: 0 | AY39: 0 | BA39: 604.49 | BB39: =IFERROR(VLOOKUP(D39,#REF!,2,0),0) -> 0 | BC39: =MAX(VLOOKUP(D39,#REF!,13,0)-VLOOKUP(D39,#REF!,14,0),0) -> #REF! | BD39: =IFERROR(VLOOKUP(D39,#REF!,3,0),0) -> 0 | BE39: =MAX(VLOOKUP(D39,#REF!,22,0)-VLOOKUP(D39,#REF!,23,0),0) -> #REF! | BF39: =BB39*BC39+BD39*BE39 -> #REF! | BG39: =BF39-BA39 -> #REF! | BH39: 0 | BK39: 459 | BL39: =ROUNDUP(DI39/(1-0.17)*0.17,0) -> 459 | BM39: =BL39-BK39 -> 0 | BN39: 0 | BR39: 0 | BT39: 0 | BV39: 0 | BX39: 81763.49 | BY39: =SUM(AE39,AH39,AN39,AR39,AU39,AY39,BA39,BH39,BK39,BN39,BR39,BT39) -> 81763.49 | BZ39: =BY39-BX39 -> 0 | CA39: 78804.49 | CB39: =SUM(AE39,AH39,BA39,BH39) -> 78804.49 | CC39: =CB39-CA39 -> 0 | CD39: 0 | CG39: 0 | CI39: 2653.1506 | CJ39: 0.05 | CL39: 0 | CM39: 0.1 | CN39: 0 | CO39: 0 | CP39: 0 | CR39: 0 | CT39: 1500 | CU39: =MIN(BX39*5%,1500) -> 1500 | CV39: =CU39-CT39 -> 0 | CW39: 3940.22 | CX39: =ROUND(CA39*CJ39,2) -> 3940.22 | CY39: =CX39-CW39 -> 0 | CZ39: 1500 | DA39: =MIN(BX39*5%,1500) -> 1500 | DB39: =DA39-CZ39 -> 0 | DC39: 6380.45 | DD39: =MAX(ROUND(CA39*CM39-CZ39,2),0) -> 6380.45 | DE39: =DD39-DC39 -> 0 | DF39: 76323.27 | DG39: =SUM(AE39,AH39,AN39,AR39,AU39,AY39,BA39,BH39,BK39,BN39,BR39,BT39,BV39,-CG39,-CP39,-CT39,-CW39) -> 76323.27 | DH39: =DG39-DF39 -> 0 | DI39: 2237.92 | DJ39: =IFERROR(VLOOKUP(D39,#REF!,2,0),0) -> 0 | DK39: =DJ39-DI39 -> -2237.92 | DL39: 79263.49 | DM39: 1269921.3 | DN39: 6516.67 | DO39: 604.49 | DP39: 0 | DQ39: 81304.49 | DR39: 28 | DS39: 0 | DT39: 2025-01-01 | DU39: 2025-12-31 | DV39: 2025-01-10 | DW39: 2025-02-10
A40: MSD Asia202502 | B40: MERCK SHARP & DOHME (ASIA) LIMITED | C40: MSD Asia | D40: 51428108 | E40: =VLOOKUP(D40,#REF!,1,0) -> #REF! | F40: Chiu | G40: Tsz Ying Ophelia | H40: =G40&" "&F40 -> Tsz Ying Ophelia Chiu | I40: =VLOOKUP(D40,#REF!,9,0) -> #REF! | J40: =I40=H40 -> #REF! | K40: Ophelia | L40: Active | M40: 2023-07-03 | N40: =VLOOKUP(D40,#REF!,80,0) -> #REF! | O40: =N40-M40 -> #REF! | P40: MRL HKG GRA INTL | Q40: =VLOOKUP(D40,#REF!,50,0) -> #REF! | R40: =Q40=P40 -> #REF! | S40: Regulatory Affairs Associate | T40: =VLOOKUP(D40,#REF!,21,0) -> #REF! | U40: =T40=S40 -> #REF! | V40: 12630168 | W40: =VLOOKUP(D40,#REF!,51,0) -> #REF! | X40: =W40=V40 -> #REF! | Y40: 202502 | Z40: N | AA40: 2.66 | AB40: 25109 | AC40: =ROUND(VLOOKUP(D40,#REF!,59,0),0) -> #REF! | AD40: =AC40-AB40 -> #REF! | AE40: 25109 | AF40: =AB40 -> 25109 | AG40: =AF40-AE40 -> 0 | AH40: 0 | AK40: 0 | AN40: 0 | AO40: 0 | AP40: =IFERROR(VLOOKUP('Feb for check'!D40,#REF!,15,0),0) -> 0 | AQ40: =AP40-AO40 -> 0 | AR40: 0 | AS40: =AO40 -> 0 | AT40: =AS40-AR40 -> 0 | AU40: 0 | AW40: 0 | AY40: 0 | BA40: 580.62 | BB40: =IFERROR(VLOOKUP(D40,#REF!,2,0),0) -> 0 | BC40: =MAX(VLOOKUP(D40,#REF!,13,0)-VLOOKUP(D40,#REF!,14,0),0) -> #REF! | BD40: =IFERROR(VLOOKUP(D40,#REF!,3,0),0) -> 0 | BE40: =MAX(VLOOKUP(D40,#REF!,22,0)-VLOOKUP(D40,#REF!,23,0),0) -> #REF! | BF40: =BB40*BC40+BD40*BE40 -> #REF! | BG40: =BF40-BA40 -> #REF! | BH40: 0 | BK40: 459 | BL40: =ROUNDUP(DI40/(1-0.17)*0.17,0) -> 459 | BM40: =BL40-BK40 -> 0 | BN40: 0 | BR40: 0 | BT40: 0 | BV40: 0 | BX40: 26148.62 | BY40: =SUM(AE40,AH40,AN40,AR40,AU40,AY40,BA40,BH40,BK40,BN40,BR40,BT40) -> 26148.62 | BZ40: =BY40-BX40 -> 0 | CA40: 25689.62 | CB40: =SUM(AE40,AH40,BA40,BH40) -> 25689.62 | CC40: =CB40-CA40 -> 0 | CD40: 0 | CG40: 0 | CI40: 825.5013 | CJ40: 0 | CL40: 0 | CM40: 0.075 | CN40: 0 | CO40: 0 | CP40: 0 | CR40: 0 | CT40: 1307.43 | CU40: =MIN(BX40*5%,1500) -> 1307.431 | CV40: =CU40-CT40 -> 0.001 | CW40: 0 | CX40: =ROUND(CA40*CJ40,2) -> 0 | CY40: =CX40-CW40 -> 0 | CZ40: 1307.43 | DA40: =MIN(BX40*5%,1500) -> 1307.431 | DB40: =DA40-CZ40 -> 0.001 | DC40: 619.29 | DD40: =MAX(ROUND(CA40*CM40-CZ40,2),0) -> 619.29 | DE40: =DD40-DC40 -> 0 | DF40: 24841.19 | DG40: =SUM(AE40,AH40,AN40,AR40,AU40,AY40,BA40,BH40,BK40,BN40,BR40,BT40,BV40,-CG40,-CP40,-CT40,-CW40) -> 24841.19 | DH40: =DG40-DF40 -> 0 | DI40: 2237.92 | DJ40: =IFERROR(VLOOKUP(D40,#REF!,2,0),0) -> 0 | DK40: =DJ40-DI40 -> -2237.92 | DL40: 26148.62 | DM40: 361271.82 | DN40: 2092.42 | DO40: 580.62 | DP40: 0 | DQ40: 25689.62 | DR40: 28 | DS40: 0 | DT40: 2025-01-01 | DU40: 2025-12-31 | DV40: 2025-01-10 | DW40: 2025-02-10
A41: MSD Asia202502 | B41: MERCK SHARP & DOHME (ASIA) LIMITED | C41: MSD Asia | D41: 10194704 | E41: =VLOOKUP(D41,#REF!,1,0) -> #REF! | F41: Lee | G41: Ka Ying | H41: =G41&" "&F41 -> Ka Ying Lee | I41: =VLOOKUP(D41,#REF!,9,0) -> #REF! | J41: =I41=H41 -> #REF! | K41: Ada | L41: Active | M41: 2021-12-01 | N41: =VLOOKUP(D41,#REF!,80,0) -> #REF! | O41: =N41-M41 -> #REF! | P41: HK Public Sector Access | Q41: =VLOOKUP(D41,#REF!,50,0) -> #REF! | R41: =Q41=P41 -> #REF! | S41: External Affairs Director | T41: =VLOOKUP(D41,#REF!,21,0) -> #REF! | U41: =T41=S41 -> #REF! | V41: 12630108 | W41: =VLOOKUP(D41,#REF!,51,0) -> #REF! | X41: =W41=V41 -> #REF! | Y41: 202502 | Z41: N | AA41: 17.89 | AB41: 111280 | AC41: =ROUND(VLOOKUP(D41,#REF!,59,0),0) -> #REF! | AD41: =AC41-AB41 -> #REF! | AE41: 111280 | AF41: =AB41 -> 111280 | AG41: =AF41-AE41 -> 0 | AH41: 0 | AK41: 0 | AN41: 0 | AO41: 0 | AP41: =IFERROR(VLOOKUP('Feb for check'!D41,#REF!,15,0),0) -> 0 | AQ41: =AP41-AO41 -> 0 | AR41: 0 | AS41: =AO41 -> 0 | AT41: =AS41-AR41 -> 0 | AU41: 0 | AW41: 0 | AY41: 0 | BA41: 756.42 | BB41: =IFERROR(VLOOKUP(D41,#REF!,2,0),0) -> 0 | BC41: =MAX(VLOOKUP(D41,#REF!,13,0)-VLOOKUP(D41,#REF!,14,0),0) -> #REF! | BD41: =IFERROR(VLOOKUP(D41,#REF!,3,0),0) -> 0 | BE41: =MAX(VLOOKUP(D41,#REF!,22,0)-VLOOKUP(D41,#REF!,23,0),0) -> #REF! | BF41: =BB41*BC41+BD41*BE41 -> #REF! | BG41: =BF41-BA41 -> #REF! | BH41: 0 | BK41: 1834 | BL41: =ROUNDUP(DI41/(1-0.17)*0.17,0) -> 1834 | BM41: =BL41-BK41 -> 0 | BN41: 0 | BR41: 0 | BT41: 0 | BV41: 0 | BX41: 113870.42 | BY41: =SUM(AE41,AH41,AN41,AR41,AU41,AY41,BA41,BH41,BK41,BN41,BR41,BT41) -> 113870.42 | BZ41: =BY41-BX41 -> 0 | CA41: 112036.42 | CB41: =SUM(AE41,AH41,BA41,BH41) -> 112036.42 | CC41: =CB41-CA41 -> 0 | CD41: 0 | CG41: 0 | CI41: 3658.5205 | CJ41: 0.05 | CL41: 0 | CM41: 0.1 | CN41: 0 | CO41: 0 | CP41: 0 | CR41: 0 | CT41: 1500 | CU41: =MIN(BX41*5%,1500) -> 1500 | CV41: =CU41-CT41 -> 0 | CW41: 5601.82 | CX41: =ROUND(CA41*CJ41,2) -> 5601.82 | CY41: =CX41-CW41 -> 0 | CZ41: 1500 | DA41: =MIN(BX41*5%,1500) -> 1500 | DB41: =DA41-CZ41 -> 0 | DC41: 9703.64 | DD41: =MAX(ROUND(CA41*CM41-CZ41,2),0) -> 9703.64 | DE41: =DD41-DC41 -> 0 | DF41: 106768.6 | DG41: =SUM(AE41,AH41,AN41,AR41,AU41,AY41,BA41,BH41,BK41,BN41,BR41,BT41,BV41,-CG41,-CP41,-CT41,-CW41) -> 106768.6 | DH41: =DG41-DF41 -> 0 | DI41: 8951.7 | DJ41: =IFERROR(VLOOKUP(D41,#REF!,2,0),0) -> 0 | DK41: =DJ41-DI41 -> -8951.7 | DL41: 113870.42 | DM41: 2016993.9 | DN41: 9273.33 | DO41: 756.42 | DP41: 0 | DQ41: 112036.42 | DR41: 28 | DS41: 0 | DT41: 2025-01-01 | DU41: 2025-12-31 | DV41: 2025-01-10 | DW41: 2025-02-10
A42: MSD Asia202502 | B42: MERCK SHARP & DOHME (ASIA) LIMITED | C42: MSD Asia | D42: 51495415 | E42: =VLOOKUP(D42,#REF!,1,0) -> #REF! | F42: Cheung | G42: Sau Kei | H42: =G42&" "&F42 -> Sau Kei Cheung | I42: =VLOOKUP(D42,#REF!,9,0) -> #REF! | J42: =I42=H42 -> #REF! | K42: Elvis | L42: Active | M42: 2024-07-22 | N42: =VLOOKUP(D42,#REF!,80,0) -> #REF! | O42: =N42-M42 -> #REF! | P42: HK Direct Selling - Oncology | Q42: =VLOOKUP(D42,#REF!,50,0) -> #REF! | R42: =Q42=P42 -> #REF! | S42: Associate Key Account Manager | T42: =VLOOKUP(D42,#REF!,21,0) -> #REF! | U42: =T42=S42 -> #REF! | V42: 12630118 | W42: =VLOOKUP(D42,#REF!,51,0) -> #REF! | X42: =W42=V42 -> #REF! | Y42: 202502 | Z42: N | AA42: 0.61 | AB42: 38440 | AC42: =ROUND(VLOOKUP(D42,#REF!,59,0),0) -> #REF! | AD42: =AC42-AB42 -> #REF! | AE42: 38440 | AF42: =AB42 -> 38440 | AG42: =AF42-AE42 -> 0 | AH42: 0 | AK42: 0 | AN42: 0 | AO42: 2500 | AP42: =IFERROR(VLOOKUP('Feb for check'!D42,#REF!,15,0),0) -> 0 | AQ42: =AP42-AO42 -> -2500 | AR42: 2500 | AS42: =AO42 -> 2500 | AT42: =AS42-AR42 -> 0 | AU42: 0 | AW42: 0 | AY42: 0 | BA42: 0 | BB42: =IFERROR(VLOOKUP(D42,#REF!,2,0),0) -> 0 | BC42: =MAX(VLOOKUP(D42,#REF!,13,0)-VLOOKUP(D42,#REF!,14,0),0) -> #REF! | BD42: =IFERROR(VLOOKUP(D42,#REF!,3,0),0) -> 0 | BE42: =MAX(VLOOKUP(D42,#REF!,22,0)-VLOOKUP(D42,#REF!,23,0),0) -> #REF! | BF42: =BB42*BC42+BD42*BE42 -> #REF! | BG42: =BF42-BA42 -> #REF! | BH42: 0 | BK42: 0 | BL42: =ROUNDUP(DI42/(1-0.17)*0.17,0) -> 0 | BM42: =BL42-BK42 -> 0 | BN42: 0 | BR42: 0 | BT42: 0 | BV42: 0 | BX42: 40940 | BY42: =SUM(AE42,AH42,AN42,AR42,AU42,AY42,BA42,BH42,BK42,BN42,BR42,BT42) -> 40940 | BZ42: =BY42-BX42 -> 0 | CA42: 38440 | CB42: =SUM(AE42,AH42,BA42,BH42) -> 38440 | CC42: =CB42-CA42 -> 0 | CD42: 0 | CG42: 0 | CI42: 1345.9726 | CJ42: 0 | CL42: 0 | CM42: 0.075 | CN42: 0 | CO42: 0 | CP42: 0 | CR42: 0 | CT42: 1500 | CU42: =MIN(BX42*5%,1500) -> 1500 | CV42: =CU42-CT42 -> 0 | CW42: 0 | CX42: =ROUND(CA42*CJ42,2) -> 0 | CY42: =CX42-CW42 -> 0 | CZ42: 1500 | DA42: =MIN(BX42*5%,1500) -> 1500 | DB42: =DA42-CZ42 -> 0 | DC42: 1383 | DD42: =MAX(ROUND(CA42*CM42-CZ42,2),0) -> 1383 | DE42: =DD42-DC42 -> 0 | DF42: 39440 | DG42: =SUM(AE42,AH42,AN42,AR42,AU42,AY42,BA42,BH42,BK42,BN42,BR42,BT42,BV42,-CG42,-CP42,-CT42,-CW42) -> 39440 | DH42: =DG42-DF42 -> 0 | DI42: 0 | DJ42: =IFERROR(VLOOKUP(D42,#REF!,2,0),0) -> 0 | DK42: =DJ42-DI42 -> 0 | DL42: 38440 | DM42: 424995.85 | DN42: 3203.33 | DO42: 0 | DP42: 0 | DQ42: 40940 | DR42: 28 | DS42: 0 | DT42: 2025-01-01 | DU42: 2025-12-31 | DV42: 2025-01-10 | DW42: 2025-02-10
A43: MSD Asia202502 | B43: MERCK SHARP & DOHME (ASIA) LIMITED | C43: MSD Asia | D43: 51217719 | E43: =VLOOKUP(D43,#REF!,1,0) -> #REF! | F43: Ling | G43: Kin Han Helena | H43: =G43&" "&F43 -> Kin Han Helena Ling | I43: =VLOOKUP(D43,#REF!,9,0) -> #REF! | J43: =I43=H43 -> #REF! | K43: Helena | L43: Active | M43: 2020-09-29 | N43: =VLOOKUP(D43,#REF!,80,0) -> #REF! | O43: =N43-M43 -> #REF! | P43: HK SPECIALTY CARE (MA) | Q43: =VLOOKUP(D43,#REF!,50,0) -> #REF! | R43: =Q43=P43 -> #REF! | S43: Associate Product Manager | T43: =VLOOKUP(D43,#REF!,21,0) -> #REF! | U43: =T43=S43 -> #REF! | V43: 12630103 | W43: =VLOOKUP(D43,#REF!,51,0) -> #REF! | X43: =W43=V43 -> #REF! | Y43: 202502 | Z43: N | AA43: 9.98 | AB43: 43900 | AC43: =ROUND(VLOOKUP(D43,#REF!,59,0),0) -> #REF! | AD43: =AC43-AB43 -> #REF! | AE43: 43900 | AF43: =AB43 -> 43900 | AG43: =AF43-AE43 -> 0 | AH43: 0 | AK43: 0 | AN43: 0 | AO43: 0 | AP43: =IFERROR(VLOOKUP('Feb for check'!D43,#REF!,15,0),0) -> 0 | AQ43: =AP43-AO43 -> 0 | AR43: 0 | AS43: =AO43 -> 0 | AT43: =AS43-AR43 -> 0 | AU43: 0 | AW43: 0 | AY43: 0 | BA43: 0 | BB43: =IFERROR(VLOOKUP(D43,#REF!,2,0),0) -> 0 | BC43: =MAX(VLOOKUP(D43,#REF!,13,0)-VLOOKUP(D43,#REF!,14,0),0) -> #REF! | BD43: =IFERROR(VLOOKUP(D43,#REF!,3,0),0) -> 0 | BE43: =MAX(VLOOKUP(D43,#REF!,22,0)-VLOOKUP(D43,#REF!,23,0),0) -> #REF! | BF43: =BB43*BC43+BD43*BE43 -> #REF! | BG43: =BF43-BA43 -> #REF! | BH43: 0 | BK43: 0 | BL43: =ROUNDUP(DI43/(1-0.17)*0.17,0) -> 0 | BM43: =BL43-BK43 -> 0 | BN43: 0 | BR43: 0 | BT43: 0 | BV43: 0 | BX43: 43900 | BY43: =SUM(AE43,AH43,AN43,AR43,AU43,AY43,BA43,BH43,BK43,BN43,BR43,BT43) -> 43900 | BZ43: =BY43-BX43 -> 0 | CA43: 43900 | CB43: =SUM(AE43,AH43,BA43,BH43) -> 43900 | CC43: =CB43-CA43 -> 0 | CD43: 0 | CG43: 0 | CI43: 1443.2876 | CJ43: 0.01 | CL43: 0.08 | CM43: 0.08 | CN43: 0 | CO43: 0 | CP43: 0 | CR43: 0 | CT43: 1500 | CU43: =MIN(BX43*5%,1500) -> 1500 | CV43: =CU43-CT43 -> 0 | CW43: 439 | CX43: =ROUND(CA43*CJ43,2) -> 439 | CY43: =CX43-CW43 -> 0 | CZ43: 1500 | DA43: =MIN(BX43*5%,1500) -> 1500 | DB43: =DA43-CZ43 -> 0 | DC43: 2012 | DD43: =MAX(ROUND(CA43*CM43-CZ43,2),0) -> 2012 | DE43: =DD43-DC43 -> 0 | DF43: 41961 | DG43: =SUM(AE43,AH43,AN43,AR43,AU43,AY43,BA43,BH43,BK43,BN43,BR43,BT43,BV43,-CG43,-CP43,-CT43,-CW43) -> 41961 | DH43: =DG43-DF43 -> 0 | DI43: 0 | DJ43: =IFERROR(VLOOKUP(D43,#REF!,2,0),0) -> 0 | DK43: =DJ43-DI43 -> 0 | DL43: 43900 | DM43: 692888.35 | DN43: 3658.33 | DO43: 0 | DP43: 0 | DQ43: 43900 | DR43: 28 | DS43: 0 | DT43: 2025-01-01 | DU43: 2025-12-31 | DV43: 2025-01-10 | DW43: 2025-02-10
A44: MSD Asia202502 | B44: MERCK SHARP & DOHME (ASIA) LIMITED | C44: MSD Asia | D44: 51369455 | E44: =VLOOKUP(D44,#REF!,1,0) -> #REF! | F44: Yuen | G44: Tak Kar | H44: =G44&" "&F44 -> Tak Kar Yuen | I44: =VLOOKUP(D44,#REF!,9,0) -> #REF! | J44: =I44=H44 -> #REF! | K44: Gavin | L44: Active | M44: 2020-06-22 | N44: =VLOOKUP(D44,#REF!,80,0) -> #REF! | O44: =N44-M44 -> #REF! | P44: HK Comm Oper (SA) | Q44: =VLOOKUP(D44,#REF!,50,0) -> #REF! | R44: =Q44=P44 -> #REF! | S44: Administrative Associate | T44: =VLOOKUP(D44,#REF!,21,0) -> #REF! | U44: =T44=S44 -> #REF! | V44: 12630222 | W44: =VLOOKUP(D44,#REF!,51,0) -> #REF! | X44: =W44=V44 -> #REF! | Y44: 202502 | Z44: N | AA44: 4.69 | AB44: 26210 | AC44: =ROUND(VLOOKUP(D44,#REF!,59,0),0) -> #REF! | AD44: =AC44-AB44 -> #REF! | AE44: 26210 | AF44: =AB44 -> 26210 | AG44: =AF44-AE44 -> 0 | AH44: 0 | AK44: 0 | AN44: 0 | AO44: 0 | AP44: =IFERROR(VLOOKUP('Feb for check'!D44,#REF!,15,0),0) -> 0 | AQ44: =AP44-AO44 -> 0 | AR44: 0 | AS44: =AO44 -> 0 | AT44: =AS44-AR44 -> 0 | AU44: 0 | AW44: 0 | AY44: 0 | BA44: 117.65 | BB44: =IFERROR(VLOOKUP(D44,#REF!,2,0),0) -> 0 | BC44: =MAX(VLOOKUP(D44,#REF!,13,0)-VLOOKUP(D44,#REF!,14,0),0) -> #REF! | BD44: =IFERROR(VLOOKUP(D44,#REF!,3,0),0) -> 0 | BE44: =MAX(VLOOKUP(D44,#REF!,22,0)-VLOOKUP(D44,#REF!,23,0),0) -> #REF! | BF44: =BB44*BC44+BD44*BE44 -> #REF! | BG44: =BF44-BA44 -> #REF! | BH44: 0 | BK44: 0 | BL44: =ROUNDUP(DI44/(1-0.17)*0.17,0) -> 0 | BM44: =BL44-BK44 -> 0 | BN44: 0 | BR44: 0 | BT44: 0 | BV44: 0 | BX44: 26327.65 | BY44: =SUM(AE44,AH44,AN44,AR44,AU44,AY44,BA44,BH44,BK44,BN44,BR44,BT44) -> 26327.65 | BZ44: =BY44-BX44 -> 0 | CA44: 26327.65 | CB44: =SUM(AE44,AH44,BA44,BH44) -> 26327.65 | CC44: =CB44-CA44 -> 0 | CD44: 0 | CG44: 0 | CI44: 861.6986 | CJ44: 0 | CL44: 0 | CM44: 0.075 | CN44: 0 | CO44: 0 | CP44: 0 | CR44: 0 | CT44: 1316.38 | CU44: =MIN(BX44*5%,1500) -> 1316.3825 | CV44: =CU44-CT44 -> 0.0025 | CW44: 0 | CX44: =ROUND(CA44*CJ44,2) -> 0 | CY44: =CX44-CW44 -> 0 | CZ44: 1316.38 | DA44: =MIN(BX44*5%,1500) -> 1316.3825 | DB44: =DA44-CZ44 -> 0.0025 | DC44: 658.19 | DD44: =MAX(ROUND(CA44*CM44-CZ44,2),0) -> 658.19 | DE44: =DD44-DC44 -> 0 | DF44: 25011.27 | DG44: =SUM(AE44,AH44,AN44,AR44,AU44,AY44,BA44,BH44,BK44,BN44,BR44,BT44,BV44,-CG44,-CP44,-CT44,-CW44) -> 25011.27 | DH44: =DG44-DF44 -> 0 | DI44: 0 | DJ44: =IFERROR(VLOOKUP(D44,#REF!,2,0),0) -> 0 | DK44: =DJ44-DI44 -> 0 | DL44: 26327.65 | DM44: 391837.67 | DN44: 2184.17 | DO44: 117.65 | DP44: 0 | DQ44: 26327.65 | DR44: 28 | DS44: 0 | DT44: 2025-01-01 | DU44: 2025-12-31 | DV44: 2025-01-10 | DW44: 2025-02-10
A45: MSD Asia202502 | B45: MERCK SHARP & DOHME (ASIA) LIMITED | C45: MSD Asia | D45: 51295934 | E45: =VLOOKUP(D45,#REF!,1,0) -> #REF! | F45: Tai | G45: Siu Lun | H45: =G45&" "&F45 -> Siu Lun Tai | I45: =VLOOKUP(D45,#REF!,9,0) -> #REF! | J45: =I45=H45 -> #REF! | K45: Kevin | L45: Active | M45: 2017-11-10 | N45: =VLOOKUP(D45,#REF!,80,0) -> #REF! | O45: =N45-M45 -> #REF! | P45: MRL HKG GS | Q45: =VLOOKUP(D45,#REF!,50,0) -> #REF! | R45: =Q45=P45 -> #REF! | S45: Senior Regional Pharmacovigilance Officer | T45: =VLOOKUP(D45,#REF!,21,0) -> #REF! | U45: =T45=S45 -> #REF! | V45: 12630166 | W45: =VLOOKUP(D45,#REF!,51,0) -> #REF! | X45: =W45=V45 -> #REF! | Y45: 202502 | Z45: N | AA45: 7.3 | AB45: 66546 | AC45: =ROUND(VLOOKUP(D45,#REF!,59,0),0) -> #REF! | AD45: =AC45-AB45 -> #REF! | AE45: 66546 | AF45: =AB45 -> 66546 | AG45: =AF45-AE45 -> 0 | AH45: 0 | AK45: 0 | AN45: 0 | AO45: 0 | AP45: =IFERROR(VLOOKUP('Feb for check'!D45,#REF!,15,0),0) -> 0 | AQ45: =AP45-AO45 -> 0 | AR45: 0 | AS45: =AO45 -> 0 | AT45: =AS45-AR45 -> 0 | AU45: 0 | AW45: 0 | AY45: 0 | BA45: 4372 | BB45: =IFERROR(VLOOKUP(D45,#REF!,2,0),0) -> 0 | BC45: =MAX(VLOOKUP(D45,#REF!,13,0)-VLOOKUP(D45,#REF!,14,0),0) -> #REF! | BD45: =IFERROR(VLOOKUP(D45,#REF!,3,0),0) -> 0 | BE45: =MAX(VLOOKUP(D45,#REF!,22,0)-VLOOKUP(D45,#REF!,23,0),0) -> #REF! | BF45: =BB45*BC45+BD45*BE45 -> #REF! | BG45: =BF45-BA45 -> #REF! | BH45: 0 | BK45: 55 | BL45: =ROUNDUP(DI45/(1-0.17)*0.17,0) -> 55 | BM45: =BL45-BK45 -> 0 | BN45: 0 | BR45: 0 | BT45: 0 | BV45: 0 | BX45: 70973 | BY45: =SUM(AE45,AH45,AN45,AR45,AU45,AY45,BA45,BH45,BK45,BN45,BR45,BT45) -> 70973 | BZ45: =BY45-BX45 -> 0 | CA45: 70918 | CB45: =SUM(AE45,AH45,BA45,BH45) -> 70918 | CC45: =CB45-CA45 -> 0 | CD45: 0 | CG45: 0 | CI45: 2187.8136 | CJ45: 0 | CL45: 0 | CM45: 0.075 | CN45: 0 | CO45: 0 | CP45: 0 | CR45: 0 | CT45: 1500 | CU45: =MIN(BX45*5%,1500) -> 1500 | CV45: =CU45-CT45 -> 0 | CW45: 0 | CX45: =ROUND(CA45*CJ45,2) -> 0 | CY45: =CX45-CW45 -> 0 | CZ45: 1500 | DA45: =MIN(BX45*5%,1500) -> 1500 | DB45: =DA45-CZ45 -> 0 | DC45: 3818.85 | DD45: =MAX(ROUND(CA45*CM45-CZ45,2),0) -> 3818.85 | DE45: =DD45-DC45 -> 0 | DF45: 69473 | DG45: =SUM(AE45,AH45,AN45,AR45,AU45,AY45,BA45,BH45,BK45,BN45,BR45,BT45,BV45,-CG45,-CP45,-CT45,-CW45) -> 69473 | DH45: =DG45-DF45 -> 0 | DI45: 268.1 | DJ45: =IFERROR(VLOOKUP(D45,#REF!,2,0),0) -> 0 | DK45: =DJ45-DI45 -> -268.1 | DL45: 70973 | DM45: 1192372.6 | DN45: 5545.5 | DO45: 4372 | DP45: 0 | DQ45: 70918 | DR45: 28 | DS45: 0 | DT45: 2025-01-01 | DU45: 2025-12-31 | DV45: 2025-01-10 | DW45: 2025-02-10
A46: MSD Asia202502 | B46: MERCK SHARP & DOHME (ASIA) LIMITED | C46: MSD Asia | D46: 51441627 | E46: =VLOOKUP(D46,#REF!,1,0) -> #REF! | F46: Ngan | G46: Hoi Lam | H46: =G46&" "&F46 -> Hoi Lam Ngan | I46: =VLOOKUP(D46,#REF!,9,0) -> #REF! | J46: =I46=H46 -> #REF! | K46: Jason | L46: Active | M46: 2022-09-19 | N46: =VLOOKUP(D46,#REF!,80,0) -> #REF! | O46: =N46-M46 -> #REF! | P46: MRL HKG ONCOLOGY GMA | Q46: =VLOOKUP(D46,#REF!,50,0) -> #REF! | R46: =Q46=P46 -> #REF! | S46: Medical Advisor, Oncology | T46: =VLOOKUP(D46,#REF!,21,0) -> #REF! | U46: =T46=S46 -> #REF! | V46: 12630107 | W46: =VLOOKUP(D46,#REF!,51,0) -> #REF! | X46: =W46=V46 -> #REF! | Y46: 202502 | Z46: N | AA46: 2.45 | AB46: 48672 | AC46: =ROUND(VLOOKUP(D46,#REF!,59,0),0) -> #REF! | AD46: =AC46-AB46 -> #REF! | AE46: 48672 | AF46: =AB46 -> 48672 | AG46: =AF46-AE46 -> 0 | AH46: 0 | AK46: 0 | AN46: 0 | AO46: 0 | AP46: =IFERROR(VLOOKUP('Feb for check'!D46,#REF!,15,0),0) -> 0 | AQ46: =AP46-AO46 -> 0 | AR46: 0 | AS46: =AO46 -> 0 | AT46: =AS46-AR46 -> 0 | AU46: 0 | AW46: 0 | AY46: 0 | BA46: 0 | BB46: =IFERROR(VLOOKUP(D46,#REF!,2,0),0) -> 0 | BC46: =MAX(VLOOKUP(D46,#REF!,13,0)-VLOOKUP(D46,#REF!,14,0),0) -> #REF! | BD46: =IFERROR(VLOOKUP(D46,#REF!,3,0),0) -> 0 | BE46: =MAX(VLOOKUP(D46,#REF!,22,0)-VLOOKUP(D46,#REF!,23,0),0) -> #REF! | BF46: =BB46*BC46+BD46*BE46 -> #REF! | BG46: =BF46-BA46 -> #REF! | BH46: 0 | BK46: 0 | BL46: =ROUNDUP(DI46/(1-0.17)*0.17,0) -> 0 | BM46: =BL46-BK46 -> 0 | BN46: 0 | BR46: 0 | BT46: 0 | BV46: 0 | BX46: 48672 | BY46: =SUM(AE46,AH46,AN46,AR46,AU46,AY46,BA46,BH46,BK46,BN46,BR46,BT46) -> 48672 | BZ46: =BY46-BX46 -> 0 | CA46: 48672 | CB46: =SUM(AE46,AH46,BA46,BH46) -> 48672 | CC46: =CB46-CA46 -> 0 | CD46: 0 | CG46: 0 | CI46: 1600.1753 | CJ46: 0 | CL46: 0 | CM46: 0.075 | CN46: 0 | CO46: 0 | CP46: 0 | CR46: 0 | CT46: 1500 | CU46: =MIN(BX46*5%,1500) -> 1500 | CV46: =CU46-CT46 -> 0 | CW46: 0 | CX46: =ROUND(CA46*CJ46,2) -> 0 | CY46: =CX46-CW46 -> 0 | CZ46: 1500 | DA46: =MIN(BX46*5%,1500) -> 1500 | DB46: =DA46-CZ46 -> 0 | DC46: 2150.4 | DD46: =MAX(ROUND(CA46*CM46-CZ46,2),0) -> 2150.4 | DE46: =DD46-DC46 -> 0 | DF46: 47172 | DG46: =SUM(AE46,AH46,AN46,AR46,AU46,AY46,BA46,BH46,BK46,BN46,BR46,BT46,BV46,-CG46,-CP46,-CT46,-CW46) -> 47172 | DH46: =DG46-DF46 -> 0 | DI46: 0 | DJ46: =IFERROR(VLOOKUP(D46,#REF!,2,0),0) -> 0 | DK46: =DJ46-DI46 -> 0 | DL46: 48672 | DM46: 832758.82 | DN46: 4056 | DO46: 0 | DP46: 0 | DQ46: 48672 | DR46: 28 | DS46: 0 | DT46: 2025-01-01 | DU46: 2025-12-31 | DV46: 2025-01-10 | DW46: 2025-02-10
A47: MSD Asia202502 | B47: MERCK SHARP & DOHME (ASIA) LIMITED | C47: MSD Asia | D47: 51452064 | E47: =VLOOKUP(D47,#REF!,1,0) -> #REF! | F47: Chan | G47: Hiu Yan | H47: =G47&" "&F47 -> Hiu Yan Chan | I47: =VLOOKUP(D47,#REF!,9,0) -> #REF! | J47: =I47=H47 -> #REF! | K47: Jackie | L47: Active | M47: 2023-01-09 | N47: =VLOOKUP(D47,#REF!,80,0) -> #REF! | O47: =N47-M47 -> #REF! | P47: HK Vaccine (DS) | Q47: =VLOOKUP(D47,#REF!,50,0) -> #REF! | R47: =Q47=P47 -> #REF! | S47: Associate Key Account Manager | T47: =VLOOKUP(D47,#REF!,21,0) -> #REF! | U47: =T47=S47 -> #REF! | V47: 12630115 | W47: =VLOOKUP(D47,#REF!,51,0) -> #REF! | X47: =W47=V47 -> #REF! | Y47: 202502 | Z47: N | AA47: 2.14 | AB47: 33766 | AC47: =ROUND(VLOOKUP(D47,#REF!,59,0),0) -> #REF! | AD47: =AC47-AB47 -> #REF! | AE47: 33766 | AF47: =AB47 -> 33766 | AG47: =AF47-AE47 -> 0 | AH47: -13070.71 | AI47: =-VLOOKUP(D47,#REF!,14,0)*12/31 -> #REF! | AJ47: =AI47-AH47 -> #REF! | AK47: 0 | AN47: 0 | AO47: 2500 | AP47: =IFERROR(VLOOKUP('Feb for check'!D47,#REF!,15,0),0) -> 0 | AQ47: =AP47-AO47 -> -2500 | AR47: 2500 | AS47: =AO47 -> 2500 | AT47: =AS47-AR47 -> 0 | AU47: -967.74 | AV47: =-AO47*#REF!/31 -> #REF! | AW47: 0 | AY47: 0 | BA47: 367.58 | BB47: =IFERROR(VLOOKUP(D47,#REF!,2,0),0) -> 0 | BC47: =MAX(VLOOKUP(D47,#REF!,13,0)-VLOOKUP(D47,#REF!,14,0),0) -> #REF! | BD47: =IFERROR(VLOOKUP(D47,#REF!,3,0),0) -> 0 | BE47: =MAX(VLOOKUP(D47,#REF!,22,0)-VLOOKUP(D47,#REF!,23,0),0) -> #REF! | BF47: =BB47*BC47+BD47*BE47 -> #REF! | BG47: =BF47-BA47 -> #REF! | BH47: 14759.52 | BI47: =VLOOKUP(D47,#REF!,15,0)*#REF! -> #REF! | BJ47: =BI47-BH47 -> #REF! | BK47: 917 | BL47: =ROUNDUP(DI47/(1-0.17)*0.17,0) -> 917 | BM47: =BL47-BK47 -> 0 | BN47: 0 | BR47: 0 | BT47: 0 | BV47: 0 | BX47: 38271.65 | BY47: =SUM(AE47,AH47,AN47,AR47,AU47,AY47,BA47,BH47,BK47,BN47,BR47,BT47) -> 38271.65 | BZ47: =BY47-BX47 -> 0 | CA47: 35822.39 | CB47: =SUM(AE47,AH47,BA47,BH47) -> 35822.39 | CC47: =CB47-CA47 -> 0 | CD47: 0 | CG47: 0 | CI47: 1192.3068 | CJ47: 0 | CL47: 0 | CM47: 0.075 | CN47: 0 | CO47: 0 | CP47: 0 | CR47: 0 | CT47: 1500 | CU47: =MIN(BX47*5%,1500) -> 1500 | CV47: =CU47-CT47 -> 0 | CW47: 0 | CX47: =ROUND(CA47*CJ47,2) -> 0 | CY47: =CX47-CW47 -> 0 | CZ47: 1500 | DA47: =MIN(BX47*5%,1500) -> 1500 | DB47: =DA47-CZ47 -> 0 | DC47: 1186.68 | DD47: =MAX(ROUND(CA47*CM47-CZ47,2),0) -> 1186.68 | DE47: =DD47-DC47 -> 0 | DF47: 36771.65 | DG47: =SUM(AE47,AH47,AN47,AR47,AU47,AY47,BA47,BH47,BK47,BN47,BR47,BT47,BV47,-CG47,-CP47,-CT47,-CW47) -> 36771.65 | DH47: =DG47-DF47 -> 0 | DI47: 4475.85 | DJ47: =IFERROR(VLOOKUP(D47,#REF!,2,0),0) -> 0 | DK47: =DJ47-DI47 -> -4475.85 | DL47: 36739.39 | DM47: 613322.23 | DN47: 2813.83 | DO47: 367.58 | DP47: 0 | DQ47: 22595.13 | DR47: 16 | DS47: 0 | DT47: 2025-01-01 | DU47: 2025-12-31 | DV47: 2025-01-10 | DW47: 2025-02-10
A48: MSD Asia202502 | B48: MERCK SHARP & DOHME (ASIA) LIMITED | C48: MSD Asia | D48: 51464884 | E48: =VLOOKUP(D48,#REF!,1,0) -> #REF! | F48: Hung | G48: Ka Hei | H48: =G48&" "&F48 -> Ka Hei Hung | I48: =VLOOKUP(D48,#REF!,9,0) -> #REF! | J48: =I48=H48 -> #REF! | K48: Keira | L48: Active | M48: 2023-06-05 | N48: =VLOOKUP(D48,#REF!,80,0) -> #REF! | O48: =N48-M48 -> #REF! | P48: HK Direct Selling - Oncology | Q48: =VLOOKUP(D48,#REF!,50,0) -> #REF! | R48: =Q48=P48 -> #REF! | S48: Senior Professional Sales Representative | T48: =VLOOKUP(D48,#REF!,21,0) -> #REF! | U48: =T48=S48 -> #REF! | V48: 12630118 | W48: =VLOOKUP(D48,#REF!,51,0) -> #REF! | X48: =W48=V48 -> #REF! | Y48: 202502 | Z48: N | AA48: 1.74 | AB48: 31740 | AC48: =ROUND(VLOOKUP(D48,#REF!,59,0),0) -> #REF! | AD48: =AC48-AB48 -> #REF! | AE48: 31740 | AF48: =AB48 -> 31740 | AG48: =AF48-AE48 -> 0 | AH48: 0 | AK48: 0 | AN48: 0 | AO48: 2500 | AP48: =IFERROR(VLOOKUP('Feb for check'!D48,#REF!,15,0),0) -> 0 | AQ48: =AP48-AO48 -> -2500 | AR48: 2500 | AS48: =AO48 -> 2500 | AT48: =AS48-AR48 -> 0 | AU48: 0 | AW48: 0 | AY48: 0 | BA48: 0 | BB48: =IFERROR(VLOOKUP(D48,#REF!,2,0),0) -> 0 | BC48: =MAX(VLOOKUP(D48,#REF!,13,0)-VLOOKUP(D48,#REF!,14,0),0) -> #REF! | BD48: =IFERROR(VLOOKUP(D48,#REF!,3,0),0) -> 0 | BE48: =MAX(VLOOKUP(D48,#REF!,22,0)-VLOOKUP(D48,#REF!,23,0),0) -> #REF! | BF48: =BB48*BC48+BD48*BE48 -> #REF! | BG48: =BF48-BA48 -> #REF! | BH48: 0 | BK48: 0 | BL48: =ROUNDUP(DI48/(1-0.17)*0.17,0) -> 0 | BM48: =BL48-BK48 -> 0 | BN48: 0 | BR48: 0 | BT48: 0 | BV48: 0 | BX48: 34240 | BY48: =SUM(AE48,AH48,AN48,AR48,AU48,AY48,BA48,BH48,BK48,BN48,BR48,BT48) -> 34240 | BZ48: =BY48-BX48 -> 0 | CA48: 31740 | CB48: =SUM(AE48,AH48,BA48,BH48) -> 31740 | CC48: =CB48-CA48 -> 0 | CD48: 0 | CG48: 0 | CI48: 1125.6986 | CJ48: 0 | CL48: 0 | CM48: 0.075 | CN48: 0 | CO48: 0 | CP48: 0 | CR48: 0 | CT48: 1500 | CU48: =MIN(BX48*5%,1500) -> 1500 | CV48: =CU48-CT48 -> 0 | CW48: 0 | CX48: =ROUND(CA48*CJ48,2) -> 0 | CY48: =CX48-CW48 -> 0 | CZ48: 1500 | DA48: =MIN(BX48*5%,1500) -> 1500 | DB48: =DA48-CZ48 -> 0 | DC48: 880.5 | DD48: =MAX(ROUND(CA48*CM48-CZ48,2),0) -> 880.5 | DE48: =DD48-DC48 -> 0 | DF48: 32740 | DG48: =SUM(AE48,AH48,AN48,AR48,AU48,AY48,BA48,BH48,BK48,BN48,BR48,BT48,BV48,-CG48,-CP48,-CT48,-CW48) -> 32740 | DH48: =DG48-DF48 -> 0 | DI48: 0 | DJ48: =IFERROR(VLOOKUP(D48,#REF!,2,0),0) -> 0 | DK48: =DJ48-DI48 -> 0 | DL48: 31740 | DM48: 570334.55 | DN48: 2645 | DO48: 0 | DP48: 0 | DQ48: 34240 | DR48: 28 | DS48: 0 | DT48: 2025-01-01 | DU48: 2025-12-31 | DV48: 2025-01-10 | DW48: 2025-02-10
A49: MSD Asia202502 | B49: MERCK SHARP & DOHME (ASIA) LIMITED | C49: MSD Asia | D49: 51462981 | E49: =VLOOKUP(D49,#REF!,1,0) -> #REF! | F49: Wu | G49: Mingshan | H49: =G49&" "&F49 -> Mingshan Wu | I49: =VLOOKUP(D49,#REF!,9,0) -> #REF! | J49: =I49=H49 -> #REF! | K49: Frankie | L49: Active | M49: 2023-05-15 | N49: =VLOOKUP(D49,#REF!,80,0) -> #REF! | O49: =N49-M49 -> #REF! | P49: HK Direct Selling - Oncology | Q49: =VLOOKUP(D49,#REF!,50,0) -> #REF! | R49: =Q49=P49 -> #REF! | S49: Professional Sales Representative | T49: =VLOOKUP(D49,#REF!,21,0) -> #REF! | U49: =T49=S49 -> #REF! | V49: 12630118 | W49: =VLOOKUP(D49,#REF!,51,0) -> #REF! | X49: =W49=V49 -> #REF! | Y49: 202502 | Z49: N | AA49: 1.79 | AB49: 27563 | AC49: =ROUND(VLOOKUP(D49,#REF!,59,0),0) -> #REF! | AD49: =AC49-AB49 -> #REF! | AE49: 27563 | AF49: =AB49 -> 27563 | AG49: =AF49-AE49 -> 0 | AH49: 0 | AK49: 0 | AN49: 0 | AO49: 2500 | AP49: =IFERROR(VLOOKUP('Feb for check'!D49,#REF!,15,0),0) -> 0 | AQ49: =AP49-AO49 -> -2500 | AR49: 2500 | AS49: =AO49 -> 2500 | AT49: =AS49-AR49 -> 0 | AU49: 0 | AW49: 0 | AY49: 0 | BA49: 247.28 | BB49: =IFERROR(VLOOKUP(D49,#REF!,2,0),0) -> 0 | BC49: =MAX(VLOOKUP(D49,#REF!,13,0)-VLOOKUP(D49,#REF!,14,0),0) -> #REF! | BD49: =IFERROR(VLOOKUP(D49,#REF!,3,0),0) -> 0 | BE49: =MAX(VLOOKUP(D49,#REF!,22,0)-VLOOKUP(D49,#REF!,23,0),0) -> #REF! | BF49: =BB49*BC49+BD49*BE49 -> #REF! | BG49: =BF49-BA49 -> #REF! | BH49: 0 | BK49: 917 | BL49: =ROUNDUP(DI49/(1-0.17)*0.17,0) -> 917 | BM49: =BL49-BK49 -> 0 | BN49: 0 | BR49: 0 | BT49: 0 | BV49: 0 | BX49: 31227.28 | BY49: =SUM(AE49,AH49,AN49,AR49,AU49,AY49,BA49,BH49,BK49,BN49,BR49,BT49) -> 31227.28 | BZ49: =BY49-BX49 -> 0 | CA49: 27810.28 | CB49: =SUM(AE49,AH49,BA49,BH49) -> 27810.28 | CC49: =CB49-CA49 -> 0 | CD49: 0 | CG49: 0 | CI49: 988.3726 | CJ49: 0 | CL49: 0 | CM49: 0.075 | CN49: 0 | CO49: 0 | CP49: 0 | CR49: 0 | CT49: 1500 | CU49: =MIN(BX49*5%,1500) -> 1500 | CV49: =CU49-CT49 -> 0 | CW49: 0 | CX49: =ROUND(CA49*CJ49,2) -> 0 | CY49: =CX49-CW49 -> 0 | CZ49: 1500 | DA49: =MIN(BX49*5%,1500) -> 1500 | DB49: =DA49-CZ49 -> 0 | DC49: 585.77 | DD49: =MAX(ROUND(CA49*CM49-CZ49,2),0) -> 585.77 | DE49: =DD49-DC49 -> 0 | DF49: 29727.28 | DG49: =SUM(AE49,AH49,AN49,AR49,AU49,AY49,BA49,BH49,BK49,BN49,BR49,BT49,BV49,-CG49,-CP49,-CT49,-CW49) -> 29727.28 | DH49: =DG49-DF49 -> 0 | DI49: 4475.85 | DJ49: =IFERROR(VLOOKUP(D49,#REF!,2,0),0) -> 0 | DK49: =DJ49-DI49 -> -4475.85 | DL49: 28727.28 | DM49: 493492.09 | DN49: 2296.92 | DO49: 247.28 | DP49: 0 | DQ49: 30310.28 | DR49: 28 | DS49: 0 | DT49: 2025-01-01 | DU49: 2025-12-31 | DV49: 2025-01-10 | DW49: 2025-02-10
A50: MSD Asia202502 | B50: MERCK SHARP & DOHME (ASIA) LIMITED | C50: MSD Asia | D50: 51442298 | E50: =VLOOKUP(D50,#REF!,1,0) -> #REF! | F50: Tam | G50: Ho Yan | H50: =G50&" "&F50 -> Ho Yan Tam | I50: =VLOOKUP(D50,#REF!,9,0) -> #REF! | J50: =I50=H50 -> #REF! | K50: Issac | L50: Active | M50: 2022-09-26 | N50: =VLOOKUP(D50,#REF!,80,0) -> #REF! | O50: =N50-M50 -> #REF! | P50: HK ONCOLOGY (MA) | Q50: =VLOOKUP(D50,#REF!,50,0) -> #REF! | R50: =Q50=P50 -> #REF! | S50: Marketing Manager | T50: =VLOOKUP(D50,#REF!,21,0) -> #REF! | U50: =T50=S50 -> #REF! | V50: 12630100 | W50: =VLOOKUP(D50,#REF!,51,0) -> #REF! | X50: =W50=V50 -> #REF! | Y50: 202502 | Z50: N | AA50: 2.43 | AB50: 83908 | AC50: =ROUND(VLOOKUP(D50,#REF!,59,0),0) -> #REF! | AD50: =AC50-AB50 -> #REF! | AE50: 83908 | AF50: =AB50 -> 83908 | AG50: =AF50-AE50 -> 0 | AH50: 0 | AK50: 0 | AN50: 0 | AO50: 0 | AP50: =IFERROR(VLOOKUP('Feb for check'!D50,#REF!,15,0),0) -> 0 | AQ50: =AP50-AO50 -> 0 | AR50: 0 | AS50: =AO50 -> 0 | AT50: =AS50-AR50 -> 0 | AU50: 0 | AW50: 0 | AY50: 0 | BA50: 1077.18 | BB50: =IFERROR(VLOOKUP(D50,#REF!,2,0),0) -> 0 | BC50: =MAX(VLOOKUP(D50,#REF!,13,0)-VLOOKUP(D50,#REF!,14,0),0) -> #REF! | BD50: =IFERROR(VLOOKUP(D50,#REF!,3,0),0) -> 0 | BE50: =MAX(VLOOKUP(D50,#REF!,22,0)-VLOOKUP(D50,#REF!,23,0),0) -> #REF! | BF50: =BB50*BC50+BD50*BE50 -> #REF! | BG50: =BF50-BA50 -> #REF! | BH50: 0 | BK50: 55 | BL50: =ROUNDUP(DI50/(1-0.17)*0.17,0) -> 55 | BM50: =BL50-BK50 -> 0 | BN50: 0 | BR50: 0 | BT50: 0 | BV50: 0 | BX50: 85040.18 | BY50: =SUM(AE50,AH50,AN50,AR50,AU50,AY50,BA50,BH50,BK50,BN50,BR50,BT50) -> 85040.18 | BZ50: =BY50-BX50 -> 0 | CA50: 84985.18 | CB50: =SUM(AE50,AH50,BA50,BH50) -> 84985.18 | CC50: =CB50-CA50 -> 0 | CD50: 0 | CG50: 0 | CI50: 2758.6191 | CJ50: 0 | CL50: 0 | CM50: 0.075 | CN50: 0 | CO50: 0 | CP50: 0 | CR50: 0 | CT50: 1500 | CU50: =MIN(BX50*5%,1500) -> 1500 | CV50: =CU50-CT50 -> 0 | CW50: 0 | CX50: =ROUND(CA50*CJ50,2) -> 0 | CY50: =CX50-CW50 -> 0 | CZ50: 1500 | DA50: =MIN(BX50*5%,1500) -> 1500 | DB50: =DA50-CZ50 -> 0 | DC50: 4873.89 | DD50: =MAX(ROUND(CA50*CM50-CZ50,2),0) -> 4873.89 | DE50: =DD50-DC50 -> 0 | DF50: 83540.18 | DG50: =SUM(AE50,AH50,AN50,AR50,AU50,AY50,BA50,BH50,BK50,BN50,BR50,BT50,BV50,-CG50,-CP50,-CT50,-CW50) -> 83540.18 | DH50: =DG50-DF50 -> 0 | DI50: 268.1 | DJ50: =IFERROR(VLOOKUP(D50,#REF!,2,0),0) -> 0 | DK50: =DJ50-DI50 -> -268.1 | DL50: 85040.18 | DM50: 1485527 | DN50: 6992.33 | DO50: 1077.18 | DP50: 0 | DQ50: 84985.18 | DR50: 28 | DS50: 0 | DT50: 2025-01-01 | DU50: 2025-12-31 | DV50: 2025-01-10 | DW50: 2025-02-10
A51: MSD Asia202502 | B51: MERCK SHARP & DOHME (ASIA) LIMITED | C51: MSD Asia | D51: 51461129 | E51: =VLOOKUP(D51,#REF!,1,0) -> #REF! | F51: Kwan | G51: Yat Tung | H51: =G51&" "&F51 -> Yat Tung Kwan | I51: =VLOOKUP(D51,#REF!,9,0) -> #REF! | J51: =I51=H51 -> #REF! | K51: Frank | L51: Active | M51: 2023-04-24 | N51: =VLOOKUP(D51,#REF!,80,0) -> #REF! | O51: =N51-M51 -> #REF! | P51: HK Vaccine (DS) | Q51: =VLOOKUP(D51,#REF!,50,0) -> #REF! | R51: =Q51=P51 -> #REF! | S51: Senior Professional Sales Representative | T51: =VLOOKUP(D51,#REF!,21,0) -> #REF! | U51: =T51=S51 -> #REF! | V51: 12630115 | W51: =VLOOKUP(D51,#REF!,51,0) -> #REF! | X51: =W51=V51 -> #REF! | Y51: 202502 | Z51: N | AA51: 1.85 | AB51: 27521 | AC51: =ROUND(VLOOKUP(D51,#REF!,59,0),0) -> #REF! | AD51: =AC51-AB51 -> #REF! | AE51: 27521 | AF51: =AB51 -> 27521 | AG51: =AF51-AE51 -> 0 | AH51: 0 | AK51: 0 | AN51: 0 | AO51: 2500 | AP51: =IFERROR(VLOOKUP('Feb for check'!D51,#REF!,15,0),0) -> 0 | AQ51: =AP51-AO51 -> -2500 | AR51: 2500 | AS51: =AO51 -> 2500 | AT51: =AS51-AR51 -> 0 | AU51: 0 | AW51: 0 | AY51: 0 | BA51: 597.24 | BB51: =IFERROR(VLOOKUP(D51,#REF!,2,0),0) -> 0 | BC51: =MAX(VLOOKUP(D51,#REF!,13,0)-VLOOKUP(D51,#REF!,14,0),0) -> #REF! | BD51: =IFERROR(VLOOKUP(D51,#REF!,3,0),0) -> 0 | BE51: =MAX(VLOOKUP(D51,#REF!,22,0)-VLOOKUP(D51,#REF!,23,0),0) -> #REF! | BF51: =BB51*BC51+BD51*BE51 -> #REF! | BG51: =BF51-BA51 -> #REF! | BH51: 0 | BK51: 0 | BL51: =ROUNDUP(DI51/(1-0.17)*0.17,0) -> 0 | BM51: =BL51-BK51 -> 0 | BN51: 0 | BR51: 0 | BT51: 0 | BV51: 0 | BX51: 30618.24 | BY51: =SUM(AE51,AH51,AN51,AR51,AU51,AY51,BA51,BH51,BK51,BN51,BR51,BT51) -> 30618.24 | BZ51: =BY51-BX51 -> 0 | CA51: 28118.24 | CB51: =SUM(AE51,AH51,BA51,BH51) -> 28118.24 | CC51: =CB51-CA51 -> 0 | CD51: 0 | CG51: 0 | CI51: 986.9917 | CJ51: 0 | CL51: 0 | CM51: 0.075 | CN51: 0 | CO51: 0 | CP51: 0 | CR51: 0 | CT51: 1500 | CU51: =MIN(BX51*5%,1500) -> 1500 | CV51: =CU51-CT51 -> 0 | CW51: 0 | CX51: =ROUND(CA51*CJ51,2) -> 0 | CY51: =CX51-CW51 -> 0 | CZ51: 1500 | DA51: =MIN(BX51*5%,1500) -> 1500 | DB51: =DA51-CZ51 -> 0 | DC51: 608.87 | DD51: =MAX(ROUND(CA51*CM51-CZ51,2),0) -> 608.87 | DE51: =DD51-DC51 -> 0 | DF51: 29118.24 | DG51: =SUM(AE51,AH51,AN51,AR51,AU51,AY51,BA51,BH51,BK51,BN51,BR51,BT51,BV51,-CG51,-CP51,-CT51,-CW51) -> 29118.24 | DH51: =DG51-DF51 -> 0 | DI51: 0 | DJ51: =IFERROR(VLOOKUP(D51,#REF!,2,0),0) -> 0 | DK51: =DJ51-DI51 -> 0 | DL51: 28118.24 | DM51: 472563.16 | DN51: 2293.42 | DO51: 597.24 | DP51: 0 | DQ51: 30618.24 | DR51: 28 | DS51: 0 | DT51: 2025-01-01 | DU51: 2025-12-31 | DV51: 2025-01-10 | DW51: 2025-02-10
A52: MSD Asia202502 | B52: MERCK SHARP & DOHME (ASIA) LIMITED | C52: MSD Asia | D52: 33990029 | E52: =VLOOKUP(D52,#REF!,1,0) -> #REF! | F52: Chau | G52: Yu Tung Gloria | H52: =G52&" "&F52 -> Yu Tung Gloria Chau | I52: =VLOOKUP(D52,#REF!,9,0) -> #REF! | J52: =I52=H52 -> #REF! | K52: Gloria | L52: Active | M52: 2024-11-29 | N52: =VLOOKUP(D52,#REF!,80,0) -> #REF! | O52: =N52-M52 -> #REF! | P52: MRL HKG GCTO | Q52: =VLOOKUP(D52,#REF!,50,0) -> #REF! | R52: =Q52=P52 -> #REF! | S52: COM Lead | T52: =VLOOKUP(D52,#REF!,21,0) -> #REF! | U52: =T52=S52 -> #REF! | V52: 12630167 | W52: =VLOOKUP(D52,#REF!,51,0) -> #REF! | X52: =W52=V52 -> #REF! | Y52: 202502 | Z52: N | AA52: 23.72 | AB52: 86000 | AC52: =ROUND(VLOOKUP(D52,#REF!,59,0),0) -> #REF! | AD52: =AC52-AB52 -> #REF! | AE52: 86000 | AF52: =AB52 -> 86000 | AG52: =AF52-AE52 -> 0 | AH52: 0 | AK52: 0 | AN52: 0 | AO52: 0 | AP52: =IFERROR(VLOOKUP('Feb for check'!D52,#REF!,15,0),0) -> 0 | AQ52: =AP52-AO52 -> 0 | AR52: 0 | AS52: =AO52 -> 0 | AT52: =AS52-AR52 -> 0 | AU52: 0 | AW52: 0 | AY52: 0 | BA52: 0 | BB52: =IFERROR(VLOOKUP(D52,#REF!,2,0),0) -> 0 | BC52: =MAX(VLOOKUP(D52,#REF!,13,0)-VLOOKUP(D52,#REF!,14,0),0) -> #REF! | BD52: =IFERROR(VLOOKUP(D52,#REF!,3,0),0) -> 0 | BE52: =MAX(VLOOKUP(D52,#REF!,22,0)-VLOOKUP(D52,#REF!,23,0),0) -> #REF! | BF52: =BB52*BC52+BD52*BE52 -> #REF! | BG52: =BF52-BA52 -> #REF! | BH52: 0 | BK52: 0 | BL52: =ROUNDUP(DI52/(1-0.17)*0.17,0) -> 0 | BM52: =BL52-BK52 -> 0 | BN52: 0 | BO52: =VLOOKUP(D52,#REF!,84,0) -> #REF! | BP52: =ROUND(AB52*(DATEDIF(M52,DATE(2025,1,1),"D"))/366,2) -> 7754.1 | BQ52: 未过试用期 | BR52: 0 | BT52: 0 | BV52: 0 | BX52: 86000 | BY52: =SUM(AE52,AH52,AN52,AR52,AU52,AY52,BA52,BH52,BK52,BN52,BR52,BT52) -> 86000 | BZ52: =BY52-BX52 -> 0 | CA52: 86000 | CB52: =SUM(AE52,AH52,BA52,BH52) -> 86000 | CC52: =CB52-CA52 -> 0 | CD52: 0 | CG52: 0 | CI52: 2827.3972 | CJ52: 0.05 | CL52: 0 | CM52: 0.1 | CN52: 0 | CO52: 0 | CP52: 0 | CR52: 0 | CT52: 1500 | CU52: =MIN(BX52*5%,1500) -> 1500 | CV52: =CU52-CT52 -> 0 | CW52: 4300 | CX52: =ROUND(CA52*CJ52,2) -> 4300 | CY52: =CX52-CW52 -> 0 | CZ52: 1500 | DA52: =MIN(BX52*5%,1500) -> 1500 | DB52: =DA52-CZ52 -> 0 | DC52: 7100 | DD52: =MAX(ROUND(CA52*CM52-CZ52,2),0) -> 7100 | DE52: =DD52-DC52 -> 0 | DF52: 80200 | DG52: =SUM(AE52,AH52,AN52,AR52,AU52,AY52,BA52,BH52,BK52,BN52,BR52,BT52,BV52,-CG52,-CP52,-CT52,-CW52) -> 80200 | DH52: =DG52-DF52 -> 0 | DI52: 0 | DJ52: =IFERROR(VLOOKUP(D52,#REF!,2,0),0) -> 0 | DK52: =DJ52-DI52 -> 0 | DL52: 86000 | DM52: 285671.33 | DN52: 7166.67 | DO52: 0 | DP52: 0 | DQ52: 86000 | DR52: 28 | DS52: 7754.1 | DT52: 2025-01-01 | DU52: 2025-12-31 | DV52: 2025-01-10 | DW52: 2025-02-10
A53: MSD Asia202502 | B53: MERCK SHARP & DOHME (ASIA) LIMITED | C53: MSD Asia | D53: 51449285 | E53: =VLOOKUP(D53,#REF!,1,0) -> #REF! | F53: Wong | G53: Hio Wa | H53: =G53&" "&F53 -> Hio Wa Wong | I53: =VLOOKUP(D53,#REF!,9,0) -> #REF! | J53: =I53=H53 -> #REF! | K53: Anthea | L53: Active | M53: 2023-01-04 | N53: =VLOOKUP(D53,#REF!,80,0) -> #REF! | O53: =N53-M53 -> #REF! | P53: HK SPECIALTY CARE (MA) | Q53: =VLOOKUP(D53,#REF!,50,0) -> #REF! | R53: =Q53=P53 -> #REF! | S53: Associate Product Manager | T53: =VLOOKUP(D53,#REF!,21,0) -> #REF! | U53: =T53=S53 -> #REF! | V53: 12630103 | W53: =VLOOKUP(D53,#REF!,51,0) -> #REF! | X53: =W53=V53 -> #REF! | Y53: 202502 | Z53: N | AA53: 2.15 | AB53: 46534 | AC53: =ROUND(VLOOKUP(D53,#REF!,59,0),0) -> #REF! | AD53: =AC53-AB53 -> #REF! | AE53: 46534 | AF53: =AB53 -> 46534 | AG53: =AF53-AE53 -> 0 | AH53: 0 | AK53: 0 | AN53: 0 | AO53: 0 | AP53: =IFERROR(VLOOKUP('Feb for check'!D53,#REF!,15,0),0) -> 0 | AQ53: =AP53-AO53 -> 0 | AR53: 0 | AS53: =AO53 -> 0 | AT53: =AS53-AR53 -> 0 | AU53: 0 | AW53: 0 | AY53: 0 | BA53: 0 | BB53: =IFERROR(VLOOKUP(D53,#REF!,2,0),0) -> 0 | BC53: =MAX(VLOOKUP(D53,#REF!,13,0)-VLOOKUP(D53,#REF!,14,0),0) -> #REF! | BD53: =IFERROR(VLOOKUP(D53,#REF!,3,0),0) -> 0 | BE53: =MAX(VLOOKUP(D53,#REF!,22,0)-VLOOKUP(D53,#REF!,23,0),0) -> #REF! | BF53: =BB53*BC53+BD53*BE53 -> #REF! | BG53: =BF53-BA53 -> #REF! | BH53: 0 | BK53: 1027 | BL53: =ROUNDUP(DI53/(1-0.17)*0.17,0) -> 1027 | BM53: =BL53-BK53 -> 0 | BN53: 0 | BR53: 0 | BT53: 0 | BV53: 0 | BX53: 47561 | BY53: =SUM(AE53,AH53,AN53,AR53,AU53,AY53,BA53,BH53,BK53,BN53,BR53,BT53) -> 47561 | BZ53: =BY53-BX53 -> 0 | CA53: 46534 | CB53: =SUM(AE53,AH53,BA53,BH53) -> 46534 | CC53: =CB53-CA53 -> 0 | CD53: 0 | CG53: 0 | CI53: 1529.8849 | CJ53: 0 | CL53: 0 | CM53: 0.075 | CN53: 0 | CO53: 0 | CP53: 0 | CR53: 0 | CT53: 1500 | CU53: =MIN(BX53*5%,1500) -> 1500 | CV53: =CU53-CT53 -> 0 | CW53: 0 | CX53: =ROUND(CA53*CJ53,2) -> 0 | CY53: =CX53-CW53 -> 0 | CZ53: 1500 | DA53: =MIN(BX53*5%,1500) -> 1500 | DB53: =DA53-CZ53 -> 0 | DC53: 1990.05 | DD53: =MAX(ROUND(CA53*CM53-CZ53,2),0) -> 1990.05 | DE53: =DD53-DC53 -> 0 | DF53: 46061 | DG53: =SUM(AE53,AH53,AN53,AR53,AU53,AY53,BA53,BH53,BK53,BN53,BR53,BT53,BV53,-CG53,-CP53,-CT53,-CW53) -> 46061 | DH53: =DG53-DF53 -> 0 | DI53: 5012.06 | DJ53: =IFERROR(VLOOKUP(D53,#REF!,2,0),0) -> 0 | DK53: =DJ53-DI53 -> -5012.06 | DL53: 47561 | DM53: 740183 | DN53: 3877.83 | DO53: 0 | DP53: 0 | DQ53: 46534 | DR53: 28 | DS53: 0 | DT53: 2025-01-01 | DU53: 2025-12-31 | DV53: 2025-01-10 | DW53: 2025-02-10
A54: MSD Asia202502 | B54: MERCK SHARP & DOHME (ASIA) LIMITED | C54: MSD Asia | D54: 51482720 | E54: =VLOOKUP(D54,#REF!,1,0) -> #REF! | F54: Lee | G54: Hin Lam | H54: =G54&" "&F54 -> Hin Lam Lee | I54: =VLOOKUP(D54,#REF!,9,0) -> #REF! | J54: =I54=H54 -> #REF! | K54: Eunice | L54: Active | M54: 2024-02-26 | N54: =VLOOKUP(D54,#REF!,80,0) -> #REF! | O54: =N54-M54 -> #REF! | P54: HK ONCOLOGY ALLIANCE (DS) | Q54: =VLOOKUP(D54,#REF!,50,0) -> #REF! | R54: =Q54=P54 -> #REF! | S54: Senior Professional Sales Representative | T54: =VLOOKUP(D54,#REF!,21,0) -> #REF! | U54: =T54=S54 -> #REF! | V54: 12630113 | W54: =VLOOKUP(D54,#REF!,51,0) -> #REF! | X54: =W54=V54 -> #REF! | Y54: 202502 | Z54: N | AA54: 1.01 | AB54: 29000 | AC54: =ROUND(VLOOKUP(D54,#REF!,59,0),0) -> #REF! | AD54: =AC54-AB54 -> #REF! | AE54: 29000 | AF54: =AB54 -> 29000 | AG54: =AF54-AE54 -> 0 | AH54: 0 | AK54: 0 | AN54: 0 | AO54: 2500 | AP54: =IFERROR(VLOOKUP('Feb for check'!D54,#REF!,15,0),0) -> 0 | AQ54: =AP54-AO54 -> -2500 | AR54: 2500 | AS54: =AO54 -> 2500 | AT54: =AS54-AR54 -> 0 | AU54: 0 | AW54: 0 | AY54: 0 | BA54: 0 | BB54: =IFERROR(VLOOKUP(D54,#REF!,2,0),0) -> 0 | BC54: =MAX(VLOOKUP(D54,#REF!,13,0)-VLOOKUP(D54,#REF!,14,0),0) -> #REF! | BD54: =IFERROR(VLOOKUP(D54,#REF!,3,0),0) -> 0 | BE54: =MAX(VLOOKUP(D54,#REF!,22,0)-VLOOKUP(D54,#REF!,23,0),0) -> #REF! | BF54: =BB54*BC54+BD54*BE54 -> #REF! | BG54: =BF54-BA54 -> #REF! | BH54: 0 | BK54: 0 | BL54: =ROUNDUP(DI54/(1-0.17)*0.17,0) -> 0 | BM54: =BL54-BK54 -> 0 | BN54: 0 | BR54: 0 | BT54: 0 | BV54: 0 | BX54: 31500 | BY54: =SUM(AE54,AH54,AN54,AR54,AU54,AY54,BA54,BH54,BK54,BN54,BR54,BT54) -> 31500 | BZ54: =BY54-BX54 -> 0 | CA54: 29000 | CB54: =SUM(AE54,AH54,BA54,BH54) -> 29000 | CC54: =CB54-CA54 -> 0 | CD54: 0 | CG54: 0 | CI54: 1035.6164 | CJ54: 0 | CL54: 0 | CM54: 0.075 | CN54: 0 | CO54: 0 | CP54: 0 | CR54: 0 | CT54: 1500 | CU54: =MIN(BX54*5%,1500) -> 1500 | CV54: =CU54-CT54 -> 0 | CW54: 0 | CX54: =ROUND(CA54*CJ54,2) -> 0 | CY54: =CX54-CW54 -> 0 | CZ54: 1500 | DA54: =MIN(BX54*5%,1500) -> 1500 | DB54: =DA54-CZ54 -> 0 | DC54: 675 | DD54: =MAX(ROUND(CA54*CM54-CZ54,2),0) -> 675 | DE54: =DD54-DC54 -> 0 | DF54: 30000 | DG54: =SUM(AE54,AH54,AN54,AR54,AU54,AY54,BA54,BH54,BK54,BN54,BR54,BT54,BV54,-CG54,-CP54,-CT54,-CW54) -> 30000 | DH54: =DG54-DF54 -> 0 | DI54: 0 | DJ54: =IFERROR(VLOOKUP(D54,#REF!,2,0),0) -> 0 | DK54: =DJ54-DI54 -> 0 | DL54: 29000 | DM54: 493617.09 | DN54: 2416.67 | DO54: 0 | DP54: 0 | DQ54: 31500 | DR54: 28 | DS54: 0 | DT54: 2025-01-01 | DU54: 2025-12-31 | DV54: 2025-01-10 | DW54: 2025-02-10
A55: MSD Asia202502 | B55: MERCK SHARP & DOHME (ASIA) LIMITED | C55: MSD Asia | D55: 33900325 | E55: =VLOOKUP(D55,#REF!,1,0) -> #REF! | F55: Lai | G55: Man See Mancy | H55: =G55&" "&F55 -> Man See Mancy Lai | I55: =VLOOKUP(D55,#REF!,9,0) -> #REF! | J55: =I55=H55 -> #REF! | K55: Mancy | L55: Active | M55: 1997-03-01 | N55: =VLOOKUP(D55,#REF!,80,0) -> #REF! | O55: =N55-M55 -> #REF! | P55: HK MD Office | Q55: =VLOOKUP(D55,#REF!,50,0) -> #REF! | R55: =Q55=P55 -> #REF! | S55: Executive Secretary | T55: =VLOOKUP(D55,#REF!,21,0) -> #REF! | U55: =T55=S55 -> #REF! | V55: 12630109 | W55: =VLOOKUP(D55,#REF!,51,0) -> #REF! | X55: =W55=V55 -> #REF! | Y55: 202502 | Z55: N | AA55: 28 | AB55: 56538 | AC55: =ROUND(VLOOKUP(D55,#REF!,59,0),0) -> #REF! | AD55: =AC55-AB55 -> #REF! | AE55: 56538 | AF55: =AB55 -> 56538 | AG55: =AF55-AE55 -> 0 | AH55: 0 | AK55: 0 | AN55: 0 | AO55: 0 | AP55: =IFERROR(VLOOKUP('Feb for check'!D55,#REF!,15,0),0) -> 0 | AQ55: =AP55-AO55 -> 0 | AR55: 0 | AS55: =AO55 -> 0 | AT55: =AS55-AR55 -> 0 | AU55: 0 | AW55: 0 | AY55: 0 | BA55: 0 | BB55: =IFERROR(VLOOKUP(D55,#REF!,2,0),0) -> 0 | BC55: =MAX(VLOOKUP(D55,#REF!,13,0)-VLOOKUP(D55,#REF!,14,0),0) -> #REF! | BD55: =IFERROR(VLOOKUP(D55,#REF!,3,0),0) -> 0 | BE55: =MAX(VLOOKUP(D55,#REF!,22,0)-VLOOKUP(D55,#REF!,23,0),0) -> #REF! | BF55: =BB55*BC55+BD55*BE55 -> #REF! | BG55: =BF55-BA55 -> #REF! | BH55: 0 | BK55: 917 | BL55: =ROUNDUP(DI55/(1-0.17)*0.17,0) -> 917 | BM55: =BL55-BK55 -> 0 | BN55: 0 | BR55: 0 | BT55: 0 | BV55: 0 | BX55: 57455 | BY55: =SUM(AE55,AH55,AN55,AR55,AU55,AY55,BA55,BH55,BK55,BN55,BR55,BT55) -> 57455 | BZ55: =BY55-BX55 -> 0 | CA55: 56538 | CB55: =SUM(AE55,AH55,BA55,BH55) -> 56538 | CC55: =CB55-CA55 -> 0 | CD55: 0 | CG55: 0 | CI55: 1858.7835 | CJ55: 0.05 | CL55: 0 | CM55: 0.1 | CN55: 0 | CO55: 0 | CP55: 0 | CR55: 0 | CT55: 0 | CU55: =MIN(BX55*5%,1500) -> 1500 | CV55: 超过65周岁没有MPF | CW55: 0 | CX55: =ROUND(CA55*CJ55,2) -> 2826.9 | CY55: 超过65周岁没有MPF | CZ55: 0 | DA55: =MIN(BX55*5%,1500) -> 1500 | DB55: 超过65周岁没有MPF | DC55: 0 | DD55: =MAX(ROUND(CA55*CM55-CZ55,2),0) -> 5653.8 | DE55: 超过65周岁没有MPF | DF55: 57455 | DG55: =SUM(AE55,AH55,AN55,AR55,AU55,AY55,BA55,BH55,BK55,BN55,BR55,BT55,BV55,-CG55,-CP55,-CT55,-CW55) -> 57455 | DH55: =DG55-DF55 -> 0 | DI55: 4475.85 | DJ55: =IFERROR(VLOOKUP(D55,#REF!,2,0),0) -> 0 | DK55: =DJ55-DI55 -> -4475.85 | DL55: 57455 | DM55: 829774.81 | DN55: 4711.5 | DO55: 0 | DP55: 0 | DQ55: 56538 | DR55: 28 | DS55: 0 | DT55: 2025-01-01 | DU55: 2025-12-31 | DV55: 2025-01-10 | DW55: 2025-02-10
A56: MSD Asia202502 | B56: MERCK SHARP & DOHME (ASIA) LIMITED | C56: MSD Asia | D56: 51232402 | E56: =VLOOKUP(D56,#REF!,1,0) -> #REF! | F56: Gu | G56: Pei Shan | H56: =G56&" "&F56 -> Pei Shan Gu | I56: =VLOOKUP(D56,#REF!,9,0) -> #REF! | J56: =I56=H56 -> #REF! | K56: Sammi | L56: Active | M56: 2015-09-01 | N56: =VLOOKUP(D56,#REF!,80,0) -> #REF! | O56: =N56-M56 -> #REF! | P56: HK VACCINE (MA) | Q56: =VLOOKUP(D56,#REF!,50,0) -> #REF! | R56: =Q56=P56 -> #REF! | S56: Associate Product Manager | T56: =VLOOKUP(D56,#REF!,21,0) -> #REF! | U56: =T56=S56 -> #REF! | V56: 12630102 | W56: =VLOOKUP(D56,#REF!,51,0) -> #REF! | X56: =W56=V56 -> #REF! | Y56: 202502 | Z56: N | AA56: 9.5 | AB56: 49425 | AC56: =ROUND(VLOOKUP(D56,#REF!,59,0),0) -> #REF! | AD56: =AC56-AB56 -> #REF! | AE56: 49425 | AF56: =AB56 -> 49425 | AG56: =AF56-AE56 -> 0 | AH56: 0 | AK56: 0 | AN56: 0 | AO56: 0 | AP56: =IFERROR(VLOOKUP('Feb for check'!D56,#REF!,15,0),0) -> 0 | AQ56: =AP56-AO56 -> 0 | AR56: 0 | AS56: =AO56 -> 0 | AT56: =AS56-AR56 -> 0 | AU56: 0 | AW56: 0 | AY56: 0 | BA56: 0 | BB56: =IFERROR(VLOOKUP(D56,#REF!,2,0),0) -> 0 | BC56: =MAX(VLOOKUP(D56,#REF!,13,0)-VLOOKUP(D56,#REF!,14,0),0) -> #REF! | BD56: =IFERROR(VLOOKUP(D56,#REF!,3,0),0) -> 0 | BE56: =MAX(VLOOKUP(D56,#REF!,22,0)-VLOOKUP(D56,#REF!,23,0),0) -> #REF! | BF56: =BB56*BC56+BD56*BE56 -> #REF! | BG56: =BF56-BA56 -> #REF! | BH56: 0 | BK56: 0 | BL56: =ROUNDUP(DI56/(1-0.17)*0.17,0) -> 0 | BM56: =BL56-BK56 -> 0 | BN56: 0 | BR56: 0 | BT56: 0 | BV56: 0 | BX56: 49425 | BY56: =SUM(AE56,AH56,AN56,AR56,AU56,AY56,BA56,BH56,BK56,BN56,BR56,BT56) -> 49425 | BZ56: =BY56-BX56 -> 0 | CA56: 49425 | CB56: =SUM(AE56,AH56,BA56,BH56) -> 49425 | CC56: =CB56-CA56 -> 0 | CD56: 0 | CG56: 0 | CI56: 1624.9315 | CJ56: 0 | CL56: 0 | CM56: 0.075 | CN56: 0 | CO56: 0 | CP56: 0 | CR56: 0 | CT56: 1500 | CU56: =MIN(BX56*5%,1500) -> 1500 | CV56: =CU56-CT56 -> 0 | CW56: 0 | CX56: =ROUND(CA56*CJ56,2) -> 0 | CY56: =CX56-CW56 -> 0 | CZ56: 1500 | DA56: =MIN(BX56*5%,1500) -> 1500 | DB56: =DA56-CZ56 -> 0 | DC56: 2206.88 | DD56: =MAX(ROUND(CA56*CM56-CZ56,2),0) -> 2206.88 | DE56: =DD56-DC56 -> 0 | DF56: 47925 | DG56: =SUM(AE56,AH56,AN56,AR56,AU56,AY56,BA56,BH56,BK56,BN56,BR56,BT56,BV56,-CG56,-CP56,-CT56,-CW56) -> 47925 | DH56: =DG56-DF56 -> 0 | DI56: 0 | DJ56: =IFERROR(VLOOKUP(D56,#REF!,2,0),0) -> 0 | DK56: =DJ56-DI56 -> 0 | DL56: 49425 | DM56: 809171.75 | DN56: 4118.75 | DO56: 0 | DP56: 0 | DQ56: 49425 | DR56: 28 | DS56: 0 | DT56: 2025-01-01 | DU56: 2025-12-31 | DV56: 2025-01-10 | DW56: 2025-02-10
A57: MSD Asia202502 | B57: MERCK SHARP & DOHME (ASIA) LIMITED | C57: MSD Asia | D57: 51068656 | E57: =VLOOKUP(D57,#REF!,1,0) -> #REF! | F57: Jen | G57: Che Lung | H57: =G57&" "&F57 -> Che Lung Jen | I57: =VLOOKUP(D57,#REF!,9,0) -> #REF! | J57: =I57=H57 -> #REF! | K57: Jason | L57: Active | M57: 2017-06-01 | N57: =VLOOKUP(D57,#REF!,80,0) -> #REF! | O57: =N57-M57 -> #REF! | P57: MRL HKG ONCOLOGY GMA | Q57: =VLOOKUP(D57,#REF!,50,0) -> #REF! | R57: =Q57=P57 -> #REF! | S57: Country Medical Lead & Oncology Medical Lead | T57: =VLOOKUP(D57,#REF!,21,0) -> #REF! | U57: =T57=S57 -> #REF! | V57: 12630107 | W57: =VLOOKUP(D57,#REF!,51,0) -> #REF! | X57: =W57=V57 -> #REF! | Y57: 202502 | Z57: N | AA57: 7.75 | AB57: 84258 | AC57: =ROUND(VLOOKUP(D57,#REF!,59,0),0) -> #REF! | AD57: =AC57-AB57 -> #REF! | AE57: 84258 | AF57: =AB57 -> 84258 | AG57: =AF57-AE57 -> 0 | AH57: 0 | AK57: 0 | AN57: 0 | AO57: 0 | AP57: =IFERROR(VLOOKUP('Feb for check'!D57,#REF!,15,0),0) -> 0 | AQ57: =AP57-AO57 -> 0 | AR57: 0 | AS57: =AO57 -> 0 | AT57: =AS57-AR57 -> 0 | AU57: 0 | AW57: 0 | AY57: 0 | BA57: 3204.24 | BB57: =IFERROR(VLOOKUP(D57,#REF!,2,0),0) -> 0 | BC57: =MAX(VLOOKUP(D57,#REF!,13,0)-VLOOKUP(D57,#REF!,14,0),0) -> #REF! | BD57: =IFERROR(VLOOKUP(D57,#REF!,3,0),0) -> 0 | BE57: =MAX(VLOOKUP(D57,#REF!,22,0)-VLOOKUP(D57,#REF!,23,0),0) -> #REF! | BF57: =BB57*BC57+BD57*BE57 -> #REF! | BG57: =BF57-BA57 -> #REF! | BH57: 0 | BK57: 2751 | BL57: =ROUNDUP(DI57/(1-0.17)*0.17,0) -> 2751 | BM57: =BL57-BK57 -> 0 | BN57: 0 | BR57: 0 | BT57: 0 | BV57: 0 | BX57: 90213.24 | BY57: =SUM(AE57,AH57,AN57,AR57,AU57,AY57,BA57,BH57,BK57,BN57,BR57,BT57) -> 90213.24 | BZ57: =BY57-BX57 -> 0 | CA57: 87462.24 | CB57: =SUM(AE57,AH57,BA57,BH57) -> 87462.24 | CC57: =CB57-CA57 -> 0 | CD57: 0 | CG57: 0 | CI57: 2770.126 | CJ57: 0 | CL57: 0 | CM57: 0.075 | CN57: 0 | CO57: 0 | CP57: 0 | CR57: 0 | CT57: 1500 | CU57: =MIN(BX57*5%,1500) -> 1500 | CV57: =CU57-CT57 -> 0 | CW57: 0 | CX57: =ROUND(CA57*CJ57,2) -> 0 | CY57: =CX57-CW57 -> 0 | CZ57: 1500 | DA57: =MIN(BX57*5%,1500) -> 1500 | DB57: =DA57-CZ57 -> 0 | DC57: 5059.67 | DD57: =MAX(ROUND(CA57*CM57-CZ57,2),0) -> 5059.67 | DE57: =DD57-DC57 -> 0 | DF57: 88713.24 | DG57: =SUM(AE57,AH57,AN57,AR57,AU57,AY57,BA57,BH57,BK57,BN57,BR57,BT57,BV57,-CG57,-CP57,-CT57,-CW57) -> 88713.24 | DH57: =DG57-DF57 -> 0 | DI57: 13427.55 | DJ57: =IFERROR(VLOOKUP(D57,#REF!,2,0),0) -> 0 | DK57: =DJ57-DI57 -> -13427.55 | DL57: 90213.24 | DM57: 1501093.2 | DN57: 7021.5 | DO57: 3204.24 | DP57: 0 | DQ57: 87462.24 | DR57: 28 | DS57: 0 | DT57: 2025-01-01 | DU57: 2025-12-31 | DV57: 2025-01-10 | DW57: 2025-02-10
A58: MSD Asia202502 | B58: MERCK SHARP & DOHME (ASIA) LIMITED | C58: MSD Asia | D58: 51459366 | E58: =VLOOKUP(D58,#REF!,1,0) -> #REF! | F58: Ma | G58: Sze Wai | H58: =G58&" "&F58 -> Sze Wai Ma | I58: =VLOOKUP(D58,#REF!,9,0) -> #REF! | J58: Correct in ADP | K58: Joyce | L58: Active | M58: 2023-04-03 | N58: =VLOOKUP(D58,#REF!,80,0) -> #REF! | O58: =N58-M58 -> #REF! | P58: HK Vaccine (DS) | Q58: =VLOOKUP(D58,#REF!,50,0) -> #REF! | R58: =Q58=P58 -> #REF! | S58: Senior Professional Sales Representative | T58: =VLOOKUP(D58,#REF!,21,0) -> #REF! | U58: =T58=S58 -> #REF! | V58: 12630115 | W58: =VLOOKUP(D58,#REF!,51,0) -> #REF! | X58: =W58=V58 -> #REF! | Y58: 202502 | Z58: N | AA58: 1.91 | AB58: 27944 | AC58: =ROUND(VLOOKUP(D58,#REF!,59,0),0) -> #REF! | AD58: =AC58-AB58 -> #REF! | AE58: 27944 | AF58: =AB58 -> 27944 | AG58: =AF58-AE58 -> 0 | AH58: 0 | AK58: 0 | AN58: 0 | AO58: 2500 | AP58: =IFERROR(VLOOKUP('Feb for check'!D58,#REF!,15,0),0) -> 0 | AQ58: =AP58-AO58 -> -2500 | AR58: 2500 | AS58: =AO58 -> 2500 | AT58: =AS58-AR58 -> 0 | AU58: 0 | AW58: 0 | AY58: 0 | BA58: 0 | BB58: =IFERROR(VLOOKUP(D58,#REF!,2,0),0) -> 0 | BC58: =MAX(VLOOKUP(D58,#REF!,13,0)-VLOOKUP(D58,#REF!,14,0),0) -> #REF! | BD58: =IFERROR(VLOOKUP(D58,#REF!,3,0),0) -> 0 | BE58: =MAX(VLOOKUP(D58,#REF!,22,0)-VLOOKUP(D58,#REF!,23,0),0) -> #REF! | BF58: =BB58*BC58+BD58*BE58 -> #REF! | BG58: =BF58-BA58 -> #REF! | BH58: 0 | BK58: 0 | BL58: =ROUNDUP(DI58/(1-0.17)*0.17,0) -> 0 | BM58: =BL58-BK58 -> 0 | BN58: 0 | BR58: 0 | BT58: 0 | BV58: 0 | BX58: 30444 | BY58: =SUM(AE58,AH58,AN58,AR58,AU58,AY58,BA58,BH58,BK58,BN58,BR58,BT58) -> 30444 | BZ58: =BY58-BX58 -> 0 | CA58: 27944 | CB58: =SUM(AE58,AH58,BA58,BH58) -> 27944 | CC58: =CB58-CA58 -> 0 | CD58: 0 | CG58: 0 | CI58: 1000.8986 | CJ58: 0 | CL58: 0 | CM58: 0.075 | CN58: 0 | CO58: 0 | CP58: 0 | CR58: 0 | CT58: 1500 | CU58: =MIN(BX58*5%,1500) -> 1500 | CV58: =CU58-CT58 -> 0 | CW58: 0 | CX58: =ROUND(CA58*CJ58,2) -> 0 | CY58: =CX58-CW58 -> 0 | CZ58: 1500 | DA58: =MIN(BX58*5%,1500) -> 1500 | DB58: =DA58-CZ58 -> 0 | DC58: 595.8 | DD58: =MAX(ROUND(CA58*CM58-CZ58,2),0) -> 595.8 | DE58: =DD58-DC58 -> 0 | DF58: 28944 | DG58: =SUM(AE58,AH58,AN58,AR58,AU58,AY58,BA58,BH58,BK58,BN58,BR58,BT58,BV58,-CG58,-CP58,-CT58,-CW58) -> 28944 | DH58: =DG58-DF58 -> 0 | DI58: 0 | DJ58: =IFERROR(VLOOKUP(D58,#REF!,2,0),0) -> 0 | DK58: =DJ58-DI58 -> 0 | DL58: 27944 | DM58: 518516.5 | DN58: 2328.67 | DO58: 0 | DP58: 0 | DQ58: 30444 | DR58: 28 | DS58: 0 | DT58: 2025-01-01 | DU58: 2025-12-31 | DV58: 2025-01-10 | DW58: 2025-02-10
A59: MSD Asia202502 | B59: MERCK SHARP & DOHME (ASIA) LIMITED | C59: MSD Asia | D59: 51315251 | E59: =VLOOKUP(D59,#REF!,1,0) -> #REF! | F59: Lee | G59: Pui Shan | H59: =G59&" "&F59 -> Pui Shan Lee | I59: =VLOOKUP(D59,#REF!,9,0) -> #REF! | J59: =I59=H59 -> #REF! | K59: Catherine | L59: Active | M59: 2018-07-16 | N59: =VLOOKUP(D59,#REF!,80,0) -> #REF! | O59: =N59-M59 -> #REF! | P59: IT Client Services - HK | Q59: =VLOOKUP(D59,#REF!,50,0) -> #REF! | R59: =Q59=P59 -> #REF! | S59: Specialist, Market Business Technologist , Asia Pacific IT | T59: =VLOOKUP(D59,#REF!,21,0) -> #REF! | U59: =T59=S59 -> #REF! | V59: 12630021 | W59: =VLOOKUP(D59,#REF!,51,0) -> #REF! | X59: =W59=V59 -> #REF! | Y59: 202502 | Z59: N | AA59: 6.62 | AB59: 43640 | AC59: =ROUND(VLOOKUP(D59,#REF!,59,0),0) -> #REF! | AD59: =AC59-AB59 -> #REF! | AE59: 43640 | AF59: =AB59 -> 43640 | AG59: =AF59-AE59 -> 0 | AH59: 0 | AK59: 0 | AN59: 0 | AO59: 0 | AP59: =IFERROR(VLOOKUP('Feb for check'!D59,#REF!,15,0),0) -> 0 | AQ59: =AP59-AO59 -> 0 | AR59: 0 | AS59: =AO59 -> 0 | AT59: =AS59-AR59 -> 0 | AU59: 0 | AW59: 0 | AY59: 0 | BA59: 0 | BB59: =IFERROR(VLOOKUP(D59,#REF!,2,0),0) -> 0 | BC59: =MAX(VLOOKUP(D59,#REF!,13,0)-VLOOKUP(D59,#REF!,14,0),0) -> #REF! | BD59: =IFERROR(VLOOKUP(D59,#REF!,3,0),0) -> 0 | BE59: =MAX(VLOOKUP(D59,#REF!,22,0)-VLOOKUP(D59,#REF!,23,0),0) -> #REF! | BF59: =BB59*BC59+BD59*BE59 -> #REF! | BG59: =BF59-BA59 -> #REF! | BH59: 0 | BK59: 110 | BL59: =ROUNDUP(DI59/(1-0.17)*0.17,0) -> 110 | BM59: =BL59-BK59 -> 0 | BN59: 0 | BR59: 0 | BT59: 0 | BV59: 0 | BX59: 43750 | BY59: =SUM(AE59,AH59,AN59,AR59,AU59,AY59,BA59,BH59,BK59,BN59,BR59,BT59) -> 43750 | BZ59: =BY59-BX59 -> 0 | CA59: 43640 | CB59: =SUM(AE59,AH59,BA59,BH59) -> 43640 | CC59: =CB59-CA59 -> 0 | CD59: 0 | CG59: 0 | CI59: 1434.7397 | CJ59: 0.03 | CL59: 0 | CM59: 0.09 | CN59: 0 | CO59: 0 | CP59: 0 | CR59: 0 | CT59: 1500 | CU59: =MIN(BX59*5%,1500) -> 1500 | CV59: =CU59-CT59 -> 0 | CW59: 1309.2 | CX59: =ROUND(CA59*CJ59,2) -> 1309.2 | CY59: =CX59-CW59 -> 0 | CZ59: 1500 | DA59: =MIN(BX59*5%,1500) -> 1500 | DB59: =DA59-CZ59 -> 0 | DC59: 2427.6 | DD59: =MAX(ROUND(CA59*CM59-CZ59,2),0) -> 2427.6 | DE59: =DD59-DC59 -> 0 | DF59: 40940.8 | DG59: =SUM(AE59,AH59,AN59,AR59,AU59,AY59,BA59,BH59,BK59,BN59,BR59,BT59,BV59,-CG59,-CP59,-CT59,-CW59) -> 40940.8 | DH59: =DG59-DF59 -> 0 | DI59: 536.21 | DJ59: =IFERROR(VLOOKUP(D59,#REF!,2,0),0) -> 0 | DK59: =DJ59-DI59 -> -536.21 | DL59: 43750 | DM59: 687665.87 | DN59: 3636.67 | DO59: 0 | DP59: 0 | DQ59: 43640 | DR59: 28 | DS59: 0 | DT59: 2025-01-01 | DU59: 2025-12-31 | DV59: 2025-01-10 | DW59: 2025-02-10
A60: MSD Asia202502 | B60: MERCK SHARP & DOHME (ASIA) LIMITED | C60: MSD Asia | D60: 51487891 | E60: =VLOOKUP(D60,#REF!,1,0) -> #REF! | F60: Lau | G60: Cheuk Ying, Valica | H60: =G60&" "&F60 -> Cheuk Ying, Valica Lau | I60: =VLOOKUP(D60,#REF!,9,0) -> #REF! | J60: =I60=H60 -> #REF! | K60: Valica | L60: Active | M60: 2024-06-17 | N60: =VLOOKUP(D60,#REF!,80,0) -> #REF! | O60: =N60-M60 -> #REF! | P60: MRL HKG GCTO | Q60: =VLOOKUP(D60,#REF!,50,0) -> #REF! | R60: =Q60=P60 -> #REF! | S60: CTC | T60: =VLOOKUP(D60,#REF!,21,0) -> #REF! | U60: =T60=S60 -> #REF! | V60: 12630167 | W60: =VLOOKUP(D60,#REF!,51,0) -> #REF! | X60: =W60=V60 -> #REF! | Y60: 202502 | Z60: N | AA60: 0.7 | AB60: 29000 | AC60: =ROUND(VLOOKUP(D60,#REF!,59,0),0) -> #REF! | AD60: =AC60-AB60 -> #REF! | AE60: 29000 | AF60: =AB60 -> 29000 | AG60: =AF60-AE60 -> 0 | AH60: 0 | AK60: 0 | AN60: 0 | AO60: 0 | AP60: =IFERROR(VLOOKUP('Feb for check'!D60,#REF!,15,0),0) -> 0 | AQ60: =AP60-AO60 -> 0 | AR60: 0 | AS60: =AO60 -> 0 | AT60: =AS60-AR60 -> 0 | AU60: 0 | AW60: 0 | AY60: 0 | BA60: 0 | BB60: =IFERROR(VLOOKUP(D60,#REF!,2,0),0) -> 0 | BC60: =MAX(VLOOKUP(D60,#REF!,13,0)-VLOOKUP(D60,#REF!,14,0),0) -> #REF! | BD60: =IFERROR(VLOOKUP(D60,#REF!,3,0),0) -> 0 | BE60: =MAX(VLOOKUP(D60,#REF!,22,0)-VLOOKUP(D60,#REF!,23,0),0) -> #REF! | BF60: =BB60*BC60+BD60*BE60 -> #REF! | BG60: =BF60-BA60 -> #REF! | BH60: 0 | BK60: 459 | BL60: =ROUNDUP(DI60/(1-0.17)*0.17,0) -> 459 | BM60: =BL60-BK60 -> 0 | BN60: 0 | BR60: 0 | BT60: 0 | BV60: 0 | BX60: 29459 | BY60: =SUM(AE60,AH60,AN60,AR60,AU60,AY60,BA60,BH60,BK60,BN60,BR60,BT60) -> 29459 | BZ60: =BY60-BX60 -> 0 | CA60: 29000 | CB60: =SUM(AE60,AH60,BA60,BH60) -> 29000 | CC60: =CB60-CA60 -> 0 | CD60: 0 | CG60: 0 | CI60: 953.4246 | CJ60: 0 | CL60: 0 | CM60: 0.075 | CN60: 0 | CO60: 0 | CP60: 0 | CR60: 0 | CT60: 1472.95 | CU60: =MIN(BX60*5%,1500) -> 1472.95 | CV60: =CU60-CT60 -> 0 | CW60: 0 | CX60: =ROUND(CA60*CJ60,2) -> 0 | CY60: =CX60-CW60 -> 0 | CZ60: 1472.95 | DA60: =MIN(BX60*5%,1500) -> 1472.95 | DB60: =DA60-CZ60 -> 0 | DC60: 702.05 | DD60: =MAX(ROUND(CA60*CM60-CZ60,2),0) -> 702.05 | DE60: =DD60-DC60 -> 0 | DF60: 27986.05 | DG60: =SUM(AE60,AH60,AN60,AR60,AU60,AY60,BA60,BH60,BK60,BN60,BR60,BT60,BV60,-CG60,-CP60,-CT60,-CW60) -> 27986.05 | DH60: =DG60-DF60 -> 0 | DI60: 2237.92 | DJ60: =IFERROR(VLOOKUP(D60,#REF!,2,0),0) -> 0 | DK60: =DJ60-DI60 -> -2237.92 | DL60: 29459 | DM60: 262684.41 | DN60: 2416.67 | DO60: 0 | DP60: 0 | DQ60: 29000 | DR60: 28 | DS60: 0 | DT60: 2025-01-01 | DU60: 2025-12-31 | DV60: 2025-01-10 | DW60: 2025-02-10
A61: MSD Asia202502 | B61: MERCK SHARP & DOHME (ASIA) LIMITED | C61: MSD Asia | D61: 51122544 | E61: =VLOOKUP(D61,#REF!,1,0) -> #REF! | F61: Mok | G61: Chun Wai | H61: =G61&" "&F61 -> Chun Wai Mok | I61: =VLOOKUP(D61,#REF!,9,0) -> #REF! | J61: =I61=H61 -> #REF! | K61: Ivan | L61: Active | M61: 2012-04-10 | N61: =VLOOKUP(D61,#REF!,80,0) -> #REF! | O61: =N61-M61 -> #REF! | P61: HK Specialty Care (DS) | Q61: =VLOOKUP(D61,#REF!,50,0) -> #REF! | R61: =Q61=P61 -> #REF! | S61: Assistant Manager | T61: =VLOOKUP(D61,#REF!,21,0) -> #REF! | U61: =T61=S61 -> #REF! | V61: 12630116 | W61: =VLOOKUP(D61,#REF!,51,0) -> #REF! | X61: =W61=V61 -> #REF! | Y61: 202502 | Z61: N | AA61: 12.89 | AB61: 49312 | AC61: =ROUND(VLOOKUP(D61,#REF!,59,0),0) -> #REF! | AD61: =AC61-AB61 -> #REF! | AE61: 49312 | AF61: =AB61 -> 49312 | AG61: =AF61-AE61 -> 0 | AH61: 0 | AK61: 0 | AN61: 0 | AO61: 2500 | AP61: =IFERROR(VLOOKUP('Feb for check'!D61,#REF!,15,0),0) -> 0 | AQ61: =AP61-AO61 -> -2500 | AR61: 2500 | AS61: =AO61 -> 2500 | AT61: =AS61-AR61 -> 0 | AU61: 0 | AW61: 0 | AY61: 0 | BA61: 0 | BB61: =IFERROR(VLOOKUP(D61,#REF!,2,0),0) -> 0 | BC61: =MAX(VLOOKUP(D61,#REF!,13,0)-VLOOKUP(D61,#REF!,14,0),0) -> #REF! | BD61: =IFERROR(VLOOKUP(D61,#REF!,3,0),0) -> 0 | BE61: =MAX(VLOOKUP(D61,#REF!,22,0)-VLOOKUP(D61,#REF!,23,0),0) -> #REF! | BF61: =BB61*BC61+BD61*BE61 -> #REF! | BG61: =BF61-BA61 -> #REF! | BH61: 0 | BK61: 0 | BL61: =ROUNDUP(DI61/(1-0.17)*0.17,0) -> 0 | BM61: =BL61-BK61 -> 0 | BN61: 0 | BR61: 0 | BT61: 0 | BV61: 0 | BX61: 51812 | BY61: =SUM(AE61,AH61,AN61,AR61,AU61,AY61,BA61,BH61,BK61,BN61,BR61,BT61) -> 51812 | BZ61: =BY61-BX61 -> 0 | CA61: 49312 | CB61: =SUM(AE61,AH61,BA61,BH61) -> 49312 | CC61: =CB61-CA61 -> 0 | CD61: 0 | CG61: 0 | CI61: 1703.4082 | CJ61: 0.05 | CL61: 0 | CM61: 0.1 | CN61: 0 | CO61: 0 | CP61: 0 | CR61: 0 | CT61: 1500 | CU61: =MIN(BX61*5%,1500) -> 1500 | CV61: =CU61-CT61 -> 0 | CW61: 2465.6 | CX61: =ROUND(CA61*CJ61,2) -> 2465.6 | CY61: =CX61-CW61 -> 0 | CZ61: 1500 | DA61: =MIN(BX61*5%,1500) -> 1500 | DB61: =DA61-CZ61 -> 0 | DC61: 3431.2 | DD61: =MAX(ROUND(CA61*CM61-CZ61,2),0) -> 3431.2 | DE61: =DD61-DC61 -> 0 | DF61: 47846.4 | DG61: =SUM(AE61,AH61,AN61,AR61,AU61,AY61,BA61,BH61,BK61,BN61,BR61,BT61,BV61,-CG61,-CP61,-CT61,-CW61) -> 47846.4 | DH61: =DG61-DF61 -> 0 | DI61: 0 | DJ61: =IFERROR(VLOOKUP(D61,#REF!,2,0),0) -> 0 | DK61: =DJ61-DI61 -> 0 | DL61: 49312 | DM61: 806909.32 | DN61: 4109.33 | DO61: 0 | DP61: 0 | DQ61: 51812 | DR61: 28 | DS61: 0 | DT61: 2025-01-01 | DU61: 2025-12-31 | DV61: 2025-01-10 | DW61: 2025-02-10
A62: MSD Asia202502 | B62: MERCK SHARP & DOHME (ASIA) LIMITED | C62: MSD Asia | D62: 51459612 | E62: =VLOOKUP(D62,#REF!,1,0) -> #REF! | F62: Mak | G62: Tsun Ho | H62: =G62&" "&F62 -> Tsun Ho Mak | I62: =VLOOKUP(D62,#REF!,9,0) -> #REF! | J62: =I62=H62 -> #REF! | K62: Max | L62: Active | M62: 2023-04-04 | N62: =VLOOKUP(D62,#REF!,80,0) -> #REF! | O62: =N62-M62 -> #REF! | P62: HK Vaccine (DS) | Q62: =VLOOKUP(D62,#REF!,50,0) -> #REF! | R62: =Q62=P62 -> #REF! | S62: Professional Sales Representative | T62: =VLOOKUP(D62,#REF!,21,0) -> #REF! | U62: =T62=S62 -> #REF! | V62: 12630115 | W62: =VLOOKUP(D62,#REF!,51,0) -> #REF! | X62: =W62=V62 -> #REF! | Y62: 202502 | Z62: N | AA62: 1.91 | AB62: 25032 | AC62: =ROUND(VLOOKUP(D62,#REF!,59,0),0) -> #REF! | AD62: =AC62-AB62 -> #REF! | AE62: 25032 | AF62: =AB62 -> 25032 | AG62: =AF62-AE62 -> 0 | AH62: 0 | AK62: 0 | AN62: 0 | AO62: 2500 | AP62: =IFERROR(VLOOKUP('Feb for check'!D62,#REF!,15,0),0) -> 0 | AQ62: =AP62-AO62 -> -2500 | AR62: 2500 | AS62: =AO62 -> 2500 | AT62: =AS62-AR62 -> 0 | AU62: 0 | AW62: 0 | AY62: 0 | BA62: 0 | BB62: =IFERROR(VLOOKUP(D62,#REF!,2,0),0) -> 0 | BC62: =MAX(VLOOKUP(D62,#REF!,13,0)-VLOOKUP(D62,#REF!,14,0),0) -> #REF! | BD62: =IFERROR(VLOOKUP(D62,#REF!,3,0),0) -> 0 | BE62: =MAX(VLOOKUP(D62,#REF!,22,0)-VLOOKUP(D62,#REF!,23,0),0) -> #REF! | BF62: =BB62*BC62+BD62*BE62 -> #REF! | BG62: =BF62-BA62 -> #REF! | BH62: 0 | BK62: 0 | BL62: =ROUNDUP(DI62/(1-0.17)*0.17,0) -> 0 | BM62: =BL62-BK62 -> 0 | BN62: 0 | BR62: 0 | BT62: 0 | BV62: 0 | BX62: 27532 | BY62: =SUM(AE62,AH62,AN62,AR62,AU62,AY62,BA62,BH62,BK62,BN62,BR62,BT62) -> 27532 | BZ62: =BY62-BX62 -> 0 | CA62: 25032 | CB62: =SUM(AE62,AH62,BA62,BH62) -> 25032 | CC62: =CB62-CA62 -> 0 | CD62: 0 | CG62: 0 | CI62: 905.1616 | CJ62: 0 | CL62: 0 | CM62: 0.075 | CN62: 0 | CO62: 0 | CP62: 0 | CR62: 0 | CT62: 1376.6 | CU62: =MIN(BX62*5%,1500) -> 1376.6 | CV62: =CU62-CT62 -> 0 | CW62: 0 | CX62: =ROUND(CA62*CJ62,2) -> 0 | CY62: =CX62-CW62 -> 0 | CZ62: 1376.6 | DA62: =MIN(BX62*5%,1500) -> 1376.6 | DB62: =DA62-CZ62 -> 0 | DC62: 500.8 | DD62: =MAX(ROUND(CA62*CM62-CZ62,2),0) -> 500.8 | DE62: =DD62-DC62 -> 0 | DF62: 26155.4 | DG62: =SUM(AE62,AH62,AN62,AR62,AU62,AY62,BA62,BH62,BK62,BN62,BR62,BT62,BV62,-CG62,-CP62,-CT62,-CW62) -> 26155.4 | DH62: =DG62-DF62 -> 0 | DI62: 0 | DJ62: =IFERROR(VLOOKUP(D62,#REF!,2,0),0) -> 0 | DK62: =DJ62-DI62 -> 0 | DL62: 25032 | DM62: 461132.73 | DN62: 2086 | DO62: 0 | DP62: 0 | DQ62: 27532 | DR62: 28 | DS62: 0 | DT62: 2025-01-01 | DU62: 2025-12-31 | DV62: 2025-01-10 | DW62: 2025-02-10
A63: MSD Asia202502 | B63: MERCK SHARP & DOHME (ASIA) LIMITED | C63: MSD Asia | D63: 51232018 | E63: =VLOOKUP(D63,#REF!,1,0) -> #REF! | F63: Wong | G63: Pui Kit | H63: =G63&" "&F63 -> Pui Kit Wong | I63: =VLOOKUP(D63,#REF!,9,0) -> #REF! | J63: =I63=H63 -> #REF! | K63: Kit | L63: Active | M63: 2018-01-01 | N63: =VLOOKUP(D63,#REF!,80,0) -> #REF! | O63: =N63-M63 -> #REF! | P63: HK Comm Oper (SA) | Q63: =VLOOKUP(D63,#REF!,50,0) -> #REF! | R63: =Q63=P63 -> #REF! | S63: Associate Analyst | T63: =VLOOKUP(D63,#REF!,21,0) -> #REF! | U63: =T63=S63 -> #REF! | V63: 12630222 | W63: =VLOOKUP(D63,#REF!,51,0) -> #REF! | X63: =W63=V63 -> #REF! | Y63: 202502 | Z63: N | AA63: 7.16 | AB63: 33336 | AC63: =ROUND(VLOOKUP(D63,#REF!,59,0),0) -> #REF! | AD63: =AC63-AB63 -> #REF! | AE63: 33336 | AF63: =AB63 -> 33336 | AG63: =AF63-AE63 -> 0 | AH63: 0 | AK63: 0 | AN63: 0 | AO63: 0 | AP63: =IFERROR(VLOOKUP('Feb for check'!D63,#REF!,15,0),0) -> 0 | AQ63: =AP63-AO63 -> 0 | AR63: 0 | AS63: =AO63 -> 0 | AT63: =AS63-AR63 -> 0 | AU63: 0 | AW63: 0 | AY63: 0 | BA63: 0 | BB63: =IFERROR(VLOOKUP(D63,#REF!,2,0),0) -> 0 | BC63: =MAX(VLOOKUP(D63,#REF!,13,0)-VLOOKUP(D63,#REF!,14,0),0) -> #REF! | BD63: =IFERROR(VLOOKUP(D63,#REF!,3,0),0) -> 0 | BE63: =MAX(VLOOKUP(D63,#REF!,22,0)-VLOOKUP(D63,#REF!,23,0),0) -> #REF! | BF63: =BB63*BC63+BD63*BE63 -> #REF! | BG63: =BF63-BA63 -> #REF! | BH63: 0 | BK63: 0 | BL63: =ROUNDUP(DI63/(1-0.17)*0.17,0) -> 0 | BM63: =BL63-BK63 -> 0 | BN63: 0 | BR63: 0 | BT63: 0 | BV63: 0 | BX63: 33336 | BY63: =SUM(AE63,AH63,AN63,AR63,AU63,AY63,BA63,BH63,BK63,BN63,BR63,BT63) -> 33336 | BZ63: =BY63-BX63 -> 0 | CA63: 33336 | CB63: =SUM(AE63,AH63,BA63,BH63) -> 33336 | CC63: =CB63-CA63 -> 0 | CD63: 0 | CG63: 0 | CI63: 1095.978 | CJ63: 0.05 | CL63: 0 | CM63: 0.1 | CN63: 0 | CO63: 0 | CP63: 0 | CR63: 0 | CT63: 1500 | CU63: =MIN(BX63*5%,1500) -> 1500 | CV63: =CU63-CT63 -> 0 | CW63: 1666.8 | CX63: =ROUND(CA63*CJ63,2) -> 1666.8 | CY63: =CX63-CW63 -> 0 | CZ63: 1500 | DA63: =MIN(BX63*5%,1500) -> 1500 | DB63: =DA63-CZ63 -> 0 | DC63: 1833.6 | DD63: =MAX(ROUND(CA63*CM63-CZ63,2),0) -> 1833.6 | DE63: =DD63-DC63 -> 0 | DF63: 30169.2 | DG63: =SUM(AE63,AH63,AN63,AR63,AU63,AY63,BA63,BH63,BK63,BN63,BR63,BT63,BV63,-CG63,-CP63,-CT63,-CW63) -> 30169.2 | DH63: =DG63-DF63 -> 0 | DI63: 0 | DJ63: =IFERROR(VLOOKUP(D63,#REF!,2,0),0) -> 0 | DK63: =DJ63-DI63 -> 0 | DL63: 33336 | DM63: 524761.84 | DN63: 2778 | DO63: 0 | DP63: 0 | DQ63: 33336 | DR63: 28 | DS63: 0 | DT63: 2025-01-01 | DU63: 2025-12-31 | DV63: 2025-01-10 | DW63: 2025-02-10
A64: MSD Asia202502 | B64: MERCK SHARP & DOHME (ASIA) LIMITED | C64: MSD Asia | D64: 51473614 | E64: =VLOOKUP(D64,#REF!,1,0) -> #REF! | F64: Cheung | G64: Wai Fong | H64: =G64&" "&F64 -> Wai Fong Cheung | I64: =VLOOKUP(D64,#REF!,9,0) -> #REF! | J64: =I64=H64 -> #REF! | K64: Pam | L64: Active | M64: 2023-09-26 | N64: =VLOOKUP(D64,#REF!,80,0) -> #REF! | O64: =N64-M64 -> #REF! | P64: HK Comm Oper (SA) | Q64: =VLOOKUP(D64,#REF!,50,0) -> #REF! | R64: =Q64=P64 -> #REF! | S64: Senior Business Practices Officer | T64: =VLOOKUP(D64,#REF!,21,0) -> #REF! | U64: =T64=S64 -> #REF! | V64: 12630222 | W64: =VLOOKUP(D64,#REF!,51,0) -> #REF! | X64: =W64=V64 -> #REF! | Y64: 202502 | Z64: N | AA64: 1.43 | AB64: 51900 | AC64: =ROUND(VLOOKUP(D64,#REF!,59,0),0) -> #REF! | AD64: =AC64-AB64 -> #REF! | AE64: 51900 | AF64: =AB64 -> 51900 | AG64: =AF64-AE64 -> 0 | AH64: 0 | AK64: 0 | AN64: 0 | AO64: 0 | AP64: =IFERROR(VLOOKUP('Feb for check'!D64,#REF!,15,0),0) -> 0 | AQ64: =AP64-AO64 -> 0 | AR64: 0 | AS64: =AO64 -> 0 | AT64: =AS64-AR64 -> 0 | AU64: 0 | AW64: 0 | AY64: 0 | BA64: 301.82 | BB64: =IFERROR(VLOOKUP(D64,#REF!,2,0),0) -> 0 | BC64: =MAX(VLOOKUP(D64,#REF!,13,0)-VLOOKUP(D64,#REF!,14,0),0) -> #REF! | BD64: =IFERROR(VLOOKUP(D64,#REF!,3,0),0) -> 0 | BE64: =MAX(VLOOKUP(D64,#REF!,22,0)-VLOOKUP(D64,#REF!,23,0),0) -> #REF! | BF64: =BB64*BC64+BD64*BE64 -> #REF! | BG64: =BF64-BA64 -> #REF! | BH64: 0 | BK64: 110 | BL64: =ROUNDUP(DI64/(1-0.17)*0.17,0) -> 110 | BM64: =BL64-BK64 -> 0 | BN64: 0 | BR64: 0 | BT64: 0 | BV64: 0 | BX64: 52311.82 | BY64: =SUM(AE64,AH64,AN64,AR64,AU64,AY64,BA64,BH64,BK64,BN64,BR64,BT64) -> 52311.82 | BZ64: =BY64-BX64 -> 0 | CA64: 52201.82 | CB64: =SUM(AE64,AH64,BA64,BH64) -> 52201.82 | CC64: =CB64-CA64 -> 0 | CD64: 0 | CG64: 0 | CI64: 1706.3013 | CJ64: 0 | CL64: 0 | CM64: 0.075 | CN64: 0 | CO64: 0 | CP64: 0 | CR64: 0 | CT64: 1500 | CU64: =MIN(BX64*5%,1500) -> 1500 | CV64: =CU64-CT64 -> 0 | CW64: 0 | CX64: =ROUND(CA64*CJ64,2) -> 0 | CY64: =CX64-CW64 -> 0 | CZ64: 1500 | DA64: =MIN(BX64*5%,1500) -> 1500 | DB64: =DA64-CZ64 -> 0 | DC64: 2415.14 | DD64: =MAX(ROUND(CA64*CM64-CZ64,2),0) -> 2415.14 | DE64: =DD64-DC64 -> 0 | DF64: 50811.82 | DG64: =SUM(AE64,AH64,AN64,AR64,AU64,AY64,BA64,BH64,BK64,BN64,BR64,BT64,BV64,-CG64,-CP64,-CT64,-CW64) -> 50811.82 | DH64: =DG64-DF64 -> 0 | DI64: 536.21 | DJ64: =IFERROR(VLOOKUP(D64,#REF!,2,0),0) -> 0 | DK64: =DJ64-DI64 -> -536.21 | DL64: 52311.82 | DM64: 726344.75 | DN64: 4325 | DO64: 301.82 | DP64: 0 | DQ64: 52201.82 | DR64: 28 | DS64: 0 | DT64: 2025-01-01 | DU64: 2025-12-31 | DV64: 2025-01-10 | DW64: 2025-02-10
A65: MSD Asia202502 | B65: MERCK SHARP & DOHME (ASIA) LIMITED | C65: MSD Asia | D65: 39490005 | E65: =VLOOKUP(D65,#REF!,1,0) -> #REF! | F65: Ng | G65: Kam Fong | H65: =G65&" "&F65 -> Kam Fong Ng | I65: =VLOOKUP(D65,#REF!,9,0) -> #REF! | J65: =I65=H65 -> #REF! | K65: Mabel | L65: Active | M65: 2008-05-05 | N65: =VLOOKUP(D65,#REF!,80,0) -> #REF! | O65: =N65-M65 -> #REF! | P65: Finance - HK | Q65: =VLOOKUP(D65,#REF!,50,0) -> #REF! | R65: =Q65=P65 -> #REF! | S65: Accountant | T65: =VLOOKUP(D65,#REF!,21,0) -> #REF! | U65: =T65=S65 -> #REF! | V65: 12630016 | W65: =VLOOKUP(D65,#REF!,51,0) -> #REF! | X65: =W65=V65 -> #REF! | Y65: 202502 | Z65: N | AA65: 16.82 | AB65: 46312 | AC65: =ROUND(VLOOKUP(D65,#REF!,59,0),0) -> #REF! | AD65: =AC65-AB65 -> #REF! | AE65: 46312 | AF65: =AB65 -> 46312 | AG65: =AF65-AE65 -> 0 | AH65: 0 | AK65: 0 | AN65: 0 | AO65: 0 | AP65: =IFERROR(VLOOKUP('Feb for check'!D65,#REF!,15,0),0) -> 0 | AQ65: =AP65-AO65 -> 0 | AR65: 0 | AS65: =AO65 -> 0 | AT65: =AS65-AR65 -> 0 | AU65: 0 | AW65: 0 | AY65: 0 | BA65: 422.25 | BB65: =IFERROR(VLOOKUP(D65,#REF!,2,0),0) -> 0 | BC65: =MAX(VLOOKUP(D65,#REF!,13,0)-VLOOKUP(D65,#REF!,14,0),0) -> #REF! | BD65: =IFERROR(VLOOKUP(D65,#REF!,3,0),0) -> 0 | BE65: =MAX(VLOOKUP(D65,#REF!,22,0)-VLOOKUP(D65,#REF!,23,0),0) -> #REF! | BF65: =BB65*BC65+BD65*BE65 -> #REF! | BG65: =BF65-BA65 -> #REF! | BH65: 0 | BK65: 459 | BL65: =ROUNDUP(DI65/(1-0.17)*0.17,0) -> 459 | BM65: =BL65-BK65 -> 0 | BN65: 0 | BR65: 0 | BT65: 0 | BV65: 0 | BX65: 47193.25 | BY65: =SUM(AE65,AH65,AN65,AR65,AU65,AY65,BA65,BH65,BK65,BN65,BR65,BT65) -> 47193.25 | BZ65: =BY65-BX65 -> 0 | CA65: 46734.25 | CB65: =SUM(AE65,AH65,BA65,BH65) -> 46734.25 | CC65: =CB65-CA65 -> 0 | CD65: 0 | CG65: 0 | CI65: 1522.5863 | CJ65: 0.05 | CL65: 0 | CM65: 0.1 | CN65: 0 | CO65: 0 | CP65: 0 | CR65: 0 | CT65: 1500 | CU65: =MIN(BX65*5%,1500) -> 1500 | CV65: =CU65-CT65 -> 0 | CW65: 2336.71 | CX65: =ROUND(CA65*CJ65,2) -> 2336.71 | CY65: =CX65-CW65 -> 0 | CZ65: 1500 | DA65: =MIN(BX65*5%,1500) -> 1500 | DB65: =DA65-CZ65 -> 0 | DC65: 3173.43 | DD65: =MAX(ROUND(CA65*CM65-CZ65,2),0) -> 3173.43 | DE65: =DD65-DC65 -> 0 | DF65: 43356.54 | DG65: =SUM(AE65,AH65,AN65,AR65,AU65,AY65,BA65,BH65,BK65,BN65,BR65,BT65,BV65,-CG65,-CP65,-CT65,-CW65) -> 43356.54 | DH65: =DG65-DF65 -> 0 | DI65: 2237.92 | DJ65: =IFERROR(VLOOKUP(D65,#REF!,2,0),0) -> 0 | DK65: =DJ65-DI65 -> -2237.92 | DL65: 47193.25 | DM65: 754284.97 | DN65: 3859.33 | DO65: 422.25 | DP65: 0 | DQ65: 46734.25 | DR65: 28 | DS65: 0 | DT65: 2025-01-01 | DU65: 2025-12-31 | DV65: 2025-01-10 | DW65: 2025-02-10
A66: MSD Asia202502 | B66: MERCK SHARP & DOHME (ASIA) LIMITED | C66: MSD Asia | D66: 51223532 | E66: =VLOOKUP(D66,#REF!,1,0) -> #REF! | F66: Cheng | G66: Wai Ki | H66: =G66&" "&F66 -> Wai Ki Cheng | I66: =VLOOKUP(D66,#REF!,9,0) -> #REF! | J66: =I66=H66 -> #REF! | K66: Helen | L66: Active | M66: 2015-05-18 | N66: =VLOOKUP(D66,#REF!,80,0) -> #REF! | O66: =N66-M66 -> #REF! | P66: MRL HKG GMVC | Q66: =VLOOKUP(D66,#REF!,50,0) -> #REF! | R66: =Q66=P66 -> #REF! | S66: Assoc Dir, V&I GMVC, AP HUB, GEMS | T66: =VLOOKUP(D66,#REF!,21,0) -> #REF! | U66: =T66=S66 -> #REF! | V66: 12630364 | W66: =VLOOKUP(D66,#REF!,51,0) -> #REF! | X66: =W66=V66 -> #REF! | Y66: 202502 | Z66: N | AA66: 9.79 | AB66: 53364 | AC66: =ROUND(VLOOKUP(D66,#REF!,59,0),0) -> #REF! | AD66: =AC66-AB66 -> #REF! | AE66: 53364 | AF66: =AB66 -> 53364 | AG66: =AF66-AE66 -> 0 | AH66: 0 | AK66: 0 | AN66: 0 | AO66: 0 | AP66: =IFERROR(VLOOKUP('Feb for check'!D66,#REF!,15,0),0) -> 0 | AQ66: =AP66-AO66 -> 0 | AR66: 0 | AS66: =AO66 -> 0 | AT66: =AS66-AR66 -> 0 | AU66: 0 | AW66: 0 | AY66: 0 | BA66: 1673.52 | BB66: =IFERROR(VLOOKUP(D66,#REF!,2,0),0) -> 0 | BC66: =MAX(VLOOKUP(D66,#REF!,13,0)-VLOOKUP(D66,#REF!,14,0),0) -> #REF! | BD66: =IFERROR(VLOOKUP(D66,#REF!,3,0),0) -> 0 | BE66: =MAX(VLOOKUP(D66,#REF!,22,0)-VLOOKUP(D66,#REF!,23,0),0) -> #REF! | BF66: =BB66*BC66+BD66*BE66 -> #REF! | BG66: =BF66-BA66 -> #REF! | BH66: 0 | BK66: 0 | BL66: =ROUNDUP(DI66/(1-0.17)*0.17,0) -> 0 | BM66: =BL66-BK66 -> 0 | BN66: 0 | BR66: 0 | BT66: 0 | BV66: 0 | BX66: 55037.52 | BY66: =SUM(AE66,AH66,AN66,AR66,AU66,AY66,BA66,BH66,BK66,BN66,BR66,BT66) -> 55037.52 | BZ66: =BY66-BX66 -> 0 | CA66: 55037.52 | CB66: =SUM(AE66,AH66,BA66,BH66) -> 55037.52 | CC66: =CB66-CA66 -> 0 | CD66: 0 | CG66: 0 | CI66: 1754.4328 | CJ66: 0 | CL66: 0 | CM66: 0.075 | CN66: 0 | CO66: 0 | CP66: 0 | CR66: 0 | CT66: 1500 | CU66: =MIN(BX66*5%,1500) -> 1500 | CV66: =CU66-CT66 -> 0 | CW66: 0 | CX66: =ROUND(CA66*CJ66,2) -> 0 | CY66: =CX66-CW66 -> 0 | CZ66: 1500 | DA66: =MIN(BX66*5%,1500) -> 1500 | DB66: =DA66-CZ66 -> 0 | DC66: 2627.81 | DD66: =MAX(ROUND(CA66*CM66-CZ66,2),0) -> 2627.81 | DE66: =DD66-DC66 -> 0 | DF66: 53537.52 | DG66: =SUM(AE66,AH66,AN66,AR66,AU66,AY66,BA66,BH66,BK66,BN66,BR66,BT66,BV66,-CG66,-CP66,-CT66,-CW66) -> 53537.52 | DH66: =DG66-DF66 -> 0 | DI66: 0 | DJ66: =IFERROR(VLOOKUP(D66,#REF!,2,0),0) -> 0 | DK66: =DJ66-DI66 -> 0 | DL66: 55037.52 | DM66: 895208.47 | DN66: 4447 | DO66: 1673.52 | DP66: 0 | DQ66: 55037.52 | DR66: 28 | DS66: 0 | DT66: 2025-01-01 | DU66: 2025-12-31 | DV66: 2025-01-10 | DW66: 2025-02-10
A67: MSD Asia202502 | B67: MERCK SHARP & DOHME (ASIA) LIMITED | C67: MSD Asia | D67: 51425313 | E67: =VLOOKUP(D67,#REF!,1,0) -> #REF! | F67: Cheng | G67: Wing Sze | H67: =G67&" "&F67 -> Wing Sze Cheng | I67: =VLOOKUP(D67,#REF!,9,0) -> #REF! | J67: =I67=H67 -> #REF! | K67: Celia | L67: Active | M67: 2022-03-07 | N67: =VLOOKUP(D67,#REF!,80,0) -> #REF! | O67: =N67-M67 -> #REF! | P67: HK Direct Selling - Oncology | Q67: =VLOOKUP(D67,#REF!,50,0) -> #REF! | R67: =Q67=P67 -> #REF! | S67: Senior Key Account Manager | T67: =VLOOKUP(D67,#REF!,21,0) -> #REF! | U67: =T67=S67 -> #REF! | V67: 12630118 | W67: =VLOOKUP(D67,#REF!,51,0) -> #REF! | X67: =W67=V67 -> #REF! | Y67: 202502 | Z67: N | AA67: 2.98 | AB67: 52566 | AC67: =ROUND(VLOOKUP(D67,#REF!,59,0),0) -> #REF! | AD67: =AC67-AB67 -> #REF! | AE67: 52566 | AF67: =AB67 -> 52566 | AG67: =AF67-AE67 -> 0 | AH67: 0 | AK67: 0 | AN67: 0 | AO67: 2500 | AP67: =IFERROR(VLOOKUP('Feb for check'!D67,#REF!,15,0),0) -> 0 | AQ67: =AP67-AO67 -> -2500 | AR67: 2500 | AS67: =AO67 -> 2500 | AT67: =AS67-AR67 -> 0 | AU67: 0 | AW67: 0 | AY67: 0 | BA67: 1031.26 | BB67: =IFERROR(VLOOKUP(D67,#REF!,2,0),0) -> 0 | BC67: =MAX(VLOOKUP(D67,#REF!,13,0)-VLOOKUP(D67,#REF!,14,0),0) -> #REF! | BD67: =IFERROR(VLOOKUP(D67,#REF!,3,0),0) -> 0 | BE67: =MAX(VLOOKUP(D67,#REF!,22,0)-VLOOKUP(D67,#REF!,23,0),0) -> #REF! | BF67: =BB67*BC67+BD67*BE67 -> #REF! | BG67: =BF67-BA67 -> #REF! | BH67: 0 | BK67: 55 | BL67: =ROUNDUP(DI67/(1-0.17)*0.17,0) -> 55 | BM67: =BL67-BK67 -> 0 | BN67: 0 | BR67: 0 | BT67: 0 | BV67: 0 | BX67: 56152.26 | BY67: =SUM(AE67,AH67,AN67,AR67,AU67,AY67,BA67,BH67,BK67,BN67,BR67,BT67) -> 56152.26 | BZ67: =BY67-BX67 -> 0 | CA67: 53597.26 | CB67: =SUM(AE67,AH67,BA67,BH67) -> 53597.26 | CC67: =CB67-CA67 -> 0 | CD67: 0 | CG67: 0 | CI67: 1810.389 | CJ67: 0 | CL67: 0 | CM67: 0.075 | CN67: 0 | CO67: 0 | CP67: 0 | CR67: 0 | CT67: 1500 | CU67: =MIN(BX67*5%,1500) -> 1500 | CV67: =CU67-CT67 -> 0 | CW67: 0 | CX67: =ROUND(CA67*CJ67,2) -> 0 | CY67: =CX67-CW67 -> 0 | CZ67: 1500 | DA67: =MIN(BX67*5%,1500) -> 1500 | DB67: =DA67-CZ67 -> 0 | DC67: 2519.79 | DD67: =MAX(ROUND(CA67*CM67-CZ67,2),0) -> 2519.79 | DE67: =DD67-DC67 -> 0 | DF67: 54652.26 | DG67: =SUM(AE67,AH67,AN67,AR67,AU67,AY67,BA67,BH67,BK67,BN67,BR67,BT67,BV67,-CG67,-CP67,-CT67,-CW67) -> 54652.26 | DH67: =DG67-DF67 -> 0 | DI67: 268.1 | DJ67: =IFERROR(VLOOKUP(D67,#REF!,2,0),0) -> 0 | DK67: =DJ67-DI67 -> -268.1 | DL67: 53652.26 | DM67: 892812.82 | DN67: 4380.5 | DO67: 1031.26 | DP67: 0 | DQ67: 56097.26 | DR67: 28 | DS67: 0 | DT67: 2025-01-01 | DU67: 2025-12-31 | DV67: 2025-01-10 | DW67: 2025-02-10
A68: MSD Asia202502 | B68: MERCK SHARP & DOHME (ASIA) LIMITED | C68: MSD Asia | D68: 51419948 | E68: =VLOOKUP(D68,#REF!,1,0) -> #REF! | F68: Chau | G68: So San | H68: =G68&" "&F68 -> So San Chau | I68: =VLOOKUP(D68,#REF!,9,0) -> #REF! | J68: =I68=H68 -> #REF! | L68: Active | M68: 2022-02-07 | N68: =VLOOKUP(D68,#REF!,80,0) -> #REF! | O68: =N68-M68 -> #REF! | P68: HK ONCOLOGY ALLIANCE (MA) | Q68: =VLOOKUP(D68,#REF!,50,0) -> #REF! | R68: =Q68=P68 -> #REF! | S68: Associate Product Manager | T68: =VLOOKUP(D68,#REF!,21,0) -> #REF! | U68: =T68=S68 -> #REF! | V68: 12630101 | W68: =VLOOKUP(D68,#REF!,51,0) -> #REF! | X68: =W68=V68 -> #REF! | Y68: 202502 | Z68: N | AA68: 3.06 | AB68: 53163 | AC68: =ROUND(VLOOKUP(D68,#REF!,59,0),0) -> #REF! | AD68: =AC68-AB68 -> #REF! | AE68: 53163 | AF68: =AB68 -> 53163 | AG68: =AF68-AE68 -> 0 | AH68: 0 | AK68: 0 | AN68: 0 | AO68: 0 | AP68: =IFERROR(VLOOKUP('Feb for check'!D68,#REF!,15,0),0) -> 0 | AQ68: =AP68-AO68 -> 0 | AR68: 0 | AS68: =AO68 -> 0 | AT68: =AS68-AR68 -> 0 | AU68: 0 | AW68: 0 | AY68: 0 | BA68: 0 | BB68: =IFERROR(VLOOKUP(D68,#REF!,2,0),0) -> 0 | BC68: =MAX(VLOOKUP(D68,#REF!,13,0)-VLOOKUP(D68,#REF!,14,0),0) -> #REF! | BD68: =IFERROR(VLOOKUP(D68,#REF!,3,0),0) -> 0 | BE68: =MAX(VLOOKUP(D68,#REF!,22,0)-VLOOKUP(D68,#REF!,23,0),0) -> #REF! | BF68: =BB68*BC68+BD68*BE68 -> #REF! | BG68: =BF68-BA68 -> #REF! | BH68: 0 | BK68: 917 | BL68: =ROUNDUP(DI68/(1-0.17)*0.17,0) -> 917 | BM68: =BL68-BK68 -> 0 | BN68: 0 | BR68: 0 | BT68: 0 | BV68: 0 | BX68: 54080 | BY68: =SUM(AE68,AH68,AN68,AR68,AU68,AY68,BA68,BH68,BK68,BN68,BR68,BT68) -> 54080 | BZ68: =BY68-BX68 -> 0 | CA68: 53163 | CB68: =SUM(AE68,AH68,BA68,BH68) -> 53163 | CC68: =CB68-CA68 -> 0 | CD68: 0 | CG68: 0 | CI68: 1747.8246 | CJ68: 0.05 | CL68: 0 | CM68: 0.1 | CN68: 0 | CO68: 0 | CP68: 0 | CR68: 0 | CT68: 1500 | CU68: =MIN(BX68*5%,1500) -> 1500 | CV68: =CU68-CT68 -> 0 | CW68: 2658.15 | CX68: =ROUND(CA68*CJ68,2) -> 2658.15 | CY68: =CX68-CW68 -> 0 | CZ68: 1500 | DA68: =MIN(BX68*5%,1500) -> 1500 | DB68: =DA68-CZ68 -> 0 | DC68: 3816.3 | DD68: =MAX(ROUND(CA68*CM68-CZ68,2),0) -> 3816.3 | DE68: =DD68-DC68 -> 0 | DF68: 49921.85 | DG68: =SUM(AE68,AH68,AN68,AR68,AU68,AY68,BA68,BH68,BK68,BN68,BR68,BT68,BV68,-CG68,-CP68,-CT68,-CW68) -> 49921.85 | DH68: =DG68-DF68 -> 0 | DI68: 4475.85 | DJ68: =IFERROR(VLOOKUP(D68,#REF!,2,0),0) -> 0 | DK68: =DJ68-DI68 -> -4475.85 | DL68: 54080 | DM68: 880336.26 | DN68: 4430.25 | DO68: 0 | DP68: 0 | DQ68: 53163 | DR68: 28 | DS68: 0 | DT68: 2025-01-01 | DU68: 2025-12-31 | DV68: 2025-01-10 | DW68: 2025-02-10
A69: MSD Asia202502 | B69: MERCK SHARP & DOHME (ASIA) LIMITED | C69: MSD Asia | D69: 51471969 | E69: =VLOOKUP(D69,#REF!,1,0) -> #REF! | F69: LI | G69: JIATONG | H69: =G69&" "&F69 -> JIATONG LI | I69: =VLOOKUP(D69,#REF!,9,0) -> #REF! | J69: =I69=H69 -> #REF! | K69: Mandy | L69: Active | M69: 2023-09-05 | N69: =VLOOKUP(D69,#REF!,80,0) -> #REF! | O69: =N69-M69 -> #REF! | P69: HK Macau Team (DS) | Q69: =VLOOKUP(D69,#REF!,50,0) -> #REF! | R69: =Q69=P69 -> #REF! | S69: Associate Key Account Manager | T69: =VLOOKUP(D69,#REF!,21,0) -> #REF! | U69: =T69=S69 -> #REF! | V69: 12630105 | W69: =VLOOKUP(D69,#REF!,51,0) -> #REF! | X69: =W69=V69 -> #REF! | Y69: 202502 | Z69: N | AA69: 1.48 | AB69: 35282 | AC69: =ROUND(VLOOKUP(D69,#REF!,59,0),0) -> #REF! | AD69: =AC69-AB69 -> #REF! | AE69: 35282 | AF69: =AB69 -> 35282 | AG69: =AF69-AE69 -> 0 | AH69: 0 | AK69: 0 | AN69: 0 | AO69: 2500 | AP69: =IFERROR(VLOOKUP('Feb for check'!D69,#REF!,15,0),0) -> 0 | AQ69: =AP69-AO69 -> -2500 | AR69: 2500 | AS69: =AO69 -> 2500 | AT69: =AS69-AR69 -> 0 | AU69: 0 | AW69: 0 | AY69: 0 | BA69: 0 | BB69: =IFERROR(VLOOKUP(D69,#REF!,2,0),0) -> 0 | BC69: =MAX(VLOOKUP(D69,#REF!,13,0)-VLOOKUP(D69,#REF!,14,0),0) -> #REF! | BD69: =IFERROR(VLOOKUP(D69,#REF!,3,0),0) -> 0 | BE69: =MAX(VLOOKUP(D69,#REF!,22,0)-VLOOKUP(D69,#REF!,23,0),0) -> #REF! | BF69: =BB69*BC69+BD69*BE69 -> #REF! | BG69: =BF69-BA69 -> #REF! | BH69: 0 | BK69: 0 | BL69: =ROUNDUP(DI69/(1-0.17)*0.17,0) -> 0 | BM69: =BL69-BK69 -> 0 | BN69: 0 | BR69: 8000 | BS69: =VLOOKUP(D69,#REF!,28,0) -> #REF! | BT69: 0 | BV69: 0 | BX69: 45782 | BY69: =SUM(AE69,AH69,AN69,AR69,AU69,AY69,BA69,BH69,BK69,BN69,BR69,BT69) -> 45782 | BZ69: =BY69-BX69 -> 0 | CA69: 35282 | CB69: =SUM(AE69,AH69,BA69,BH69) -> 35282 | CC69: =CB69-CA69 -> 0 | CD69: 0 | CG69: 0 | CI69: 1242.1479 | CJ69: 0 | CL69: 0 | CM69: 0.075 | CN69: 0 | CO69: 0 | CP69: 0 | CR69: 0 | CT69: 1500 | CU69: =MIN(BX69*5%,1500) -> 1500 | CV69: =CU69-CT69 -> 0 | CW69: 0 | CX69: =ROUND(CA69*CJ69,2) -> 0 | CY69: =CX69-CW69 -> 0 | CZ69: 1500 | DA69: =MIN(BX69*5%,1500) -> 1500 | DB69: =DA69-CZ69 -> 0 | DC69: 1146.15 | DD69: =MAX(ROUND(CA69*CM69-CZ69,2),0) -> 1146.15 | DE69: =DD69-DC69 -> 0 | DF69: 44282 | DG69: =SUM(AE69,AH69,AN69,AR69,AU69,AY69,BA69,BH69,BK69,BN69,BR69,BT69,BV69,-CG69,-CP69,-CT69,-CW69) -> 44282 | DH69: =DG69-DF69 -> 0 | DI69: 0 | DJ69: =IFERROR(VLOOKUP(D69,#REF!,2,0),0) -> 0 | DK69: =DJ69-DI69 -> 0 | DL69: 43282 | DM69: 697521.19 | DN69: 2940.17 | DO69: 0 | DP69: 0 | DQ69: 37782 | DR69: 28 | DS69: 0 | DT69: 2025-01-01 | DU69: 2025-12-31 | DV69: 2025-01-10 | DW69: 2025-02-10
A70: MSD Asia202502 | B70: MERCK SHARP & DOHME (ASIA) LIMITED | C70: MSD Asia | D70: 10179194 | E70: =VLOOKUP(D70,#REF!,1,0) -> #REF! | F70: Tong | G70: Wai Shing | H70: =G70&" "&F70 -> Wai Shing Tong | I70: =VLOOKUP(D70,#REF!,9,0) -> #REF! | J70: =I70=H70 -> #REF! | K70: Vincent | L70: Active | M70: 2021-01-01 | N70: =VLOOKUP(D70,#REF!,80,0) -> #REF! | O70: Follow Payroll system date | P70: MANAGING DIRECTOR OFFICE – TAIWAN | Q70: =VLOOKUP(D70,#REF!,50,0) -> #REF! | R70: =Q70=P70 -> #REF! | S70: Managing Director Taiwan | T70: =VLOOKUP(D70,#REF!,21,0) -> #REF! | U70: =T70=S70 -> #REF! | V70: 12630410 | W70: =VLOOKUP(D70,#REF!,51,0) -> #REF! | X70: =W70=V70 -> #REF! | Y70: 202502 | Z70: N | AA70: 19.33 | AB70: 0 | AE70: 0 | AF70: =AB70 -> 0 | AG70: =AF70-AE70 -> 0 | AH70: 0 | AK70: 0 | AN70: 0 | AO70: 0 | AP70: =IFERROR(VLOOKUP('Feb for check'!D70,#REF!,15,0),0) -> 0 | AQ70: =AP70-AO70 -> 0 | AR70: 0 | AS70: =AO70 -> 0 | AT70: =AS70-AR70 -> 0 | AU70: 0 | AW70: 0 | AY70: 0 | BA70: 0 | BH70: 0 | BK70: 0 | BL70: =ROUNDUP(DI70/(1-0.17)*0.17,0) -> 0 | BM70: =BL70-BK70 -> 0 | BN70: 0 | BR70: 0 | BT70: 0 | BV70: 162067.16 | BW70: =#REF! -> #REF! | BX70: 238167.85 | BY70: =#REF! -> #REF! | BZ70: =BY70-BX70 -> #REF! | CA70: 215497.77 | CB70: =#REF! -> #REF! | CC70: =CB70-CA70 -> #REF! | CD70: 0 | CG70: 0 | CI70: 0 | CJ70: 0.05 | CL70: 0 | CM70: 0.1 | CN70: 0 | CO70: 0 | CP70: 0 | CR70: 0 | CT70: 1500 | CU70: =MIN(BX70*5%,1500) -> 1500 | CV70: =CU70-CT70 -> 0 | CW70: 10774.89 | CX70: =ROUND(CA70*CJ70,2) -> 10774.89 | CY70: =CX70-CW70 -> 0 | CZ70: 1500 | DA70: =MIN(BX70*5%,1500) -> 1500 | DB70: =DA70-CZ70 -> 0 | DC70: 20049.78 | DD70: =MAX(ROUND(CA70*CM70-CZ70,2),0) -> 20049.78 | DE70: =DD70-DC70 -> 0 | DF70: 149792.27 | DG70: =SUM(AE70,AH70,AN70,AR70,AU70,AY70,BA70,BH70,BK70,BN70,BR70,BT70,BV70,-CG70,-CP70,-CT70,-CW70) -> 149792.27 | DH70: =DG70-DF70 -> 0 | DI70: 0 | DJ70: =IFERROR(VLOOKUP(D70,#REF!,2,0),0) -> 0 | DK70: =DJ70-DI70 -> 0 | DL70: 0 | DM70: 0 | DN70: 0 | DO70: 0 | DP70: 0 | DQ70: 0 | DR70: 0 | DS70: 0 | DT70: 2025-01-01 | DU70: 2025-12-31 | DV70: 2025-01-10 | DW70: 2025-02-10
A71: MSD Asia202502 | B71: MERCK SHARP & DOHME (ASIA) LIMITED | C71: MSD Asia | D71: 51405878 | E71: =VLOOKUP(D71,#REF!,1,0) -> #REF! | F71: Fung | G71: Wing Yee | H71: =G71&" "&F71 -> Wing Yee Fung | I71: =VLOOKUP(D71,#REF!,9,0) -> #REF! | J71: =I71=H71 -> #REF! | K71: Stella Fung | L71: Active | M71: 2021-08-16 | N71: =VLOOKUP(D71,#REF!,80,0) -> #REF! | O71: =N71-M71 -> #REF! | P71: HK Vaccine (DS) | Q71: =VLOOKUP(D71,#REF!,50,0) -> #REF! | R71: =Q71=P71 -> #REF! | S71: Senior Sales Manager | T71: =VLOOKUP(D71,#REF!,21,0) -> #REF! | U71: =T71=S71 -> #REF! | V71: 12630115 | W71: =VLOOKUP(D71,#REF!,51,0) -> #REF! | X71: =W71=V71 -> #REF! | Y71: 202502 | Z71: N | AA71: 3.54 | AB71: 90100 | AC71: =ROUND(VLOOKUP(D71,#REF!,59,0),0) -> #REF! | AD71: =AC71-AB71 -> #REF! | AE71: 90100 | AF71: =AB71 -> 90100 | AG71: =AF71-AE71 -> 0 | AH71: 0 | AK71: 0 | AN71: 0 | AO71: 2500 | AP71: =IFERROR(VLOOKUP('Feb for check'!D71,#REF!,15,0),0) -> 0 | AQ71: =AP71-AO71 -> -2500 | AR71: 2500 | AS71: =AO71 -> 2500 | AT71: =AS71-AR71 -> 0 | AU71: 0 | AW71: 0 | AY71: 0 | BA71: 4026.9 | BB71: =IFERROR(VLOOKUP(D71,#REF!,2,0),0) -> 0 | BC71: =MAX(VLOOKUP(D71,#REF!,13,0)-VLOOKUP(D71,#REF!,14,0),0) -> #REF! | BD71: =IFERROR(VLOOKUP(D71,#REF!,3,0),0) -> 0 | BE71: =MAX(VLOOKUP(D71,#REF!,22,0)-VLOOKUP(D71,#REF!,23,0),0) -> #REF! | BF71: =BB71*BC71+BD71*BE71 -> #REF! | BG71: =BF71-BA71 -> #REF! | BH71: 0 | BK71: 0 | BL71: =ROUNDUP(DI71/(1-0.17)*0.17,0) -> 0 | BM71: =BL71-BK71 -> 0 | BN71: 0 | BR71: 0 | BT71: 0 | BV71: 0 | BX71: 96626.9 | BY71: =SUM(AE71,AH71,AN71,AR71,AU71,AY71,BA71,BH71,BK71,BN71,BR71,BT71) -> 96626.9 | BZ71: =BY71-BX71 -> 0 | CA71: 94126.9 | CB71: =SUM(AE71,AH71,BA71,BH71) -> 94126.9 | CC71: =CB71-CA71 -> 0 | CD71: 0 | CG71: 0 | CI71: 3044.3835 | CJ71: 0.03 | CL71: 0 | CM71: 0.09 | CN71: 0 | CO71: 0 | CP71: 0 | CR71: 0 | CT71: 1500 | CU71: =MIN(BX71*5%,1500) -> 1500 | CV71: =CU71-CT71 -> 0 | CW71: 2823.81 | CX71: =ROUND(CA71*CJ71,2) -> 2823.81 | CY71: =CX71-CW71 -> 0 | CZ71: 1500 | DA71: =MIN(BX71*5%,1500) -> 1500 | DB71: =DA71-CZ71 -> 0 | DC71: 6971.42 | DD71: =MAX(ROUND(CA71*CM71-CZ71,2),0) -> 6971.42 | DE71: =DD71-DC71 -> 0 | DF71: 92303.09 | DG71: =SUM(AE71,AH71,AN71,AR71,AU71,AY71,BA71,BH71,BK71,BN71,BR71,BT71,BV71,-CG71,-CP71,-CT71,-CW71) -> 92303.09 | DH71: =DG71-DF71 -> 0 | DI71: 0 | DJ71: =IFERROR(VLOOKUP(D71,#REF!,2,0),0) -> 0 | DK71: =DJ71-DI71 -> 0 | DL71: 94126.9 | DM71: 1733577.3 | DN71: 7508.33 | DO71: 4026.9 | DP71: 0 | DQ71: 96626.9 | DR71: 28 | DS71: 0 | DT71: 2025-01-01 | DU71: 2025-12-31 | DV71: 2025-01-10 | DW71: 2025-02-10
A72: MSD Asia202502 | B72: MERCK SHARP & DOHME (ASIA) LIMITED | C72: MSD Asia | D72: 51423067 | E72: =VLOOKUP(D72,#REF!,1,0) -> #REF! | F72: So | G72: Man Sin | H72: =G72&" "&F72 -> Man Sin So | I72: =VLOOKUP(D72,#REF!,9,0) -> #REF! | J72: =I72=H72 -> #REF! | L72: Active | M72: 2022-02-14 | N72: =VLOOKUP(D72,#REF!,80,0) -> #REF! | O72: =N72-M72 -> #REF! | P72: HK Vaccine (DS) | Q72: =VLOOKUP(D72,#REF!,50,0) -> #REF! | R72: =Q72=P72 -> #REF! | S72: Business Development Manager | T72: =VLOOKUP(D72,#REF!,21,0) -> #REF! | U72: =T72=S72 -> #REF! | V72: 12630115 | W72: =VLOOKUP(D72,#REF!,51,0) -> #REF! | X72: =W72=V72 -> #REF! | Y72: 202502 | Z72: N | AA72: 3.04 | AB72: 51772 | AC72: =ROUND(VLOOKUP(D72,#REF!,59,0),0) -> #REF! | AD72: =AC72-AB72 -> #REF! | AE72: 51772 | AF72: =AB72 -> 51772 | AG72: =AF72-AE72 -> 0 | AH72: 0 | AK72: 0 | AN72: 0 | AO72: 2500 | AP72: =IFERROR(VLOOKUP('Feb for check'!D72,#REF!,15,0),0) -> 0 | AQ72: =AP72-AO72 -> -2500 | AR72: 2500 | AS72: =AO72 -> 2500 | AT72: =AS72-AR72 -> 0 | AU72: 0 | AW72: 0 | AY72: 0 | BA72: 0 | BB72: =IFERROR(VLOOKUP(D72,#REF!,2,0),0) -> 0 | BC72: =MAX(VLOOKUP(D72,#REF!,13,0)-VLOOKUP(D72,#REF!,14,0),0) -> #REF! | BD72: =IFERROR(VLOOKUP(D72,#REF!,3,0),0) -> 0 | BE72: =MAX(VLOOKUP(D72,#REF!,22,0)-VLOOKUP(D72,#REF!,23,0),0) -> #REF! | BF72: =BB72*BC72+BD72*BE72 -> #REF! | BG72: =BF72-BA72 -> #REF! | BH72: 0 | BK72: 0 | BL72: =ROUNDUP(DI72/(1-0.17)*0.17,0) -> 0 | BM72: =BL72-BK72 -> 0 | BN72: 0 | BR72: 0 | BT72: 0 | BV72: 0 | BX72: 54272 | BY72: =SUM(AE72,AH72,AN72,AR72,AU72,AY72,BA72,BH72,BK72,BN72,BR72,BT72) -> 54272 | BZ72: =BY72-BX72 -> 0 | CA72: 51772 | CB72: =SUM(AE72,AH72,BA72,BH72) -> 51772 | CC72: =CB72-CA72 -> 0 | CD72: 0 | CG72: 0 | CI72: 1784.2849 | CJ72: 0.05 | CL72: 0 | CM72: 0.1 | CN72: 0 | CO72: 0 | CP72: 0 | CR72: 0 | CT72: 1500 | CU72: =MIN(BX72*5%,1500) -> 1500 | CV72: =CU72-CT72 -> 0 | CW72: 2588.6 | CX72: =ROUND(CA72*CJ72,2) -> 2588.6 | CY72: =CX72-CW72 -> 0 | CZ72: 1500 | DA72: =MIN(BX72*5%,1500) -> 1500 | DB72: =DA72-CZ72 -> 0 | DC72: 3677.2 | DD72: =MAX(ROUND(CA72*CM72-CZ72,2),0) -> 3677.2 | DE72: =DD72-DC72 -> 0 | DF72: 50183.4 | DG72: =SUM(AE72,AH72,AN72,AR72,AU72,AY72,BA72,BH72,BK72,BN72,BR72,BT72,BV72,-CG72,-CP72,-CT72,-CW72) -> 50183.4 | DH72: =DG72-DF72 -> 0 | DI72: 0 | DJ72: =IFERROR(VLOOKUP(D72,#REF!,2,0),0) -> 0 | DK72: =DJ72-DI72 -> 0 | DL72: 51772 | DM72: 824639.93 | DN72: 4314.33 | DO72: 0 | DP72: 0 | DQ72: 54272 | DR72: 28 | DS72: 0 | DT72: 2025-01-01 | DU72: 2025-12-31 | DV72: 2025-01-10 | DW72: 2025-02-10
A73: MSD Asia202502 | B73: MERCK SHARP & DOHME (ASIA) LIMITED | C73: MSD Asia | D73: 51490077 | E73: =VLOOKUP(D73,#REF!,1,0) -> #REF! | F73: Wong | G73: Hoi Ki | H73: =G73&" "&F73 -> Hoi Ki Wong | I73: =VLOOKUP(D73,#REF!,9,0) -> #REF! | J73: =I73=H73 -> #REF! | K73: Hoiki | L73: Active | M73: 2024-05-16 | N73: =VLOOKUP(D73,#REF!,80,0) -> #REF! | O73: =N73-M73 -> #REF! | P73: CAS-HONG KONG | Q73: =VLOOKUP(D73,#REF!,50,0) -> #REF! | R73: =Q73=P73 -> #REF! | S73: Specialist - Consumer, Digital Activation, HHDDA- Asia Pacific | T73: =VLOOKUP(D73,#REF!,21,0) -> #REF! | U73: =T73=S73 -> #REF! | V73: 12630420 | W73: =VLOOKUP(D73,#REF!,51,0) -> #REF! | X73: =W73=V73 -> #REF! | Y73: 202502 | Z73: N | AA73: 0.79 | AB73: 40000 | AC73: =ROUND(VLOOKUP(D73,#REF!,59,0),0) -> #REF! | AD73: =AC73-AB73 -> #REF! | AE73: 40000 | AF73: =AB73 -> 40000 | AG73: =AF73-AE73 -> 0 | AH73: 0 | AK73: 0 | AN73: 0 | AO73: 0 | AP73: =IFERROR(VLOOKUP('Feb for check'!D73,#REF!,15,0),0) -> 0 | AQ73: =AP73-AO73 -> 0 | AR73: 0 | AS73: =AO73 -> 0 | AT73: =AS73-AR73 -> 0 | AU73: 0 | AW73: 0 | AY73: 0 | BA73: 0 | BB73: =IFERROR(VLOOKUP(D73,#REF!,2,0),0) -> 0 | BC73: =MAX(VLOOKUP(D73,#REF!,13,0)-VLOOKUP(D73,#REF!,14,0),0) -> #REF! | BD73: =IFERROR(VLOOKUP(D73,#REF!,3,0),0) -> 0 | BE73: =MAX(VLOOKUP(D73,#REF!,22,0)-VLOOKUP(D73,#REF!,23,0),0) -> #REF! | BF73: =BB73*BC73+BD73*BE73 -> #REF! | BG73: =BF73-BA73 -> #REF! | BH73: 0 | BK73: 55 | BL73: =ROUNDUP(DI73/(1-0.17)*0.17,0) -> 55 | BM73: =BL73-BK73 -> 0 | BN73: 0 | BR73: 0 | BT73: 0 | BV73: 0 | BX73: 40055 | BY73: =SUM(AE73,AH73,AN73,AR73,AU73,AY73,BA73,BH73,BK73,BN73,BR73,BT73) -> 40055 | BZ73: =BY73-BX73 -> 0 | CA73: 40000 | CB73: =SUM(AE73,AH73,BA73,BH73) -> 40000 | CC73: =CB73-CA73 -> 0 | CD73: 0 | CG73: 0 | CI73: 1315.0684 | CJ73: 0 | CL73: 0 | CM73: 0.075 | CN73: 0 | CO73: 0 | CP73: 0 | CR73: 0 | CT73: 1500 | CU73: =MIN(BX73*5%,1500) -> 1500 | CV73: =CU73-CT73 -> 0 | CW73: 0 | CX73: =ROUND(CA73*CJ73,2) -> 0 | CY73: =CX73-CW73 -> 0 | CZ73: 1500 | DA73: =MIN(BX73*5%,1500) -> 1500 | DB73: =DA73-CZ73 -> 0 | DC73: 1500 | DD73: =MAX(ROUND(CA73*CM73-CZ73,2),0) -> 1500 | DE73: =DD73-DC73 -> 0 | DF73: 38555 | DG73: =SUM(AE73,AH73,AN73,AR73,AU73,AY73,BA73,BH73,BK73,BN73,BR73,BT73,BV73,-CG73,-CP73,-CT73,-CW73) -> 38555 | DH73: =DG73-DF73 -> 0 | DI73: 268.1 | DJ73: =IFERROR(VLOOKUP(D73,#REF!,2,0),0) -> 0 | DK73: =DJ73-DI73 -> -268.1 | DL73: 40055 | DM73: 406233.89 | DN73: 3333.33 | DO73: 0 | DP73: 0 | DQ73: 40000 | DR73: 28 | DS73: 0 | DT73: 2025-01-01 | DU73: 2025-12-31 | DV73: 2025-01-10 | DW73: 2025-02-10
A74: MSD Asia202502 | B74: MERCK SHARP & DOHME (ASIA) LIMITED | C74: MSD Asia | D74: 33900118 | E74: =VLOOKUP(D74,#REF!,1,0) -> #REF! | F74: Chuk | G74: Ling Cheung Andrew | H74: =G74&" "&F74 -> Ling Cheung Andrew Chuk | I74: =VLOOKUP(D74,#REF!,9,0) -> #REF! | J74: =I74=H74 -> #REF! | K74: Andrew | L74: Active | M74: 1994-05-01 | N74: =VLOOKUP(D74,#REF!,80,0) -> #REF! | O74: =N74-M74 -> #REF! | P74: Legal - AP | Q74: =VLOOKUP(D74,#REF!,50,0) -> #REF! | R74: =Q74=P74 -> #REF! | S74: Sr. Counsel | T74: =VLOOKUP(D74,#REF!,21,0) -> #REF! | U74: =T74=S74 -> #REF! | V74: 12630019 | W74: =VLOOKUP(D74,#REF!,51,0) -> #REF! | X74: =W74=V74 -> #REF! | Y74: 202502 | Z74: N | AA74: 30.83 | AB74: 252892 | AC74: =ROUND(VLOOKUP(D74,#REF!,59,0),0) -> #REF! | AD74: =AC74-AB74 -> #REF! | AE74: 252892 | AF74: =AB74 -> 252892 | AG74: =AF74-AE74 -> 0 | AH74: 0 | AK74: 0 | AN74: 0 | AO74: 10000 | AP74: 10000 | AQ74: =AP74-AO74 -> 0 | AR74: 10000 | AS74: =AO74 -> 10000 | AT74: =AS74-AR74 -> 0 | AU74: 0 | AW74: 40000 | AX74: Andrew Monthly 40000 | AY74: 40000 | AZ74: =AW74=AY74 -> TRUE | BA74: 23905.55 | BB74: =IFERROR(VLOOKUP(D74,#REF!,2,0),0) -> 0 | BC74: =MAX(VLOOKUP(D74,#REF!,13,0)-VLOOKUP(D74,#REF!,14,0),0) -> #REF! | BD74: =IFERROR(VLOOKUP(D74,#REF!,3,0),0) -> 0 | BE74: =MAX(VLOOKUP(D74,#REF!,22,0)-VLOOKUP(D74,#REF!,23,0),0) -> #REF! | BF74: =BB74*BC74+BD74*BE74 -> #REF! | BG74: =BF74-BA74 -> #REF! | BH74: 0 | BK74: 0 | BL74: =ROUNDUP(DI74/(1-0.17)*0.17,0) -> 0 | BM74: =BL74-BK74 -> 0 | BN74: 0 | BR74: 0 | BT74: 0 | BV74: 0 | BX74: 0 | CA74: 0 | CD74: 252892 | CE74: =AE74 -> 252892 | CF74: =CE74-CD74 -> 0 | CG74: 962 | CH74: =VLOOKUP(D74,#REF!,3,0) -> #REF! | CI74: 9958.0931 | CJ74: 0 | CL74: 0 | CM74: 0 | CN74: 0.05 | CO74: 0.061 | CP74: 12644.6 | CQ74: =ROUND(CN74*CD74,2) -> 12644.6 | CR74: 15426.41 | CS74: =ROUND(CD74*CO74,2) -> 15426.41 | CT74: 0 | CW74: 0 | CX74: =ROUND(CA74*CJ74,2) -> 0 | CY74: =CX74-CW74 -> 0 | CZ74: 0 | DA74: =MIN(BX74*5%,1500) -> 0 | DB74: =DA74-CZ74 -> 0 | DC74: 0 | DD74: =MAX(ROUND(CA74*CM74-CZ74,2),0) -> 0 | DE74: =DD74-DC74 -> 0 | DF74: 313190.95 | DG74: =SUM(AE74,AH74,AN74,AR74,AU74,AY74,BA74,BH74,BK74,BN74,BR74,BT74,BV74,-CG74,-CP74,-CT74,-CW74) -> 313190.95 | DH74: =DG74-DF74 -> 0 | DI74: 0 | DJ74: =IFERROR(VLOOKUP(D74,#REF!,2,0),0) -> 0 | DK74: =DJ74-DI74 -> 0 | DL74: 315835.55 | DM74: 5622562.9 | DN74: 21074.33 | DO74: 23905.55 | DP74: 224.57 | DQ74: 326797.55 | DR74: 28 | DS74: 0 | DT74: 2025-01-01 | DU74: 2025-12-31 | DV74: 2025-01-10 | DW74: 2025-02-10
A75: MSD Asia202502 | B75: MERCK SHARP & DOHME (ASIA) LIMITED | C75: MSD Asia | D75: 51342433 | E75: =VLOOKUP(D75,#REF!,1,0) -> #REF! | F75: Tse | G75: Wai Fan | H75: =G75&" "&F75 -> Wai Fan Tse | I75: =VLOOKUP(D75,#REF!,9,0) -> #REF! | J75: =I75=H75 -> #REF! | K75: Tracy | L75: Active | M75: 2022-07-12 | N75: =VLOOKUP(D75,#REF!,80,0) -> #REF! | O75: =N75-M75 -> #REF! | P75: MRL HKG GCTO | Q75: =VLOOKUP(D75,#REF!,50,0) -> #REF! | R75: =Q75=P75 -> #REF! | S75: aCRM | T75: =VLOOKUP(D75,#REF!,21,0) -> #REF! | U75: =T75=S75 -> #REF! | V75: 12630167 | W75: =VLOOKUP(D75,#REF!,51,0) -> #REF! | X75: =W75=V75 -> #REF! | Y75: 202502 | Z75: N | AA75: 2.64 | AB75: 56550 | AC75: =ROUND(VLOOKUP(D75,#REF!,59,0),0) -> #REF! | AD75: =AC75-AB75 -> #REF! | AE75: 56550 | AF75: =AB75 -> 56550 | AG75: =AF75-AE75 -> 0 | AH75: 0 | AK75: 0 | AN75: 0 | AO75: 0 | AP75: =IFERROR(VLOOKUP('Feb for check'!D75,#REF!,15,0),0) -> 0 | AQ75: =AP75-AO75 -> 0 | AR75: 0 | AS75: =AO75 -> 0 | AT75: =AS75-AR75 -> 0 | AU75: 0 | AW75: 0 | AY75: 0 | BA75: 0 | BB75: =IFERROR(VLOOKUP(D75,#REF!,2,0),0) -> 0 | BC75: =MAX(VLOOKUP(D75,#REF!,13,0)-VLOOKUP(D75,#REF!,14,0),0) -> #REF! | BD75: =IFERROR(VLOOKUP(D75,#REF!,3,0),0) -> 0 | BE75: =MAX(VLOOKUP(D75,#REF!,22,0)-VLOOKUP(D75,#REF!,23,0),0) -> #REF! | BF75: =BB75*BC75+BD75*BE75 -> #REF! | BG75: =BF75-BA75 -> #REF! | BH75: 0 | BK75: 0 | BL75: =ROUNDUP(DI75/(1-0.17)*0.17,0) -> 0 | BM75: =BL75-BK75 -> 0 | BN75: 0 | BR75: 0 | BT75: 0 | BV75: 0 | BX75: 56550 | BY75: =SUM(AE75,AH75,AN75,AR75,AU75,AY75,BA75,BH75,BK75,BN75,BR75,BT75) -> 56550 | BZ75: =BY75-BX75 -> 0 | CA75: 56550 | CB75: =SUM(AE75,AH75,BA75,BH75) -> 56550 | CC75: =CB75-CA75 -> 0 | CD75: 0 | CG75: 0 | CI75: 1859.178 | CJ75: 0 | CL75: 0 | CM75: 0.075 | CN75: 0 | CO75: 0 | CP75: 0 | CR75: 0 | CT75: 1500 | CU75: =MIN(BX75*5%,1500) -> 1500 | CV75: =CU75-CT75 -> 0 | CW75: 0 | CX75: =ROUND(CA75*CJ75,2) -> 0 | CY75: =CX75-CW75 -> 0 | CZ75: 1500 | DA75: =MIN(BX75*5%,1500) -> 1500 | DB75: =DA75-CZ75 -> 0 | DC75: 2741.25 | DD75: =MAX(ROUND(CA75*CM75-CZ75,2),0) -> 2741.25 | DE75: =DD75-DC75 -> 0 | DF75: 55050 | DG75: =SUM(AE75,AH75,AN75,AR75,AU75,AY75,BA75,BH75,BK75,BN75,BR75,BT75,BV75,-CG75,-CP75,-CT75,-CW75) -> 55050 | DH75: =DG75-DF75 -> 0 | DI75: 0 | DJ75: =IFERROR(VLOOKUP(D75,#REF!,2,0),0) -> 0 | DK75: =DJ75-DI75 -> 0 | DL75: 56550 | DM75: 947422.48 | DN75: 4712.5 | DO75: 0 | DP75: 0 | DQ75: 56550 | DR75: 28 | DS75: 0 | DT75: 2025-01-01 | DU75: 2025-12-31 | DV75: 2025-01-10 | DW75: 2025-02-10
A76: MSD Asia202502 | B76: MERCK SHARP & DOHME (ASIA) LIMITED | C76: MSD Asia | D76: 51402209 | E76: =VLOOKUP(D76,#REF!,1,0) -> #REF! | F76: Fung | G76: Tsan Chung | H76: =G76&" "&F76 -> Tsan Chung Fung | I76: =VLOOKUP(D76,#REF!,9,0) -> #REF! | J76: =I76=H76 -> #REF! | K76: Joe Fung | L76: Active | M76: 2021-07-21 | N76: =VLOOKUP(D76,#REF!,80,0) -> #REF! | O76: =N76-M76 -> #REF! | P76: HK Vaccine (DS) | Q76: =VLOOKUP(D76,#REF!,50,0) -> #REF! | R76: =Q76=P76 -> #REF! | S76: Senior Professional Sales Representative | T76: =VLOOKUP(D76,#REF!,21,0) -> #REF! | U76: =T76=S76 -> #REF! | V76: 12630115 | W76: =VLOOKUP(D76,#REF!,51,0) -> #REF! | X76: =W76=V76 -> #REF! | Y76: 202502 | Z76: N | AA76: 3.61 | AB76: 28906 | AC76: =ROUND(VLOOKUP(D76,#REF!,59,0),0) -> #REF! | AD76: =AC76-AB76 -> #REF! | AE76: 28906 | AF76: =AB76 -> 28906 | AG76: =AF76-AE76 -> 0 | AH76: 0 | AK76: 0 | AN76: 0 | AO76: 2500 | AP76: =IFERROR(VLOOKUP('Feb for check'!D76,#REF!,15,0),0) -> 0 | AQ76: =AP76-AO76 -> -2500 | AR76: 2500 | AS76: =AO76 -> 2500 | AT76: =AS76-AR76 -> 0 | AU76: 0 | AW76: 0 | AY76: 0 | BA76: 0 | BB76: =IFERROR(VLOOKUP(D76,#REF!,2,0),0) -> 0 | BC76: =MAX(VLOOKUP(D76,#REF!,13,0)-VLOOKUP(D76,#REF!,14,0),0) -> #REF! | BD76: =IFERROR(VLOOKUP(D76,#REF!,3,0),0) -> 0 | BE76: =MAX(VLOOKUP(D76,#REF!,22,0)-VLOOKUP(D76,#REF!,23,0),0) -> #REF! | BF76: =BB76*BC76+BD76*BE76 -> #REF! | BG76: =BF76-BA76 -> #REF! | BH76: 0 | BK76: 0 | BL76: =ROUNDUP(DI76/(1-0.17)*0.17,0) -> 0 | BM76: =BL76-BK76 -> 0 | BN76: 0 | BR76: 0 | BT76: 0 | BV76: 0 | BX76: 31406 | BY76: =SUM(AE76,AH76,AN76,AR76,AU76,AY76,BA76,BH76,BK76,BN76,BR76,BT76) -> 31406 | BZ76: =BY76-BX76 -> 0 | CA76: 28906 | CB76: =SUM(AE76,AH76,BA76,BH76) -> 28906 | CC76: =CB76-CA76 -> 0 | CD76: 0 | CG76: 0 | CI76: 1032.526 | CJ76: 0 | CL76: 0 | CM76: 0.075 | CN76: 0 | CO76: 0 | CP76: 0 | CR76: 0 | CT76: 1500 | CU76: =MIN(BX76*5%,1500) -> 1500 | CV76: =CU76-CT76 -> 0 | CW76: 0 | CX76: =ROUND(CA76*CJ76,2) -> 0 | CY76: =CX76-CW76 -> 0 | CZ76: 1500 | DA76: =MIN(BX76*5%,1500) -> 1500 | DB76: =DA76-CZ76 -> 0 | DC76: 667.95 | DD76: =MAX(ROUND(CA76*CM76-CZ76,2),0) -> 667.95 | DE76: =DD76-DC76 -> 0 | DF76: 29906 | DG76: =SUM(AE76,AH76,AN76,AR76,AU76,AY76,BA76,BH76,BK76,BN76,BR76,BT76,BV76,-CG76,-CP76,-CT76,-CW76) -> 29906 | DH76: =DG76-DF76 -> 0 | DI76: 0 | DJ76: =IFERROR(VLOOKUP(D76,#REF!,2,0),0) -> 0 | DK76: =DJ76-DI76 -> 0 | DL76: 28906 | DM76: 584158.36 | DN76: 2408.83 | DO76: 0 | DP76: 0 | DQ76: 31406 | DR76: 28 | DS76: 0 | DT76: 2025-01-01 | DU76: 2025-12-31 | DV76: 2025-01-10 | DW76: 2025-02-10
